Workbook
Name V_Mois: DATA_VENTES!$A$2:$A$9516
Name V_Ex: DATA_VENTES!$B$2:$B$9516
Name V_Mag: DATA_VENTES!$C$2:$C$9516
Name V_Reg: DATA_VENTES!$D$2:$D$9516
Name V_Canal: DATA_VENTES!$E$2:$E$9516
Name V_Jours: DATA_VENTES!$F$2:$F$9516
Name V_Tickets: DATA_VENTES!$G$2:$G$9516
Name V_Articles: DATA_VENTES!$H$2:$H$9516
Name V_CABrut: DATA_VENTES!$I$2:$I$9516
Name V_Remises: DATA_VENTES!$J$2:$J$9516
Name V_CANet: DATA_VENTES!$K$2:$K$9516
Name V_Cout: DATA_VENTES!$L$2:$L$9516
Name B_Mois: DATA_BUDGET!$A$2:$A$2881
Name B_Ex: DATA_BUDGET!$B$2:$B$2881
Name B_Mag: DATA_BUDGET!$C$2:$C$2881
Name B_Reg: DATA_BUDGET!$D$2:$D$2881
Name B_Budget: DATA_BUDGET!$E$2:$E$2881
Name S_Mois: DATA_STOCKS!$A$2:$A$2831
Name S_Ex: DATA_STOCKS!$B$2:$B$2831
Name S_Mag: DATA_STOCKS!$C$2:$C$2831
Name S_Sorties: DATA_STOCKS!$D$2:$D$2831
Name S_Pertes: DATA_STOCKS!$E$2:$E$2831
Name A_Mois: DATA_ACHATS!$A$2:$A$333
Name A_Ex: DATA_ACHATS!$B$2:$B$333
Name A_Fourn: DATA_ACHATS!$C$2:$C$333
Name A_Lignes: DATA_ACHATS!$D$2:$D$333
Name A_Livrees: DATA_ACHATS!$E$2:$E$333
Name A_Retard: DATA_ACHATS!$F$2:$F$333
Name A_EnRetard: DATA_ACHATS!$G$2:$G$333
Name A_Montant: DATA_ACHATS!$H$2:$H$333
Name AM_Ex: DATA_ACHATS_MAG!$A$2:$A$239
Name AM_Mag: DATA_ACHATS_MAG!$B$2:$B$239
Name AM_Reel: DATA_ACHATS_MAG!$C$2:$C$239
Name AM_Reseau: DATA_ACHATS_MAG!$D$2:$D$239
Name R_Mois: DATA_RH!$A$2:$A$2831
Name R_Ex: DATA_RH!$B$2:$B$2831
Name R_Mag: DATA_RH!$C$2:$C$2831
Name R_Salaries: DATA_RH!$D$2:$D$2831
Name R_Heures: DATA_RH!$E$2:$E$2831
Name R_HS: DATA_RH!$F$2:$F$2831
Name R_Abs: DATA_RH!$G$2:$G$2831
Name X_Ex: DATA_MIX!$A$2:$A$9993
Name X_Mag: DATA_MIX!$B$2:$B$9993
Name X_Prod: DATA_MIX!$C$2:$C$9993
Name X_Qte: DATA_MIX!$D$2:$D$9993
Name X_CA: DATA_MIX!$E$2:$E$9993
Name X_Cout: DATA_MIX!$F$2:$F$9993
Name M_Code: REF_MAGASINS!$A$2:$A$121
Name M_Nom: REF_MAGASINS!$B$2:$B$121
Name M_Ville: REF_MAGASINS!$C$2:$C$121
Name M_Region: REF_MAGASINS!$D$2:$D$121
Name M_Type: REF_MAGASINS!$E$2:$E$121
Name M_Statut: REF_MAGASINS!$F$2:$F$121
Name M_Surface: REF_MAGASINS!$G$2:$G$121
Name M_Places: REF_MAGASINS!$H$2:$H$121
Name M_Drive: REF_MAGASINS!$I$2:$I$121
Name M_Franchise: REF_MAGASINS!$J$2:$J$121
Name M_Ouv: REF_MAGASINS!$K$2:$K$121
Name M_Ferm: REF_MAGASINS!$L$2:$L$121
Name P_Code: REF_PRODUITS!$A$2:$A$43

Sheet DASHBOARD
B1: HORIZON_CONTRAT — PILOTAGE RÉSEAU
B2: ="Exercice "&Exercice_Courant&" (sept.–août) · comparatif "&Exercice_Precedent&" · "&D_Nb_Magasins&" points de vente dans le filtre"
B4: Région | C4: Toutes | G4: Canal | H4: Tous | L4: Les deux filtres pilotent les cartes, la courbe et le classement. Le budget n'existe pas par canal.
B6: CA NET HT | E6: CROISSANCE COMPARABLE | H6: TAUX DE MARGE BRUTE | K6: TICKETS | N6: TICKET MOYEN HT | Q6: ATTEINTE BUDGET 2026
B7: =D_CA_N | E7: =D_Delta_Comp | H7: =D_Taux_N | K7: =D_Tickets_N | N7: =D_TM_N | Q7: =IF(Canal_Filtre="Tous",D_Atteinte,"n/a")
B9: =IF(D_Delta_CA>=0,"+","")&FIXED(D_Delta_CA*100,1)&" % vs N-1" | E9: =D_Nb_Comparables&" magasins comparables" | H9: =IF(D_Delta_Taux_pt>=0,"+","")&FIXED(D_Delta_Taux_pt,2)&" pt vs N-1" | K9: =IF(D_Delta_Tickets>=0,"+","")&FIXED(D_Delta_Tickets*100,1)&" % vs N-1" | N9: =IF(D_Delta_TM>=0,"+","")&FIXED(D_Delta_TM*100,1)&" % — dont prix +"&FIXED(Hausse_Tarifaire*100,1)&" %" | Q9: =IF(Canal_Filtre="Tous",D_Nb_Sous_Objectif&" magasins sous "&FIXED(Seuil_Atteinte_Budget*100,0)&" %","Budget non ventilé par canal")
B30: Magasins sous surveillance — taux de marge les plus faibles du filtre | O30: Constat à instruire
B31: Code | D31: Ville | F31: Région | H31: CA net | J31: Taux de marge | L31: Écart réseau | O31: =D_Nb_Sous_Seuil&" magasin(s) sous le seuil d'alerte de "&FIXED(D_Seuil_Taux_Alerte*100,2)&" % (réseau − "&FIXED(Seuil_Alerte_Marge_Pt*100,0)&" pt). Le plus bas, "&CALC_DASH!D70&" ("&CALC_DASH!E70&"), est à "&FIXED(CALC_DASH!H70*100,2)&" %, soit "&FIXED(-CALC_DASH!I70,2)&" pt sous le réseau. À croiser avec les pertes de stock et les prix d'achat : voir FICHE_MAGASIN, bloc Diagnostic."
B32: =CALC_DASH!D70 | D32: =CALC_DASH!E70 | F32: =CALC_DASH!F70 | H32: =CALC_DASH!G70 | J32: =CALC_DASH!H70 | L32: =CALC_DASH!I70
B33: =CALC_DASH!D71 | D33: =CALC_DASH!E71 | F33: =CALC_DASH!F71 | H33: =CALC_DASH!G71 | J33: =CALC_DASH!H71 | L33: =CALC_DASH!I71
B34: =CALC_DASH!D72 | D34: =CALC_DASH!E72 | F34: =CALC_DASH!F72 | H34: =CALC_DASH!G72 | J34: =CALC_DASH!H72 | L34: =CALC_DASH!I72
B35: =CALC_DASH!D73 | D35: =CALC_DASH!E73 | F35: =CALC_DASH!F73 | H35: =CALC_DASH!G73 | J35: =CALC_DASH!H73 | L35: =CALC_DASH!I73
B36: =CALC_DASH!D74 | D36: =CALC_DASH!E74 | F36: =CALC_DASH!F74 | H36: =CALC_DASH!G74 | J36: =CALC_DASH!H74 | L36: =CALC_DASH!I74
B37: =CALC_DASH!D75 | D37: =CALC_DASH!E75 | F37: =CALC_DASH!F75 | H37: =CALC_DASH!G75 | J37: =CALC_DASH!H75 | L37: =CALC_DASH!I75
B39: ="Seuil d'alerte : taux de marge du réseau ("&FIXED(D_Taux_Reseau*100,2)&" %) moins "&FIXED(Seuil_Alerte_Marge_Pt*100,0)&" pt. Barres de données à échelle fixe 55 %–72 % pour rester comparables d'un filtre à l'autre."

Sheet FICHE_MAGASIN
B1: FICHE MAGASIN
B2: ="Exercice "&Exercice_Courant&" — toutes les valeurs sont des formules pilotées par la cellule Mag_Selectionne (E4)"
B4: Région | C4: Sud-Est | E4: HC-115 | F4: =IF(F_Valide,INDEX(M_Ville,F_Ref),"") | H4: =IF(F_Valide,"","Sélectionne un magasin de la région "&Region_Fiche&" dans la liste en E4.")
B6: =IF(F_Valide,INDEX(M_Ville,F_Ref)&" — "&INDEX(M_Type,F_Ref),"") | G6: CA NET HT | I6: TAUX DE MARGE | K6: TICKETS | M6: TICKET MOYEN HT | O6: ATTEINTE BUDGET 2026
G7: =IF(F_Valide,INDEX(CM_CA_Net_N,F_Ligne),"") | I7: =IF(F_Valide,INDEX(CM_Taux_Marge_N,F_Ligne),"") | K7: =IF(F_Valide,INDEX(CM_Tickets_N,F_Ligne),"") | M7: =IF(F_Valide,INDEX(CM_Ticket_Moyen_N,F_Ligne),"") | O7: =IF(F_Valide,INDEX(CM_Atteinte_Budget,F_Ligne),"")
B8: Code | C8: =IF(F_Valide,Mag_Selectionne,"")
B9: Nom | C9: =IF(F_Valide,INDEX(M_Nom,F_Ref),"") | G9: =IF(F_Valide,IF(ISNUMBER(INDEX(CM_Delta_CA,F_Ligne)),IF(INDEX(CM_Delta_CA,F_Ligne)>=0,"+","")&FIXED(INDEX(CM_Delta_CA,F_Ligne)*100,1)&" % vs N-1","ouvert en cours de N-1"),"") | I9: =IF(F_Valide,IF(INDEX(CM_Taux_Marge_N,F_Ligne)>=D_Taux_Reseau,"+","")&FIXED((INDEX(CM_Taux_Marge_N,F_Ligne)-D_Taux_Reseau)*100,2)&" pt vs réseau","") | K9: =IF(F_Valide,FIXED(INDEX(CM_Tickets_N,F_Ligne)/INDEX(CM_Jours_Ouverts_N,F_Ligne),0)&" par jour ouvert","") | M9: =IF(F_Valide,"réseau : "&FIXED(D_TM_Reseau,2)&" €","") | O9: =IF(F_Valide,IF(INDEX(CM_Reel_2026,F_Ligne)>=INDEX(CM_Budget_2026,F_Ligne),"+","")&FIXED((INDEX(CM_Reel_2026,F_Ligne)-INDEX(CM_Budget_2026,F_Ligne))/1000,0)&" k€ sur janv.–août","")
B10: Région | C10: =IF(F_Valide,INDEX(M_Region,F_Ref),"")
B11: Statut | C11: =IF(F_Valide,INDEX(M_Statut,F_Ref),"") | G11: Position dans le réseau (rang sur l'ensemble des magasins)
B12: Surface | C12: =IF(F_Valide,INDEX(M_Surface,F_Ref),"") | G12: Taux de marge | J12: CA net | M12: Ticket moyen | P12: Perte de stock
B13: Drive | C13: =IF(F_Valide,INDEX(M_Drive,F_Ref),"") | G13: =IF(F_Valide,"rang "&INDEX(CM_Rang_Marge,F_Ligne)&"/"&COUNT(CM_Rang_Marge),"") | J13: =IF(F_Valide,"rang "&INDEX(CM_Rang_CA,F_Ligne)&"/"&COUNT(CM_Rang_CA),"") | M13: =IF(F_Valide,"rang "&INDEX(CM_Rang_Ticket_Moyen,F_Ligne)&"/"&COUNT(CM_Rang_Ticket_Moyen),"") | P13: =IF(F_Valide,"rang "&INDEX(CM_Rang_Perte,F_Ligne)&"/"&COUNT(CM_Rang_Perte),"")
B14: Franchisé | C14: =IF(F_Valide,INDEX(M_Franchise,F_Ref),"") | G14: Rang 1 = meilleur : taux, CA et ticket moyen les plus élevés, taux de perte le plus faible.
B15: Ouverture | C15: =IF(F_Valide,INDEX(M_Ouv,F_Ref),"")
B16: Fermeture | C16: =IF(F_Valide,IF(INDEX(M_Ferm,F_Ref)="","—",INDEX(M_Ferm,F_Ref)),"") | G16: CA net mensuel (barres, k€) et taux de marge (courbe, %)
B19: Top 6 produits — CA et marge
B20: Produit | D20: CA net | E20: Marge
B21: =IF(F_Valide,CALC_FICHE!D73,"") | D21: =IF(F_Valide,CALC_FICHE!F73,"") | E21: =IF(F_Valide,CALC_FICHE!G73,"")
B22: =IF(F_Valide,CALC_FICHE!D74,"") | D22: =IF(F_Valide,CALC_FICHE!F74,"") | E22: =IF(F_Valide,CALC_FICHE!G74,"")
B23: =IF(F_Valide,CALC_FICHE!D75,"") | D23: =IF(F_Valide,CALC_FICHE!F75,"") | E23: =IF(F_Valide,CALC_FICHE!G75,"")
B24: =IF(F_Valide,CALC_FICHE!D76,"") | D24: =IF(F_Valide,CALC_FICHE!F76,"") | E24: =IF(F_Valide,CALC_FICHE!G76,"")
B25: =IF(F_Valide,CALC_FICHE!D77,"") | D25: =IF(F_Valide,CALC_FICHE!F77,"") | E25: =IF(F_Valide,CALC_FICHE!G77,"")
B26: =IF(F_Valide,CALC_FICHE!D78,"") | D26: =IF(F_Valide,CALC_FICHE!F78,"") | E26: =IF(F_Valide,CALC_FICHE!G78,"")
B27: Rouge sous 58 %, vert au-dessus de 65 %.
B29: Ressources humaines (exercice)
B30: Effectif moyen | E30: =IF(F_Valide,INDEX(CM_Effectif_Moyen_N,F_Ligne),"")
B31: Absence / salarié / mois | E31: =IF(F_Valide,INDEX(CM_Absence_Sal_Mois_N,F_Ligne),"")
B32: Heures sup. / salarié / mois | E32: =IF(F_Valide,INDEX(CM_HS_Sal_Mois_N,F_Ligne),"")
B33: CA net / heure travaillée | E33: =IF(F_Valide,INDEX(CM_CA_par_Heure_N,F_Ligne),"") | G33: Diagnostic automatique — hypothèses testées
G34: Hypothèse | J34: Mesure du magasin | L34: Référence réseau | N34: Verdict
G35: Pertes de stock | J35: =IF(F_Valide,INDEX(CM_Taux_Perte_N,F_Ligne),"") | L35: ="médiane "&FIXED(D_Mediane_Perte_N*100,2)&" %" | N35: =IF(F_Valide,IF(INDEX(CM_Taux_Perte_N,F_Ligne)<=Seuil_Perte_Multiple_Mediane*D_Mediane_Perte_N,"écarté","à instruire"),"")
G36: Prix d'achat fournisseurs | J36: =IF(F_Valide,INDEX(CM_Indice_Prix_Achat,F_Ligne),"") | L36: ="tolérance ±"&FIXED(Tolerance_Prix_Achat*100,0)&" %" | N36: =IF(F_Valide,IF(ABS(INDEX(CM_Indice_Prix_Achat,F_Ligne))<=Tolerance_Prix_Achat,"écarté","à instruire"),"")
G37: Mix canal (part livraison) | J37: =IF(F_Valide,INDEX(CM_Part_Livraison_N,F_Ligne),"") | L37: ="réseau "&FIXED(D_Part_Livraison_Reseau*100,1)&" %" | N37: =IF(F_Valide,IF(ABS(INDEX(CM_Part_Livraison_N,F_Ligne)-D_Part_Livraison_Reseau)<=Tolerance_Mix_Livraison,"écarté","à instruire"),"")
G38: Coût matière consommé | J38: =IF(F_Valide,F_Pente,"") | L38: ="seuil d'alerte "&FIXED(D_Seuil_Taux_Alerte*100,2)&" %" | N38: =IF(F_Valide,IF(INDEX(CM_Taux_Marge_N,F_Ligne)<D_Seuil_Taux_Alerte,"à auditer","conforme"),"")
G40: =IF(NOT(F_Valide),"",IF(INDEX(CM_Taux_Marge_N,F_Ligne)>=D_Seuil_Taux_Alerte,"Taux de marge conforme : "&FIXED(INDEX(CM_Taux_Marge_N,F_Ligne)*100,2)&" % contre "&FIXED(D_Taux_Reseau*100,2)&" % pour le réseau. Pas d'action sur la marge.",IF(AND(N35="écarté",N36="écarté",N37="écarté"),"Le taux de marge est "&FIXED((D_Taux_Reseau-INDEX(CM_Taux_Marge_N,F_Ligne))*100,2)&" pt sous le réseau et recule de "&FIXED(-F_Pente,2)&" pt par mois. Pertes, prix d'achat et mix sont conformes : la dérive vient de la consommation en cuisine (grammages, offerts non enregistrés, démarque non déclarée). Demander un inventaire physique contradictoire et un relevé de grammages.","Le taux de marge est "&FIXED((D_Taux_Reseau-INDEX(CM_Taux_Marge_N,F_Ligne))*100,2)&" pt sous le réseau et au moins une cause externe est identifiée ci-dessus : la traiter avant d'auditer la cuisine.")))

Sheet ANALYSES
B1: ANALYSES — les sept constats du réseau
B2: Chaque bloc répond à une question. La phrase « Constat » est générée par formule : elle change si les données changent.
B4: 1. Quels magasins perdent de la marge ?
B5: ="Taux de marge sur la période A ("&CHOOSE(MONTH(Periode_A_Debut),"janv","févr","mars","avr","mai","juin","juil","août","sept","oct","nov","déc")&"–"&CHOOSE(MONTH(Periode_A_Fin),"janv","févr","mars","avr","mai","juin","juil","août","sept","oct","nov","déc")&" "&YEAR(Periode_A_Fin)&") contre la période B ("&CHOOSE(MONTH(Periode_B_Debut),"janv","févr","mars","avr","mai","juin","juil","août","sept","oct","nov","déc")&"–"&CHOOSE(MONTH(Periode_B_Fin),"janv","févr","mars","avr","mai","juin","juil","août","sept","oct","nov","déc")&" "&YEAR(Periode_B_Fin)&") — les 10 plus forts reculs."
B6: Rang | C6: Ville | D6: Code | E6: Région | F6: Type | G6: Taux A | H6: Taux B | I6: Écart | J6: En dérive
B7: 1 | C7: =INDEX(CM_Ville,MATCH(SMALL(CM_Cle_Derive,1),CM_Cle_Derive,0)) | D7: =INDEX(CM_Code_Magasin,MATCH(SMALL(CM_Cle_Derive,1),CM_Cle_Derive,0)) | E7: =INDEX(CM_Region,MATCH(SMALL(CM_Cle_Derive,1),CM_Cle_Derive,0)) | F7: =INDEX(CM_Type_Emplacement,MATCH(SMALL(CM_Cle_Derive,1),CM_Cle_Derive,0)) | G7: =INDEX(CM_Taux_Marge_A,MATCH(SMALL(CM_Cle_Derive,1),CM_Cle_Derive,0)) | H7: =INDEX(CM_Taux_Marge_B,MATCH(SMALL(CM_Cle_Derive,1),CM_Cle_Derive,0)) | I7: =INDEX(CM_Ecart_A_B_pt,MATCH(SMALL(CM_Cle_Derive,1),CM_Cle_Derive,0)) | J7: =IF(I7<=Seuil_Derive_Marge_Pt,"oui","non")
B8: 2 | C8: =INDEX(CM_Ville,MATCH(SMALL(CM_Cle_Derive,2),CM_Cle_Derive,0)) | D8: =INDEX(CM_Code_Magasin,MATCH(SMALL(CM_Cle_Derive,2),CM_Cle_Derive,0)) | E8: =INDEX(CM_Region,MATCH(SMALL(CM_Cle_Derive,2),CM_Cle_Derive,0)) | F8: =INDEX(CM_Type_Emplacement,MATCH(SMALL(CM_Cle_Derive,2),CM_Cle_Derive,0)) | G8: =INDEX(CM_Taux_Marge_A,MATCH(SMALL(CM_Cle_Derive,2),CM_Cle_Derive,0)) | H8: =INDEX(CM_Taux_Marge_B,MATCH(SMALL(CM_Cle_Derive,2),CM_Cle_Derive,0)) | I8: =INDEX(CM_Ecart_A_B_pt,MATCH(SMALL(CM_Cle_Derive,2),CM_Cle_Derive,0)) | J8: =IF(I8<=Seuil_Derive_Marge_Pt,"oui","non")
B9: 3 | C9: =INDEX(CM_Ville,MATCH(SMALL(CM_Cle_Derive,3),CM_Cle_Derive,0)) | D9: =INDEX(CM_Code_Magasin,MATCH(SMALL(CM_Cle_Derive,3),CM_Cle_Derive,0)) | E9: =INDEX(CM_Region,MATCH(SMALL(CM_Cle_Derive,3),CM_Cle_Derive,0)) | F9: =INDEX(CM_Type_Emplacement,MATCH(SMALL(CM_Cle_Derive,3),CM_Cle_Derive,0)) | G9: =INDEX(CM_Taux_Marge_A,MATCH(SMALL(CM_Cle_Derive,3),CM_Cle_Derive,0)) | H9: =INDEX(CM_Taux_Marge_B,MATCH(SMALL(CM_Cle_Derive,3),CM_Cle_Derive,0)) | I9: =INDEX(CM_Ecart_A_B_pt,MATCH(SMALL(CM_Cle_Derive,3),CM_Cle_Derive,0)) | J9: =IF(I9<=Seuil_Derive_Marge_Pt,"oui","non")
B10: 4 | C10: =INDEX(CM_Ville,MATCH(SMALL(CM_Cle_Derive,4),CM_Cle_Derive,0)) | D10: =INDEX(CM_Code_Magasin,MATCH(SMALL(CM_Cle_Derive,4),CM_Cle_Derive,0)) | E10: =INDEX(CM_Region,MATCH(SMALL(CM_Cle_Derive,4),CM_Cle_Derive,0)) | F10: =INDEX(CM_Type_Emplacement,MATCH(SMALL(CM_Cle_Derive,4),CM_Cle_Derive,0)) | G10: =INDEX(CM_Taux_Marge_A,MATCH(SMALL(CM_Cle_Derive,4),CM_Cle_Derive,0)) | H10: =INDEX(CM_Taux_Marge_B,MATCH(SMALL(CM_Cle_Derive,4),CM_Cle_Derive,0)) | I10: =INDEX(CM_Ecart_A_B_pt,MATCH(SMALL(CM_Cle_Derive,4),CM_Cle_Derive,0)) | J10: =IF(I10<=Seuil_Derive_Marge_Pt,"oui","non")
B11: 5 | C11: =INDEX(CM_Ville,MATCH(SMALL(CM_Cle_Derive,5),CM_Cle_Derive,0)) | D11: =INDEX(CM_Code_Magasin,MATCH(SMALL(CM_Cle_Derive,5),CM_Cle_Derive,0)) | E11: =INDEX(CM_Region,MATCH(SMALL(CM_Cle_Derive,5),CM_Cle_Derive,0)) | F11: =INDEX(CM_Type_Emplacement,MATCH(SMALL(CM_Cle_Derive,5),CM_Cle_Derive,0)) | G11: =INDEX(CM_Taux_Marge_A,MATCH(SMALL(CM_Cle_Derive,5),CM_Cle_Derive,0)) | H11: =INDEX(CM_Taux_Marge_B,MATCH(SMALL(CM_Cle_Derive,5),CM_Cle_Derive,0)) | I11: =INDEX(CM_Ecart_A_B_pt,MATCH(SMALL(CM_Cle_Derive,5),CM_Cle_Derive,0)) | J11: =IF(I11<=Seuil_Derive_Marge_Pt,"oui","non")
B12: 6 | C12: =INDEX(CM_Ville,MATCH(SMALL(CM_Cle_Derive,6),CM_Cle_Derive,0)) | D12: =INDEX(CM_Code_Magasin,MATCH(SMALL(CM_Cle_Derive,6),CM_Cle_Derive,0)) | E12: =INDEX(CM_Region,MATCH(SMALL(CM_Cle_Derive,6),CM_Cle_Derive,0)) | F12: =INDEX(CM_Type_Emplacement,MATCH(SMALL(CM_Cle_Derive,6),CM_Cle_Derive,0)) | G12: =INDEX(CM_Taux_Marge_A,MATCH(SMALL(CM_Cle_Derive,6),CM_Cle_Derive,0)) | H12: =INDEX(CM_Taux_Marge_B,MATCH(SMALL(CM_Cle_Derive,6),CM_Cle_Derive,0)) | I12: =INDEX(CM_Ecart_A_B_pt,MATCH(SMALL(CM_Cle_Derive,6),CM_Cle_Derive,0)) | J12: =IF(I12<=Seuil_Derive_Marge_Pt,"oui","non")
B13: 7 | C13: =INDEX(CM_Ville,MATCH(SMALL(CM_Cle_Derive,7),CM_Cle_Derive,0)) | D13: =INDEX(CM_Code_Magasin,MATCH(SMALL(CM_Cle_Derive,7),CM_Cle_Derive,0)) | E13: =INDEX(CM_Region,MATCH(SMALL(CM_Cle_Derive,7),CM_Cle_Derive,0)) | F13: =INDEX(CM_Type_Emplacement,MATCH(SMALL(CM_Cle_Derive,7),CM_Cle_Derive,0)) | G13: =INDEX(CM_Taux_Marge_A,MATCH(SMALL(CM_Cle_Derive,7),CM_Cle_Derive,0)) | H13: =INDEX(CM_Taux_Marge_B,MATCH(SMALL(CM_Cle_Derive,7),CM_Cle_Derive,0)) | I13: =INDEX(CM_Ecart_A_B_pt,MATCH(SMALL(CM_Cle_Derive,7),CM_Cle_Derive,0)) | J13: =IF(I13<=Seuil_Derive_Marge_Pt,"oui","non")
B14: 8 | C14: =INDEX(CM_Ville,MATCH(SMALL(CM_Cle_Derive,8),CM_Cle_Derive,0)) | D14: =INDEX(CM_Code_Magasin,MATCH(SMALL(CM_Cle_Derive,8),CM_Cle_Derive,0)) | E14: =INDEX(CM_Region,MATCH(SMALL(CM_Cle_Derive,8),CM_Cle_Derive,0)) | F14: =INDEX(CM_Type_Emplacement,MATCH(SMALL(CM_Cle_Derive,8),CM_Cle_Derive,0)) | G14: =INDEX(CM_Taux_Marge_A,MATCH(SMALL(CM_Cle_Derive,8),CM_Cle_Derive,0)) | H14: =INDEX(CM_Taux_Marge_B,MATCH(SMALL(CM_Cle_Derive,8),CM_Cle_Derive,0)) | I14: =INDEX(CM_Ecart_A_B_pt,MATCH(SMALL(CM_Cle_Derive,8),CM_Cle_Derive,0)) | J14: =IF(I14<=Seuil_Derive_Marge_Pt,"oui","non")
B15: 9 | C15: =INDEX(CM_Ville,MATCH(SMALL(CM_Cle_Derive,9),CM_Cle_Derive,0)) | D15: =INDEX(CM_Code_Magasin,MATCH(SMALL(CM_Cle_Derive,9),CM_Cle_Derive,0)) | E15: =INDEX(CM_Region,MATCH(SMALL(CM_Cle_Derive,9),CM_Cle_Derive,0)) | F15: =INDEX(CM_Type_Emplacement,MATCH(SMALL(CM_Cle_Derive,9),CM_Cle_Derive,0)) | G15: =INDEX(CM_Taux_Marge_A,MATCH(SMALL(CM_Cle_Derive,9),CM_Cle_Derive,0)) | H15: =INDEX(CM_Taux_Marge_B,MATCH(SMALL(CM_Cle_Derive,9),CM_Cle_Derive,0)) | I15: =INDEX(CM_Ecart_A_B_pt,MATCH(SMALL(CM_Cle_Derive,9),CM_Cle_Derive,0)) | J15: =IF(I15<=Seuil_Derive_Marge_Pt,"oui","non")
B16: 10 | C16: =INDEX(CM_Ville,MATCH(SMALL(CM_Cle_Derive,10),CM_Cle_Derive,0)) | D16: =INDEX(CM_Code_Magasin,MATCH(SMALL(CM_Cle_Derive,10),CM_Cle_Derive,0)) | E16: =INDEX(CM_Region,MATCH(SMALL(CM_Cle_Derive,10),CM_Cle_Derive,0)) | F16: =INDEX(CM_Type_Emplacement,MATCH(SMALL(CM_Cle_Derive,10),CM_Cle_Derive,0)) | G16: =INDEX(CM_Taux_Marge_A,MATCH(SMALL(CM_Cle_Derive,10),CM_Cle_Derive,0)) | H16: =INDEX(CM_Taux_Marge_B,MATCH(SMALL(CM_Cle_Derive,10),CM_Cle_Derive,0)) | I16: =INDEX(CM_Ecart_A_B_pt,MATCH(SMALL(CM_Cle_Derive,10),CM_Cle_Derive,0)) | J16: =IF(I16<=Seuil_Derive_Marge_Pt,"oui","non")
B18: =COUNTIF(CM_En_Derive,1)&" magasins perdent plus de "&FIXED(-Seuil_Derive_Marge_Pt,0)&" pt de taux de marge, de "&FIXED(SMALL(CM_Ecart_A_B_pt,1),2)&" à "&FIXED(SMALL(CM_Ecart_A_B_pt,COUNTIF(CM_En_Derive,1)),2)&" pt. Le suivant est à "&FIXED(SMALL(CM_Ecart_A_B_pt,COUNTIF(CM_En_Derive,1)+1),2)&" pt : la coupure est franche, ces magasins forment un groupe."
B21: Contrôle du piège « Gare / Aéroport » : taux de marge de l'exercice par type, avec et sans les magasins en dérive.
C22: Type d'emplacement | D22: Nb magasins | E22: dont en dérive | F22: Taux — tous | G22: Taux — hors dérive
C23: Centre commercial | D23: =COUNTIF(CM_Type_Emplacement,C23) | E23: =COUNTIFS(CM_Type_Emplacement,C23,CM_En_Derive,1) | F23: =1-SUMIFS(CM_Cout_N,CM_Type_Emplacement,C23)/SUMIFS(CM_CA_Net_N,CM_Type_Emplacement,C23) | G23: =1-SUMIFS(CM_Cout_N,CM_Type_Emplacement,C23,CM_En_Derive,0)/SUMIFS(CM_CA_Net_N,CM_Type_Emplacement,C23,CM_En_Derive,0)
C24: Centre-ville | D24: =COUNTIF(CM_Type_Emplacement,C24) | E24: =COUNTIFS(CM_Type_Emplacement,C24,CM_En_Derive,1) | F24: =1-SUMIFS(CM_Cout_N,CM_Type_Emplacement,C24)/SUMIFS(CM_CA_Net_N,CM_Type_Emplacement,C24) | G24: =1-SUMIFS(CM_Cout_N,CM_Type_Emplacement,C24,CM_En_Derive,0)/SUMIFS(CM_CA_Net_N,CM_Type_Emplacement,C24,CM_En_Derive,0)
C25: Gare / Aéroport | D25: =COUNTIF(CM_Type_Emplacement,C25) | E25: =COUNTIFS(CM_Type_Emplacement,C25,CM_En_Derive,1) | F25: =1-SUMIFS(CM_Cout_N,CM_Type_Emplacement,C25)/SUMIFS(CM_CA_Net_N,CM_Type_Emplacement,C25) | G25: =1-SUMIFS(CM_Cout_N,CM_Type_Emplacement,C25,CM_En_Derive,0)/SUMIFS(CM_CA_Net_N,CM_Type_Emplacement,C25,CM_En_Derive,0)
C26: Périphérie | D26: =COUNTIF(CM_Type_Emplacement,C26) | E26: =COUNTIFS(CM_Type_Emplacement,C26,CM_En_Derive,1) | F26: =1-SUMIFS(CM_Cout_N,CM_Type_Emplacement,C26)/SUMIFS(CM_CA_Net_N,CM_Type_Emplacement,C26) | G26: =1-SUMIFS(CM_Cout_N,CM_Type_Emplacement,C26,CM_En_Derive,0)/SUMIFS(CM_CA_Net_N,CM_Type_Emplacement,C26,CM_En_Derive,0)
B28: ="Les magasins en dérive se concentrent en « Gare / Aéroport » ("&E25&" sur "&COUNTIF(CM_En_Derive,1)&"), dont le taux paraît plus faible ("&FIXED(F25*100,2)&" %). Hors magasins en dérive, les quatre types se situent entre "&FIXED(MIN(G23:G26)*100,2)&" % et "&FIXED(MAX(G23:G26)*100,2)&" % : l'emplacement n'explique rien, l'écart venait de ces magasins."
B32: 2. Le mix canal bouge-t-il ?
B33: Part du CA net par canal et par trimestre civil (2024 T3 = septembre seul ; 2026 T3 = juillet–août).
B34: Trimestre | C34: Début | D34: Fin | E34: Sur place | F34: À emporter | G34: Livraison | H34: Drive
B35: 2024 T3 | C35: 45474 | D35: 45536 | E35: =SUMIFS(V_CANet,V_Mois,">="&$C35,V_Mois,"<="&$D35,V_Canal,E$34)/SUMIFS(V_CANet,V_Mois,">="&$C35,V_Mois,"<="&$D35) | F35: =SUMIFS(V_CANet,V_Mois,">="&$C35,V_Mois,"<="&$D35,V_Canal,F$34)/SUMIFS(V_CANet,V_Mois,">="&$C35,V_Mois,"<="&$D35) | G35: =SUMIFS(V_CANet,V_Mois,">="&$C35,V_Mois,"<="&$D35,V_Canal,G$34)/SUMIFS(V_CANet,V_Mois,">="&$C35,V_Mois,"<="&$D35) | H35: =SUMIFS(V_CANet,V_Mois,">="&$C35,V_Mois,"<="&$D35,V_Canal,H$34)/SUMIFS(V_CANet,V_Mois,">="&$C35,V_Mois,"<="&$D35)
B36: 2024 T4 | C36: 45566 | D36: 45627 | E36: =SUMIFS(V_CANet,V_Mois,">="&$C36,V_Mois,"<="&$D36,V_Canal,E$34)/SUMIFS(V_CANet,V_Mois,">="&$C36,V_Mois,"<="&$D36) | F36: =SUMIFS(V_CANet,V_Mois,">="&$C36,V_Mois,"<="&$D36,V_Canal,F$34)/SUMIFS(V_CANet,V_Mois,">="&$C36,V_Mois,"<="&$D36) | G36: =SUMIFS(V_CANet,V_Mois,">="&$C36,V_Mois,"<="&$D36,V_Canal,G$34)/SUMIFS(V_CANet,V_Mois,">="&$C36,V_Mois,"<="&$D36) | H36: =SUMIFS(V_CANet,V_Mois,">="&$C36,V_Mois,"<="&$D36,V_Canal,H$34)/SUMIFS(V_CANet,V_Mois,">="&$C36,V_Mois,"<="&$D36)
B37: 2025 T1 | C37: 45658 | D37: 45717 | E37: =SUMIFS(V_CANet,V_Mois,">="&$C37,V_Mois,"<="&$D37,V_Canal,E$34)/SUMIFS(V_CANet,V_Mois,">="&$C37,V_Mois,"<="&$D37) | F37: =SUMIFS(V_CANet,V_Mois,">="&$C37,V_Mois,"<="&$D37,V_Canal,F$34)/SUMIFS(V_CANet,V_Mois,">="&$C37,V_Mois,"<="&$D37) | G37: =SUMIFS(V_CANet,V_Mois,">="&$C37,V_Mois,"<="&$D37,V_Canal,G$34)/SUMIFS(V_CANet,V_Mois,">="&$C37,V_Mois,"<="&$D37) | H37: =SUMIFS(V_CANet,V_Mois,">="&$C37,V_Mois,"<="&$D37,V_Canal,H$34)/SUMIFS(V_CANet,V_Mois,">="&$C37,V_Mois,"<="&$D37)
B38: 2025 T2 | C38: 45748 | D38: 45809 | E38: =SUMIFS(V_CANet,V_Mois,">="&$C38,V_Mois,"<="&$D38,V_Canal,E$34)/SUMIFS(V_CANet,V_Mois,">="&$C38,V_Mois,"<="&$D38) | F38: =SUMIFS(V_CANet,V_Mois,">="&$C38,V_Mois,"<="&$D38,V_Canal,F$34)/SUMIFS(V_CANet,V_Mois,">="&$C38,V_Mois,"<="&$D38) | G38: =SUMIFS(V_CANet,V_Mois,">="&$C38,V_Mois,"<="&$D38,V_Canal,G$34)/SUMIFS(V_CANet,V_Mois,">="&$C38,V_Mois,"<="&$D38) | H38: =SUMIFS(V_CANet,V_Mois,">="&$C38,V_Mois,"<="&$D38,V_Canal,H$34)/SUMIFS(V_CANet,V_Mois,">="&$C38,V_Mois,"<="&$D38)
B39: 2025 T3 | C39: 45839 | D39: 45901 | E39: =SUMIFS(V_CANet,V_Mois,">="&$C39,V_Mois,"<="&$D39,V_Canal,E$34)/SUMIFS(V_CANet,V_Mois,">="&$C39,V_Mois,"<="&$D39) | F39: =SUMIFS(V_CANet,V_Mois,">="&$C39,V_Mois,"<="&$D39,V_Canal,F$34)/SUMIFS(V_CANet,V_Mois,">="&$C39,V_Mois,"<="&$D39) | G39: =SUMIFS(V_CANet,V_Mois,">="&$C39,V_Mois,"<="&$D39,V_Canal,G$34)/SUMIFS(V_CANet,V_Mois,">="&$C39,V_Mois,"<="&$D39) | H39: =SUMIFS(V_CANet,V_Mois,">="&$C39,V_Mois,"<="&$D39,V_Canal,H$34)/SUMIFS(V_CANet,V_Mois,">="&$C39,V_Mois,"<="&$D39)
B40: 2025 T4 | C40: 45931 | D40: 45992 | E40: =SUMIFS(V_CANet,V_Mois,">="&$C40,V_Mois,"<="&$D40,V_Canal,E$34)/SUMIFS(V_CANet,V_Mois,">="&$C40,V_Mois,"<="&$D40) | F40: =SUMIFS(V_CANet,V_Mois,">="&$C40,V_Mois,"<="&$D40,V_Canal,F$34)/SUMIFS(V_CANet,V_Mois,">="&$C40,V_Mois,"<="&$D40) | G40: =SUMIFS(V_CANet,V_Mois,">="&$C40,V_Mois,"<="&$D40,V_Canal,G$34)/SUMIFS(V_CANet,V_Mois,">="&$C40,V_Mois,"<="&$D40) | H40: =SUMIFS(V_CANet,V_Mois,">="&$C40,V_Mois,"<="&$D40,V_Canal,H$34)/SUMIFS(V_CANet,V_Mois,">="&$C40,V_Mois,"<="&$D40)
B41: 2026 T1 | C41: 46023 | D41: 46082 | E41: =SUMIFS(V_CANet,V_Mois,">="&$C41,V_Mois,"<="&$D41,V_Canal,E$34)/SUMIFS(V_CANet,V_Mois,">="&$C41,V_Mois,"<="&$D41) | F41: =SUMIFS(V_CANet,V_Mois,">="&$C41,V_Mois,"<="&$D41,V_Canal,F$34)/SUMIFS(V_CANet,V_Mois,">="&$C41,V_Mois,"<="&$D41) | G41: =SUMIFS(V_CANet,V_Mois,">="&$C41,V_Mois,"<="&$D41,V_Canal,G$34)/SUMIFS(V_CANet,V_Mois,">="&$C41,V_Mois,"<="&$D41) | H41: =SUMIFS(V_CANet,V_Mois,">="&$C41,V_Mois,"<="&$D41,V_Canal,H$34)/SUMIFS(V_CANet,V_Mois,">="&$C41,V_Mois,"<="&$D41)
B42: 2026 T2 | C42: 46113 | D42: 46174 | E42: =SUMIFS(V_CANet,V_Mois,">="&$C42,V_Mois,"<="&$D42,V_Canal,E$34)/SUMIFS(V_CANet,V_Mois,">="&$C42,V_Mois,"<="&$D42) | F42: =SUMIFS(V_CANet,V_Mois,">="&$C42,V_Mois,"<="&$D42,V_Canal,F$34)/SUMIFS(V_CANet,V_Mois,">="&$C42,V_Mois,"<="&$D42) | G42: =SUMIFS(V_CANet,V_Mois,">="&$C42,V_Mois,"<="&$D42,V_Canal,G$34)/SUMIFS(V_CANet,V_Mois,">="&$C42,V_Mois,"<="&$D42) | H42: =SUMIFS(V_CANet,V_Mois,">="&$C42,V_Mois,"<="&$D42,V_Canal,H$34)/SUMIFS(V_CANet,V_Mois,">="&$C42,V_Mois,"<="&$D42)
B43: 2026 T3 | C43: 46204 | D43: 46266 | E43: =SUMIFS(V_CANet,V_Mois,">="&$C43,V_Mois,"<="&$D43,V_Canal,E$34)/SUMIFS(V_CANet,V_Mois,">="&$C43,V_Mois,"<="&$D43) | F43: =SUMIFS(V_CANet,V_Mois,">="&$C43,V_Mois,"<="&$D43,V_Canal,F$34)/SUMIFS(V_CANet,V_Mois,">="&$C43,V_Mois,"<="&$D43) | G43: =SUMIFS(V_CANet,V_Mois,">="&$C43,V_Mois,"<="&$D43,V_Canal,G$34)/SUMIFS(V_CANet,V_Mois,">="&$C43,V_Mois,"<="&$D43) | H43: =SUMIFS(V_CANet,V_Mois,">="&$C43,V_Mois,"<="&$D43,V_Canal,H$34)/SUMIFS(V_CANet,V_Mois,">="&$C43,V_Mois,"<="&$D43)
B45: ="La livraison passe de "&FIXED(G35*100,1)&" % à "&FIXED(G43*100,1)&" % du CA net en "&ROWS(G35:G43)-1&" trimestres (+"&FIXED((G43-G35)*100,1)&" pt), prise sur le sur place ("&FIXED((E43-E35)*100,1)&" pt) et l'à emporter ("&FIXED((F43-F35)*100,1)&" pt). Le Drive est stable."
B49: 3. Quels fournisseurs dérivent ?
B50: Retard moyen de livraison (jours au-delà du délai contractuel) par semestre civil de commande. Commandes non livrées exclues.
F51: Début → | G51: 45474 | H51: 45658 | I51: 45839 | J51: 46023 | K51: 46204
F52: Fin → | G52: 45627 | H52: 45809 | I52: 45992 | J52: 46174 | K52: 46357
B53: Code | C53: Fournisseur | D53: Retard moyen | E53: Part en retard | F53: Clé | G53: 2024 S2 | H53: 2025 S1 | I53: 2025 S2 | J53: 2026 S1 | K53: 2026 S2
B54: =REF_FOURNISSEURS!A2 | C54: =REF_FOURNISSEURS!B2 | D54: =IF(SUMIFS(A_Livrees,A_Fourn,B54)=0,"aucune commande",SUMIFS(A_Retard,A_Fourn,B54)/SUMIFS(A_Livrees,A_Fourn,B54)) | E54: =IF(SUMIFS(A_Livrees,A_Fourn,B54)=0,"",SUMIFS(A_EnRetard,A_Fourn,B54)/SUMIFS(A_Livrees,A_Fourn,B54)) | F54: =IF(ISNUMBER(D54),D54+ROW()/10^9,-99) | G54: =IFERROR(SUMIFS(A_Retard,A_Fourn,$B54,A_Mois,">="&G$51,A_Mois,"<="&G$52)/SUMIFS(A_Livrees,A_Fourn,$B54,A_Mois,">="&G$51,A_Mois,"<="&G$52),"") | H54: =IFERROR(SUMIFS(A_Retard,A_Fourn,$B54,A_Mois,">="&H$51,A_Mois,"<="&H$52)/SUMIFS(A_Livrees,A_Fourn,$B54,A_Mois,">="&H$51,A_Mois,"<="&H$52),"") | I54: =IFERROR(SUMIFS(A_Retard,A_Fourn,$B54,A_Mois,">="&I$51,A_Mois,"<="&I$52)/SUMIFS(A_Livrees,A_Fourn,$B54,A_Mois,">="&I$51,A_Mois,"<="&I$52),"") | J54: =IFERROR(SUMIFS(A_Retard,A_Fourn,$B54,A_Mois,">="&J$51,A_Mois,"<="&J$52)/SUMIFS(A_Livrees,A_Fourn,$B54,A_Mois,">="&J$51,A_Mois,"<="&J$52),"") | K54: =IFERROR(SUMIFS(A_Retard,A_Fourn,$B54,A_Mois,">="&K$51,A_Mois,"<="&K$52)/SUMIFS(A_Livrees,A_Fourn,$B54,A_Mois,">="&K$51,A_Mois,"<="&K$52),"")
B55: =REF_FOURNISSEURS!A3 | C55: =REF_FOURNISSEURS!B3 | D55: =IF(SUMIFS(A_Livrees,A_Fourn,B55)=0,"aucune commande",SUMIFS(A_Retard,A_Fourn,B55)/SUMIFS(A_Livrees,A_Fourn,B55)) | E55: =IF(SUMIFS(A_Livrees,A_Fourn,B55)=0,"",SUMIFS(A_EnRetard,A_Fourn,B55)/SUMIFS(A_Livrees,A_Fourn,B55)) | F55: =IF(ISNUMBER(D55),D55+ROW()/10^9,-99) | G55: =IFERROR(SUMIFS(A_Retard,A_Fourn,$B55,A_Mois,">="&G$51,A_Mois,"<="&G$52)/SUMIFS(A_Livrees,A_Fourn,$B55,A_Mois,">="&G$51,A_Mois,"<="&G$52),"") | H55: =IFERROR(SUMIFS(A_Retard,A_Fourn,$B55,A_Mois,">="&H$51,A_Mois,"<="&H$52)/SUMIFS(A_Livrees,A_Fourn,$B55,A_Mois,">="&H$51,A_Mois,"<="&H$52),"") | I55: =IFERROR(SUMIFS(A_Retard,A_Fourn,$B55,A_Mois,">="&I$51,A_Mois,"<="&I$52)/SUMIFS(A_Livrees,A_Fourn,$B55,A_Mois,">="&I$51,A_Mois,"<="&I$52),"") | J55: =IFERROR(SUMIFS(A_Retard,A_Fourn,$B55,A_Mois,">="&J$51,A_Mois,"<="&J$52)/SUMIFS(A_Livrees,A_Fourn,$B55,A_Mois,">="&J$51,A_Mois,"<="&J$52),"") | K55: =IFERROR(SUMIFS(A_Retard,A_Fourn,$B55,A_Mois,">="&K$51,A_Mois,"<="&K$52)/SUMIFS(A_Livrees,A_Fourn,$B55,A_Mois,">="&K$51,A_Mois,"<="&K$52),"")
B56: =REF_FOURNISSEURS!A4 | C56: =REF_FOURNISSEURS!B4 | D56: =IF(SUMIFS(A_Livrees,A_Fourn,B56)=0,"aucune commande",SUMIFS(A_Retard,A_Fourn,B56)/SUMIFS(A_Livrees,A_Fourn,B56)) | E56: =IF(SUMIFS(A_Livrees,A_Fourn,B56)=0,"",SUMIFS(A_EnRetard,A_Fourn,B56)/SUMIFS(A_Livrees,A_Fourn,B56)) | F56: =IF(ISNUMBER(D56),D56+ROW()/10^9,-99) | G56: =IFERROR(SUMIFS(A_Retard,A_Fourn,$B56,A_Mois,">="&G$51,A_Mois,"<="&G$52)/SUMIFS(A_Livrees,A_Fourn,$B56,A_Mois,">="&G$51,A_Mois,"<="&G$52),"") | H56: =IFERROR(SUMIFS(A_Retard,A_Fourn,$B56,A_Mois,">="&H$51,A_Mois,"<="&H$52)/SUMIFS(A_Livrees,A_Fourn,$B56,A_Mois,">="&H$51,A_Mois,"<="&H$52),"") | I56: =IFERROR(SUMIFS(A_Retard,A_Fourn,$B56,A_Mois,">="&I$51,A_Mois,"<="&I$52)/SUMIFS(A_Livrees,A_Fourn,$B56,A_Mois,">="&I$51,A_Mois,"<="&I$52),"") | J56: =IFERROR(SUMIFS(A_Retard,A_Fourn,$B56,A_Mois,">="&J$51,A_Mois,"<="&J$52)/SUMIFS(A_Livrees,A_Fourn,$B56,A_Mois,">="&J$51,A_Mois,"<="&J$52),"") | K56: =IFERROR(SUMIFS(A_Retard,A_Fourn,$B56,A_Mois,">="&K$51,A_Mois,"<="&K$52)/SUMIFS(A_Livrees,A_Fourn,$B56,A_Mois,">="&K$51,A_Mois,"<="&K$52),"")
B57: =REF_FOURNISSEURS!A5 | C57: =REF_FOURNISSEURS!B5 | D57: =IF(SUMIFS(A_Livrees,A_Fourn,B57)=0,"aucune commande",SUMIFS(A_Retard,A_Fourn,B57)/SUMIFS(A_Livrees,A_Fourn,B57)) | E57: =IF(SUMIFS(A_Livrees,A_Fourn,B57)=0,"",SUMIFS(A_EnRetard,A_Fourn,B57)/SUMIFS(A_Livrees,A_Fourn,B57)) | F57: =IF(ISNUMBER(D57),D57+ROW()/10^9,-99) | G57: =IFERROR(SUMIFS(A_Retard,A_Fourn,$B57,A_Mois,">="&G$51,A_Mois,"<="&G$52)/SUMIFS(A_Livrees,A_Fourn,$B57,A_Mois,">="&G$51,A_Mois,"<="&G$52),"") | H57: =IFERROR(SUMIFS(A_Retard,A_Fourn,$B57,A_Mois,">="&H$51,A_Mois,"<="&H$52)/SUMIFS(A_Livrees,A_Fourn,$B57,A_Mois,">="&H$51,A_Mois,"<="&H$52),"") | I57: =IFERROR(SUMIFS(A_Retard,A_Fourn,$B57,A_Mois,">="&I$51,A_Mois,"<="&I$52)/SUMIFS(A_Livrees,A_Fourn,$B57,A_Mois,">="&I$51,A_Mois,"<="&I$52),"") | J57: =IFERROR(SUMIFS(A_Retard,A_Fourn,$B57,A_Mois,">="&J$51,A_Mois,"<="&J$52)/SUMIFS(A_Livrees,A_Fourn,$B57,A_Mois,">="&J$51,A_Mois,"<="&J$52),"") | K57: =IFERROR(SUMIFS(A_Retard,A_Fourn,$B57,A_Mois,">="&K$51,A_Mois,"<="&K$52)/SUMIFS(A_Livrees,A_Fourn,$B57,A_Mois,">="&K$51,A_Mois,"<="&K$52),"")
B58: =REF_FOURNISSEURS!A6 | C58: =REF_FOURNISSEURS!B6 | D58: =IF(SUMIFS(A_Livrees,A_Fourn,B58)=0,"aucune commande",SUMIFS(A_Retard,A_Fourn,B58)/SUMIFS(A_Livrees,A_Fourn,B58)) | E58: =IF(SUMIFS(A_Livrees,A_Fourn,B58)=0,"",SUMIFS(A_EnRetard,A_Fourn,B58)/SUMIFS(A_Livrees,A_Fourn,B58)) | F58: =IF(ISNUMBER(D58),D58+ROW()/10^9,-99) | G58: =IFERROR(SUMIFS(A_Retard,A_Fourn,$B58,A_Mois,">="&G$51,A_Mois,"<="&G$52)/SUMIFS(A_Livrees,A_Fourn,$B58,A_Mois,">="&G$51,A_Mois,"<="&G$52),"") | H58: =IFERROR(SUMIFS(A_Retard,A_Fourn,$B58,A_Mois,">="&H$51,A_Mois,"<="&H$52)/SUMIFS(A_Livrees,A_Fourn,$B58,A_Mois,">="&H$51,A_Mois,"<="&H$52),"") | I58: =IFERROR(SUMIFS(A_Retard,A_Fourn,$B58,A_Mois,">="&I$51,A_Mois,"<="&I$52)/SUMIFS(A_Livrees,A_Fourn,$B58,A_Mois,">="&I$51,A_Mois,"<="&I$52),"") | J58: =IFERROR(SUMIFS(A_Retard,A_Fourn,$B58,A_Mois,">="&J$51,A_Mois,"<="&J$52)/SUMIFS(A_Livrees,A_Fourn,$B58,A_Mois,">="&J$51,A_Mois,"<="&J$52),"") | K58: =IFERROR(SUMIFS(A_Retard,A_Fourn,$B58,A_Mois,">="&K$51,A_Mois,"<="&K$52)/SUMIFS(A_Livrees,A_Fourn,$B58,A_Mois,">="&K$51,A_Mois,"<="&K$52),"")
B59: =REF_FOURNISSEURS!A7 | C59: =REF_FOURNISSEURS!B7 | D59: =IF(SUMIFS(A_Livrees,A_Fourn,B59)=0,"aucune commande",SUMIFS(A_Retard,A_Fourn,B59)/SUMIFS(A_Livrees,A_Fourn,B59)) | E59: =IF(SUMIFS(A_Livrees,A_Fourn,B59)=0,"",SUMIFS(A_EnRetard,A_Fourn,B59)/SUMIFS(A_Livrees,A_Fourn,B59)) | F59: =IF(ISNUMBER(D59),D59+ROW()/10^9,-99) | G59: =IFERROR(SUMIFS(A_Retard,A_Fourn,$B59,A_Mois,">="&G$51,A_Mois,"<="&G$52)/SUMIFS(A_Livrees,A_Fourn,$B59,A_Mois,">="&G$51,A_Mois,"<="&G$52),"") | H59: =IFERROR(SUMIFS(A_Retard,A_Fourn,$B59,A_Mois,">="&H$51,A_Mois,"<="&H$52)/SUMIFS(A_Livrees,A_Fourn,$B59,A_Mois,">="&H$51,A_Mois,"<="&H$52),"") | I59: =IFERROR(SUMIFS(A_Retard,A_Fourn,$B59,A_Mois,">="&I$51,A_Mois,"<="&I$52)/SUMIFS(A_Livrees,A_Fourn,$B59,A_Mois,">="&I$51,A_Mois,"<="&I$52),"") | J59: =IFERROR(SUMIFS(A_Retard,A_Fourn,$B59,A_Mois,">="&J$51,A_Mois,"<="&J$52)/SUMIFS(A_Livrees,A_Fourn,$B59,A_Mois,">="&J$51,A_Mois,"<="&J$52),"") | K59: =IFERROR(SUMIFS(A_Retard,A_Fourn,$B59,A_Mois,">="&K$51,A_Mois,"<="&K$52)/SUMIFS(A_Livrees,A_Fourn,$B59,A_Mois,">="&K$51,A_Mois,"<="&K$52),"")
B60: =REF_FOURNISSEURS!A8 | C60: =REF_FOURNISSEURS!B8 | D60: =IF(SUMIFS(A_Livrees,A_Fourn,B60)=0,"aucune commande",SUMIFS(A_Retard,A_Fourn,B60)/SUMIFS(A_Livrees,A_Fourn,B60)) | E60: =IF(SUMIFS(A_Livrees,A_Fourn,B60)=0,"",SUMIFS(A_EnRetard,A_Fourn,B60)/SUMIFS(A_Livrees,A_Fourn,B60)) | F60: =IF(ISNUMBER(D60),D60+ROW()/10^9,-99) | G60: =IFERROR(SUMIFS(A_Retard,A_Fourn,$B60,A_Mois,">="&G$51,A_Mois,"<="&G$52)/SUMIFS(A_Livrees,A_Fourn,$B60,A_Mois,">="&G$51,A_Mois,"<="&G$52),"") | H60: =IFERROR(SUMIFS(A_Retard,A_Fourn,$B60,A_Mois,">="&H$51,A_Mois,"<="&H$52)/SUMIFS(A_Livrees,A_Fourn,$B60,A_Mois,">="&H$51,A_Mois,"<="&H$52),"") | I60: =IFERROR(SUMIFS(A_Retard,A_Fourn,$B60,A_Mois,">="&I$51,A_Mois,"<="&I$52)/SUMIFS(A_Livrees,A_Fourn,$B60,A_Mois,">="&I$51,A_Mois,"<="&I$52),"") | J60: =IFERROR(SUMIFS(A_Retard,A_Fourn,$B60,A_Mois,">="&J$51,A_Mois,"<="&J$52)/SUMIFS(A_Livrees,A_Fourn,$B60,A_Mois,">="&J$51,A_Mois,"<="&J$52),"") | K60: =IFERROR(SUMIFS(A_Retard,A_Fourn,$B60,A_Mois,">="&K$51,A_Mois,"<="&K$52)/SUMIFS(A_Livrees,A_Fourn,$B60,A_Mois,">="&K$51,A_Mois,"<="&K$52),"")
B61: =REF_FOURNISSEURS!A9 | C61: =REF_FOURNISSEURS!B9 | D61: =IF(SUMIFS(A_Livrees,A_Fourn,B61)=0,"aucune commande",SUMIFS(A_Retard,A_Fourn,B61)/SUMIFS(A_Livrees,A_Fourn,B61)) | E61: =IF(SUMIFS(A_Livrees,A_Fourn,B61)=0,"",SUMIFS(A_EnRetard,A_Fourn,B61)/SUMIFS(A_Livrees,A_Fourn,B61)) | F61: =IF(ISNUMBER(D61),D61+ROW()/10^9,-99) | G61: =IFERROR(SUMIFS(A_Retard,A_Fourn,$B61,A_Mois,">="&G$51,A_Mois,"<="&G$52)/SUMIFS(A_Livrees,A_Fourn,$B61,A_Mois,">="&G$51,A_Mois,"<="&G$52),"") | H61: =IFERROR(SUMIFS(A_Retard,A_Fourn,$B61,A_Mois,">="&H$51,A_Mois,"<="&H$52)/SUMIFS(A_Livrees,A_Fourn,$B61,A_Mois,">="&H$51,A_Mois,"<="&H$52),"") | I61: =IFERROR(SUMIFS(A_Retard,A_Fourn,$B61,A_Mois,">="&I$51,A_Mois,"<="&I$52)/SUMIFS(A_Livrees,A_Fourn,$B61,A_Mois,">="&I$51,A_Mois,"<="&I$52),"") | J61: =IFERROR(SUMIFS(A_Retard,A_Fourn,$B61,A_Mois,">="&J$51,A_Mois,"<="&J$52)/SUMIFS(A_Livrees,A_Fourn,$B61,A_Mois,">="&J$51,A_Mois,"<="&J$52),"") | K61: =IFERROR(SUMIFS(A_Retard,A_Fourn,$B61,A_Mois,">="&K$51,A_Mois,"<="&K$52)/SUMIFS(A_Livrees,A_Fourn,$B61,A_Mois,">="&K$51,A_Mois,"<="&K$52),"")
B62: =REF_FOURNISSEURS!A10 | C62: =REF_FOURNISSEURS!B10 | D62: =IF(SUMIFS(A_Livrees,A_Fourn,B62)=0,"aucune commande",SUMIFS(A_Retard,A_Fourn,B62)/SUMIFS(A_Livrees,A_Fourn,B62)) | E62: =IF(SUMIFS(A_Livrees,A_Fourn,B62)=0,"",SUMIFS(A_EnRetard,A_Fourn,B62)/SUMIFS(A_Livrees,A_Fourn,B62)) | F62: =IF(ISNUMBER(D62),D62+ROW()/10^9,-99) | G62: =IFERROR(SUMIFS(A_Retard,A_Fourn,$B62,A_Mois,">="&G$51,A_Mois,"<="&G$52)/SUMIFS(A_Livrees,A_Fourn,$B62,A_Mois,">="&G$51,A_Mois,"<="&G$52),"") | H62: =IFERROR(SUMIFS(A_Retard,A_Fourn,$B62,A_Mois,">="&H$51,A_Mois,"<="&H$52)/SUMIFS(A_Livrees,A_Fourn,$B62,A_Mois,">="&H$51,A_Mois,"<="&H$52),"") | I62: =IFERROR(SUMIFS(A_Retard,A_Fourn,$B62,A_Mois,">="&I$51,A_Mois,"<="&I$52)/SUMIFS(A_Livrees,A_Fourn,$B62,A_Mois,">="&I$51,A_Mois,"<="&I$52),"") | J62: =IFERROR(SUMIFS(A_Retard,A_Fourn,$B62,A_Mois,">="&J$51,A_Mois,"<="&J$52)/SUMIFS(A_Livrees,A_Fourn,$B62,A_Mois,">="&J$51,A_Mois,"<="&J$52),"") | K62: =IFERROR(SUMIFS(A_Retard,A_Fourn,$B62,A_Mois,">="&K$51,A_Mois,"<="&K$52)/SUMIFS(A_Livrees,A_Fourn,$B62,A_Mois,">="&K$51,A_Mois,"<="&K$52),"")
B63: =REF_FOURNISSEURS!A11 | C63: =REF_FOURNISSEURS!B11 | D63: =IF(SUMIFS(A_Livrees,A_Fourn,B63)=0,"aucune commande",SUMIFS(A_Retard,A_Fourn,B63)/SUMIFS(A_Livrees,A_Fourn,B63)) | E63: =IF(SUMIFS(A_Livrees,A_Fourn,B63)=0,"",SUMIFS(A_EnRetard,A_Fourn,B63)/SUMIFS(A_Livrees,A_Fourn,B63)) | F63: =IF(ISNUMBER(D63),D63+ROW()/10^9,-99) | G63: =IFERROR(SUMIFS(A_Retard,A_Fourn,$B63,A_Mois,">="&G$51,A_Mois,"<="&G$52)/SUMIFS(A_Livrees,A_Fourn,$B63,A_Mois,">="&G$51,A_Mois,"<="&G$52),"") | H63: =IFERROR(SUMIFS(A_Retard,A_Fourn,$B63,A_Mois,">="&H$51,A_Mois,"<="&H$52)/SUMIFS(A_Livrees,A_Fourn,$B63,A_Mois,">="&H$51,A_Mois,"<="&H$52),"") | I63: =IFERROR(SUMIFS(A_Retard,A_Fourn,$B63,A_Mois,">="&I$51,A_Mois,"<="&I$52)/SUMIFS(A_Livrees,A_Fourn,$B63,A_Mois,">="&I$51,A_Mois,"<="&I$52),"") | J63: =IFERROR(SUMIFS(A_Retard,A_Fourn,$B63,A_Mois,">="&J$51,A_Mois,"<="&J$52)/SUMIFS(A_Livrees,A_Fourn,$B63,A_Mois,">="&J$51,A_Mois,"<="&J$52),"") | K63: =IFERROR(SUMIFS(A_Retard,A_Fourn,$B63,A_Mois,">="&K$51,A_Mois,"<="&K$52)/SUMIFS(A_Livrees,A_Fourn,$B63,A_Mois,">="&K$51,A_Mois,"<="&K$52),"")
B64: =REF_FOURNISSEURS!A12 | C64: =REF_FOURNISSEURS!B12 | D64: =IF(SUMIFS(A_Livrees,A_Fourn,B64)=0,"aucune commande",SUMIFS(A_Retard,A_Fourn,B64)/SUMIFS(A_Livrees,A_Fourn,B64)) | E64: =IF(SUMIFS(A_Livrees,A_Fourn,B64)=0,"",SUMIFS(A_EnRetard,A_Fourn,B64)/SUMIFS(A_Livrees,A_Fourn,B64)) | F64: =IF(ISNUMBER(D64),D64+ROW()/10^9,-99) | G64: =IFERROR(SUMIFS(A_Retard,A_Fourn,$B64,A_Mois,">="&G$51,A_Mois,"<="&G$52)/SUMIFS(A_Livrees,A_Fourn,$B64,A_Mois,">="&G$51,A_Mois,"<="&G$52),"") | H64: =IFERROR(SUMIFS(A_Retard,A_Fourn,$B64,A_Mois,">="&H$51,A_Mois,"<="&H$52)/SUMIFS(A_Livrees,A_Fourn,$B64,A_Mois,">="&H$51,A_Mois,"<="&H$52),"") | I64: =IFERROR(SUMIFS(A_Retard,A_Fourn,$B64,A_Mois,">="&I$51,A_Mois,"<="&I$52)/SUMIFS(A_Livrees,A_Fourn,$B64,A_Mois,">="&I$51,A_Mois,"<="&I$52),"") | J64: =IFERROR(SUMIFS(A_Retard,A_Fourn,$B64,A_Mois,">="&J$51,A_Mois,"<="&J$52)/SUMIFS(A_Livrees,A_Fourn,$B64,A_Mois,">="&J$51,A_Mois,"<="&J$52),"") | K64: =IFERROR(SUMIFS(A_Retard,A_Fourn,$B64,A_Mois,">="&K$51,A_Mois,"<="&K$52)/SUMIFS(A_Livrees,A_Fourn,$B64,A_Mois,">="&K$51,A_Mois,"<="&K$52),"")
B65: =REF_FOURNISSEURS!A13 | C65: =REF_FOURNISSEURS!B13 | D65: =IF(SUMIFS(A_Livrees,A_Fourn,B65)=0,"aucune commande",SUMIFS(A_Retard,A_Fourn,B65)/SUMIFS(A_Livrees,A_Fourn,B65)) | E65: =IF(SUMIFS(A_Livrees,A_Fourn,B65)=0,"",SUMIFS(A_EnRetard,A_Fourn,B65)/SUMIFS(A_Livrees,A_Fourn,B65)) | F65: =IF(ISNUMBER(D65),D65+ROW()/10^9,-99) | G65: =IFERROR(SUMIFS(A_Retard,A_Fourn,$B65,A_Mois,">="&G$51,A_Mois,"<="&G$52)/SUMIFS(A_Livrees,A_Fourn,$B65,A_Mois,">="&G$51,A_Mois,"<="&G$52),"") | H65: =IFERROR(SUMIFS(A_Retard,A_Fourn,$B65,A_Mois,">="&H$51,A_Mois,"<="&H$52)/SUMIFS(A_Livrees,A_Fourn,$B65,A_Mois,">="&H$51,A_Mois,"<="&H$52),"") | I65: =IFERROR(SUMIFS(A_Retard,A_Fourn,$B65,A_Mois,">="&I$51,A_Mois,"<="&I$52)/SUMIFS(A_Livrees,A_Fourn,$B65,A_Mois,">="&I$51,A_Mois,"<="&I$52),"") | J65: =IFERROR(SUMIFS(A_Retard,A_Fourn,$B65,A_Mois,">="&J$51,A_Mois,"<="&J$52)/SUMIFS(A_Livrees,A_Fourn,$B65,A_Mois,">="&J$51,A_Mois,"<="&J$52),"") | K65: =IFERROR(SUMIFS(A_Retard,A_Fourn,$B65,A_Mois,">="&K$51,A_Mois,"<="&K$52)/SUMIFS(A_Livrees,A_Fourn,$B65,A_Mois,">="&K$51,A_Mois,"<="&K$52),"")
... B68: =REF_FOURNISSEURS!A16 | C68: =REF_FOURNISSEURS!B16 | D68: =IF(SUMIFS(A_Livrees,A_Fourn,B68)=0,"aucune commande",SUMIFS(A_Retard,A_Fourn,B68)/SUMIFS(A_Livrees,A_Fourn,B68)) | E68: =IF(SUMIFS(A_Livrees,A_Fourn,B68)=0,"",SUMIFS(A_EnRetard,A_Fourn,B68)/SUMIFS(A_Livrees,A_Fourn,B68)) | F68: =IF(ISNUMBER(D68),D68+ROW()/10^9,-99) | G68: =IFERROR(SUMIFS(A_Retard,A_Fourn,$B68,A_Mois,">="&G$51,A_Mois,"<="&G$52)/SUMIFS(A_Livrees,A_Fourn,$B68,A_Mois,">="&G$51,A_Mois,"<="&G$52),"") | H68: =IFERROR(SUMIFS(A_Retard,A_Fourn,$B68,A_Mois,">="&H$51,A_Mois,"<="&H$52)/SUMIFS(A_Livrees,A_Fourn,$B68,A_Mois,">="&H$51,A_Mois,"<="&H$52),"") | I68: =IFERROR(SUMIFS(A_Retard,A_Fourn,$B68,A_Mois,">="&I$51,A_Mois,"<="&I$52)/SUMIFS(A_Livrees,A_Fourn,$B68,A_Mois,">="&I$51,A_Mois,"<="&I$52),"") | J68: =IFERROR(SUMIFS(A_Retard,A_Fourn,$B68,A_Mois,">="&J$51,A_Mois,"<="&J$52)/SUMIFS(A_Livrees,A_Fourn,$B68,A_Mois,">="&J$51,A_Mois,"<="&J$52),"") | K68: =IFERROR(SUMIFS(A_Retard,A_Fourn,$B68,A_Mois,">="&K$51,A_Mois,"<="&K$52)/SUMIFS(A_Livrees,A_Fourn,$B68,A_Mois,">="&K$51,A_Mois,"<="&K$52),"")
B70: ="Deux fournisseurs décrochent : "&INDEX(C54:C68,MATCH(LARGE($F$54:$F$68,1),$F$54:$F$68,0))&" (+"&FIXED(INDEX(D54:D68,MATCH(LARGE($F$54:$F$68,1),$F$54:$F$68,0)),2)&" j) et "&INDEX(C54:C68,MATCH(LARGE($F$54:$F$68,2),$F$54:$F$68,0))&" (+"&FIXED(INDEX(D54:D68,MATCH(LARGE($F$54:$F$68,2),$F$54:$F$68,0)),2)&" j), contre +"&FIXED(LARGE($F$54:$F$68,3),2)&" j au mieux pour les autres. La dérive est progressive : "&FIXED(INDEX(G54:G68,MATCH(LARGE($F$54:$F$68,1),$F$54:$F$68,0)),2)&" j au premier semestre, "&FIXED(INDEX(K54:K68,MATCH(LARGE($F$54:$F$68,1),$F$54:$F$68,0)),2)&" j au dernier pour le premier d'entre eux."
B74: 4. Où part le stock ?
B75: Taux de perte = pertes / sorties, sur les 24 mois (ratio de sommes). Les 7 plus élevés.
B76: Rang | C76: Code | D76: Ville | E76: Taux de perte | F76: × médiane | G76: En dérive marge ?
B77: 1 | C77: =INDEX(CM_Code_Magasin,MATCH(LARGE(CM_Cle_Perte_24m,1),CM_Cle_Perte_24m,0)) | D77: =INDEX(CM_Ville,MATCH(LARGE(CM_Cle_Perte_24m,1),CM_Cle_Perte_24m,0)) | E77: =INDEX(CM_Taux_Perte_24m,MATCH(LARGE(CM_Cle_Perte_24m,1),CM_Cle_Perte_24m,0)) | F77: =E77/D_Mediane_Perte_24m | G77: =IF(INDEX(CM_En_Derive,MATCH(LARGE(CM_Cle_Perte_24m,1),CM_Cle_Perte_24m,0))=1,"oui","non")
B78: 2 | C78: =INDEX(CM_Code_Magasin,MATCH(LARGE(CM_Cle_Perte_24m,2),CM_Cle_Perte_24m,0)) | D78: =INDEX(CM_Ville,MATCH(LARGE(CM_Cle_Perte_24m,2),CM_Cle_Perte_24m,0)) | E78: =INDEX(CM_Taux_Perte_24m,MATCH(LARGE(CM_Cle_Perte_24m,2),CM_Cle_Perte_24m,0)) | F78: =E78/D_Mediane_Perte_24m | G78: =IF(INDEX(CM_En_Derive,MATCH(LARGE(CM_Cle_Perte_24m,2),CM_Cle_Perte_24m,0))=1,"oui","non")
B79: 3 | C79: =INDEX(CM_Code_Magasin,MATCH(LARGE(CM_Cle_Perte_24m,3),CM_Cle_Perte_24m,0)) | D79: =INDEX(CM_Ville,MATCH(LARGE(CM_Cle_Perte_24m,3),CM_Cle_Perte_24m,0)) | E79: =INDEX(CM_Taux_Perte_24m,MATCH(LARGE(CM_Cle_Perte_24m,3),CM_Cle_Perte_24m,0)) | F79: =E79/D_Mediane_Perte_24m | G79: =IF(INDEX(CM_En_Derive,MATCH(LARGE(CM_Cle_Perte_24m,3),CM_Cle_Perte_24m,0))=1,"oui","non")
B80: 4 | C80: =INDEX(CM_Code_Magasin,MATCH(LARGE(CM_Cle_Perte_24m,4),CM_Cle_Perte_24m,0)) | D80: =INDEX(CM_Ville,MATCH(LARGE(CM_Cle_Perte_24m,4),CM_Cle_Perte_24m,0)) | E80: =INDEX(CM_Taux_Perte_24m,MATCH(LARGE(CM_Cle_Perte_24m,4),CM_Cle_Perte_24m,0)) | F80: =E80/D_Mediane_Perte_24m | G80: =IF(INDEX(CM_En_Derive,MATCH(LARGE(CM_Cle_Perte_24m,4),CM_Cle_Perte_24m,0))=1,"oui","non")
B81: 5 | C81: =INDEX(CM_Code_Magasin,MATCH(LARGE(CM_Cle_Perte_24m,5),CM_Cle_Perte_24m,0)) | D81: =INDEX(CM_Ville,MATCH(LARGE(CM_Cle_Perte_24m,5),CM_Cle_Perte_24m,0)) | E81: =INDEX(CM_Taux_Perte_24m,MATCH(LARGE(CM_Cle_Perte_24m,5),CM_Cle_Perte_24m,0)) | F81: =E81/D_Mediane_Perte_24m | G81: =IF(INDEX(CM_En_Derive,MATCH(LARGE(CM_Cle_Perte_24m,5),CM_Cle_Perte_24m,0))=1,"oui","non")
B82: 6 | C82: =INDEX(CM_Code_Magasin,MATCH(LARGE(CM_Cle_Perte_24m,6),CM_Cle_Perte_24m,0)) | D82: =INDEX(CM_Ville,MATCH(LARGE(CM_Cle_Perte_24m,6),CM_Cle_Perte_24m,0)) | E82: =INDEX(CM_Taux_Perte_24m,MATCH(LARGE(CM_Cle_Perte_24m,6),CM_Cle_Perte_24m,0)) | F82: =E82/D_Mediane_Perte_24m | G82: =IF(INDEX(CM_En_Derive,MATCH(LARGE(CM_Cle_Perte_24m,6),CM_Cle_Perte_24m,0))=1,"oui","non")
B83: 7 | C83: =INDEX(CM_Code_Magasin,MATCH(LARGE(CM_Cle_Perte_24m,7),CM_Cle_Perte_24m,0)) | D83: =INDEX(CM_Ville,MATCH(LARGE(CM_Cle_Perte_24m,7),CM_Cle_Perte_24m,0)) | E83: =INDEX(CM_Taux_Perte_24m,MATCH(LARGE(CM_Cle_Perte_24m,7),CM_Cle_Perte_24m,0)) | F83: =E83/D_Mediane_Perte_24m | G83: =IF(INDEX(CM_En_Derive,MATCH(LARGE(CM_Cle_Perte_24m,7),CM_Cle_Perte_24m,0))=1,"oui","non")
B85: =COUNTIF(F77:F83,">"&Seuil_Perte_Multiple_Mediane)&" magasins dépassent "&Seuil_Perte_Multiple_Mediane&" fois la médiane du réseau ("&FIXED(D_Mediane_Perte_24m*100,2)&" %), de "&FIXED(INDEX(E77:E83,COUNTIF(F77:F83,">"&Seuil_Perte_Multiple_Mediane))*100,2)&" % à "&FIXED(E77*100,2)&" %. Le suivant est à "&FIXED(INDEX(E77:E83,COUNTIF(F77:F83,">"&Seuil_Perte_Multiple_Mediane)+1)*100,2)&" %. Aucun n'est en dérive de marge : les deux problèmes sont disjoints."
B89: 5. Quelle part de la croissance vient du périmètre ?
B90: Code | C90: Ville | D90: Événement | E90: Date
B91: =IFERROR(INDEX(CM_Code_Magasin,MATCH(1,CM_Rang_Mouvement,0)),"") | C91: =IFERROR(INDEX(CM_Ville,MATCH(1,CM_Rang_Mouvement,0)),"") | D91: =IFERROR(INDEX(CM_Mouvement,MATCH(1,CM_Rang_Mouvement,0)),"") | E91: =IFERROR(IF(INDEX(CM_Mouvement,MATCH(1,CM_Rang_Mouvement,0))="Ouverture",INDEX(CM_Date_Ouverture,MATCH(1,CM_Rang_Mouvement,0)),INDEX(CM_Date_Fermeture,MATCH(1,CM_Rang_Mouvement,0))),"")
B92: =IFERROR(INDEX(CM_Code_Magasin,MATCH(2,CM_Rang_Mouvement,0)),"") | C92: =IFERROR(INDEX(CM_Ville,MATCH(2,CM_Rang_Mouvement,0)),"") | D92: =IFERROR(INDEX(CM_Mouvement,MATCH(2,CM_Rang_Mouvement,0)),"") | E92: =IFERROR(IF(INDEX(CM_Mouvement,MATCH(2,CM_Rang_Mouvement,0))="Ouverture",INDEX(CM_Date_Ouverture,MATCH(2,CM_Rang_Mouvement,0)),INDEX(CM_Date_Fermeture,MATCH(2,CM_Rang_Mouvement,0))),"")
B93: =IFERROR(INDEX(CM_Code_Magasin,MATCH(3,CM_Rang_Mouvement,0)),"") | C93: =IFERROR(INDEX(CM_Ville,MATCH(3,CM_Rang_Mouvement,0)),"") | D93: =IFERROR(INDEX(CM_Mouvement,MATCH(3,CM_Rang_Mouvement,0)),"") | E93: =IFERROR(IF(INDEX(CM_Mouvement,MATCH(3,CM_Rang_Mouvement,0))="Ouverture",INDEX(CM_Date_Ouverture,MATCH(3,CM_Rang_Mouvement,0)),INDEX(CM_Date_Fermeture,MATCH(3,CM_Rang_Mouvement,0))),"")
B94: =IFERROR(INDEX(CM_Code_Magasin,MATCH(4,CM_Rang_Mouvement,0)),"") | C94: =IFERROR(INDEX(CM_Ville,MATCH(4,CM_Rang_Mouvement,0)),"") | D94: =IFERROR(INDEX(CM_Mouvement,MATCH(4,CM_Rang_Mouvement,0)),"") | E94: =IFERROR(IF(INDEX(CM_Mouvement,MATCH(4,CM_Rang_Mouvement,0))="Ouverture",INDEX(CM_Date_Ouverture,MATCH(4,CM_Rang_Mouvement,0)),INDEX(CM_Date_Fermeture,MATCH(4,CM_Rang_Mouvement,0))),"")
B95: =IFERROR(INDEX(CM_Code_Magasin,MATCH(5,CM_Rang_Mouvement,0)),"") | C95: =IFERROR(INDEX(CM_Ville,MATCH(5,CM_Rang_Mouvement,0)),"") | D95: =IFERROR(INDEX(CM_Mouvement,MATCH(5,CM_Rang_Mouvement,0)),"") | E95: =IFERROR(IF(INDEX(CM_Mouvement,MATCH(5,CM_Rang_Mouvement,0))="Ouverture",INDEX(CM_Date_Ouverture,MATCH(5,CM_Rang_Mouvement,0)),INDEX(CM_Date_Fermeture,MATCH(5,CM_Rang_Mouvement,0))),"")
B97: Périmètre | D97: Magasins | E97: CA net N-1 | F97: CA net N | G97: Évolution
B98: Total réseau | D98: =COUNTA(CM_Code_Magasin) | E98: =SUM(CM_CA_Net_N1) | F98: =SUM(CM_CA_Net_N) | G98: =F98/E98-1
B99: Périmètre comparable | D99: =SUM(CM_Comparable) | E99: =SUMPRODUCT(CM_Comparable,CM_CA_Net_N1) | F99: =SUMPRODUCT(CM_Comparable,CM_CA_Net_N) | G99: =F99/E99-1
B101: ="La croissance totale de "&FIXED(G98*100,1)&" % se décompose en "&FIXED(G99*100,1)&" % à périmètre comparable ("&D99&" magasins) et "&FIXED((G98-G99)*100,1)&" pt d'effet périmètre. Le comparable contient encore la hausse tarifaire de "&FIXED(Hausse_Tarifaire*100,1)&" % (constat 6)."
B105: 6. La hausse tarifaire du 01/09/2025 a-t-elle tenu ?
B106: Ticket moyen HT mensuel = CA net total / tickets totaux du mois (ratio de sommes, pas moyenne de ratios).
B107: Mois | C107: CA net | D107: Tickets | E107: Ticket moyen | F107: Évol. / mois préc.
B108: =EDATE(Debut_N1,0) | C108: =SUMIFS(V_CANet,V_Mois,B108) | D108: =SUMIFS(V_Tickets,V_Mois,B108) | E108: =C108/D108
B109: =EDATE(Debut_N1,1) | C109: =SUMIFS(V_CANet,V_Mois,B109) | D109: =SUMIFS(V_Tickets,V_Mois,B109) | E109: =C109/D109 | F109: =E109/E108-1
B110: =EDATE(Debut_N1,2) | C110: =SUMIFS(V_CANet,V_Mois,B110) | D110: =SUMIFS(V_Tickets,V_Mois,B110) | E110: =C110/D110 | F110: =E110/E109-1
B111: =EDATE(Debut_N1,3) | C111: =SUMIFS(V_CANet,V_Mois,B111) | D111: =SUMIFS(V_Tickets,V_Mois,B111) | E111: =C111/D111 | F111: =E111/E110-1
B112: =EDATE(Debut_N1,4) | C112: =SUMIFS(V_CANet,V_Mois,B112) | D112: =SUMIFS(V_Tickets,V_Mois,B112) | E112: =C112/D112 | F112: =E112/E111-1
B113: =EDATE(Debut_N1,5) | C113: =SUMIFS(V_CANet,V_Mois,B113) | D113: =SUMIFS(V_Tickets,V_Mois,B113) | E113: =C113/D113 | F113: =E113/E112-1
B114: =EDATE(Debut_N1,6) | C114: =SUMIFS(V_CANet,V_Mois,B114) | D114: =SUMIFS(V_Tickets,V_Mois,B114) | E114: =C114/D114 | F114: =E114/E113-1
B115: =EDATE(Debut_N1,7) | C115: =SUMIFS(V_CANet,V_Mois,B115) | D115: =SUMIFS(V_Tickets,V_Mois,B115) | E115: =C115/D115 | F115: =E115/E114-1
B116: =EDATE(Debut_N1,8) | C116: =SUMIFS(V_CANet,V_Mois,B116) | D116: =SUMIFS(V_Tickets,V_Mois,B116) | E116: =C116/D116 | F116: =E116/E115-1
B117: =EDATE(Debut_N1,9) | C117: =SUMIFS(V_CANet,V_Mois,B117) | D117: =SUMIFS(V_Tickets,V_Mois,B117) | E117: =C117/D117 | F117: =E117/E116-1
B118: =EDATE(Debut_N1,10) | C118: =SUMIFS(V_CANet,V_Mois,B118) | D118: =SUMIFS(V_Tickets,V_Mois,B118) | E118: =C118/D118 | F118: =E118/E117-1
B119: =EDATE(Debut_N1,11) | C119: =SUMIFS(V_CANet,V_Mois,B119) | D119: =SUMIFS(V_Tickets,V_Mois,B119) | E119: =C119/D119 | F119: =E119/E118-1
B120: =EDATE(Debut_N1,12) | C120: =SUMIFS(V_CANet,V_Mois,B120) | D120: =SUMIFS(V_Tickets,V_Mois,B120) | E120: =C120/D120 | F120: =E120/E119-1
B121: =EDATE(Debut_N1,13) | C121: =SUMIFS(V_CANet,V_Mois,B121) | D121: =SUMIFS(V_Tickets,V_Mois,B121) | E121: =C121/D121 | F121: =E121/E120-1
B122: =EDATE(Debut_N1,14) | C122: =SUMIFS(V_CANet,V_Mois,B122) | D122: =SUMIFS(V_Tickets,V_Mois,B122) | E122: =C122/D122 | F122: =E122/E121-1
B123: =EDATE(Debut_N1,15) | C123: =SUMIFS(V_CANet,V_Mois,B123) | D123: =SUMIFS(V_Tickets,V_Mois,B123) | E123: =C123/D123 | F123: =E123/E122-1
B124: =EDATE(Debut_N1,16) | C124: =SUMIFS(V_CANet,V_Mois,B124) | D124: =SUMIFS(V_Tickets,V_Mois,B124) | E124: =C124/D124 | F124: =E124/E123-1
B125: =EDATE(Debut_N1,17) | C125: =SUMIFS(V_CANet,V_Mois,B125) | D125: =SUMIFS(V_Tickets,V_Mois,B125) | E125: =C125/D125 | F125: =E125/E124-1
B126: =EDATE(Debut_N1,18) | C126: =SUMIFS(V_CANet,V_Mois,B126) | D126: =SUMIFS(V_Tickets,V_Mois,B126) | E126: =C126/D126 | F126: =E126/E125-1
B127: =EDATE(Debut_N1,19) | C127: =SUMIFS(V_CANet,V_Mois,B127) | D127: =SUMIFS(V_Tickets,V_Mois,B127) | E127: =C127/D127 | F127: =E127/E126-1
...

Sheet SIMULATEUR
B1: SIMULATEUR — combien mettre, où, pour récupérer la marge perdue ?
B2: Les magasins candidats sont les 8 plus forts reculs de taux de marge (constat 1). Hypothèses dans PARAMETRES ; décisions d'audit en colonne L (0/1).
B4: Modèle — un audit par magasin candidat | P4: Contraintes et objectif
B5: Code | C5: Ville | D5: Région | E5: CA net N | F5: Taux N | G5: Écart (pt) | H5: Marge manquante | I5: Coût audit | J5: Gain net | K5: Seuil récup. | L5: Décision | M5: Gain retenu | N5: Coût retenu | P5: Coût engagé | Q5: =N14 | R5: =IF(Q5<=Q6,"respectée","DÉPASSÉE")
B6: =INDEX(CM_Code_Magasin,MATCH(SMALL(CM_Cle_Derive,1),CM_Cle_Derive,0)) | C6: =INDEX(CM_Ville,MATCH(SMALL(CM_Cle_Derive,1),CM_Cle_Derive,0)) | D6: =INDEX(CM_Region,MATCH(SMALL(CM_Cle_Derive,1),CM_Cle_Derive,0)) | E6: =INDEX(CM_CA_Net_N,MATCH(SMALL(CM_Cle_Derive,1),CM_Cle_Derive,0)) | F6: =INDEX(CM_Taux_Marge_N,MATCH(SMALL(CM_Cle_Derive,1),CM_Cle_Derive,0)) | G6: =(D_Taux_Reseau-F6)*100 | H6: =E6*(D_Taux_Reseau-F6) | I6: =Cout_Audit | J6: =H6*Taux_Recup-I6 | K6: =IF(H6>0,I6/H6,"") | L6: 1 | M6: =L6*J6 | N6: =L6*I6 | P6: Enveloppe | Q6: =Enveloppe_Audit
B7: =INDEX(CM_Code_Magasin,MATCH(SMALL(CM_Cle_Derive,2),CM_Cle_Derive,0)) | C7: =INDEX(CM_Ville,MATCH(SMALL(CM_Cle_Derive,2),CM_Cle_Derive,0)) | D7: =INDEX(CM_Region,MATCH(SMALL(CM_Cle_Derive,2),CM_Cle_Derive,0)) | E7: =INDEX(CM_CA_Net_N,MATCH(SMALL(CM_Cle_Derive,2),CM_Cle_Derive,0)) | F7: =INDEX(CM_Taux_Marge_N,MATCH(SMALL(CM_Cle_Derive,2),CM_Cle_Derive,0)) | G7: =(D_Taux_Reseau-F7)*100 | H7: =E7*(D_Taux_Reseau-F7) | I7: =Cout_Audit | J7: =H7*Taux_Recup-I7 | K7: =IF(H7>0,I7/H7,"") | L7: 1 | M7: =L7*J7 | N7: =L7*I7
B8: =INDEX(CM_Code_Magasin,MATCH(SMALL(CM_Cle_Derive,3),CM_Cle_Derive,0)) | C8: =INDEX(CM_Ville,MATCH(SMALL(CM_Cle_Derive,3),CM_Cle_Derive,0)) | D8: =INDEX(CM_Region,MATCH(SMALL(CM_Cle_Derive,3),CM_Cle_Derive,0)) | E8: =INDEX(CM_CA_Net_N,MATCH(SMALL(CM_Cle_Derive,3),CM_Cle_Derive,0)) | F8: =INDEX(CM_Taux_Marge_N,MATCH(SMALL(CM_Cle_Derive,3),CM_Cle_Derive,0)) | G8: =(D_Taux_Reseau-F8)*100 | H8: =E8*(D_Taux_Reseau-F8) | I8: =Cout_Audit | J8: =H8*Taux_Recup-I8 | K8: =IF(H8>0,I8/H8,"") | L8: 1 | M8: =L8*J8 | N8: =L8*I8 | P8: Région | Q8: Candidats | R8: Retenus | S8: Contrainte ≥ 1
B9: =INDEX(CM_Code_Magasin,MATCH(SMALL(CM_Cle_Derive,4),CM_Cle_Derive,0)) | C9: =INDEX(CM_Ville,MATCH(SMALL(CM_Cle_Derive,4),CM_Cle_Derive,0)) | D9: =INDEX(CM_Region,MATCH(SMALL(CM_Cle_Derive,4),CM_Cle_Derive,0)) | E9: =INDEX(CM_CA_Net_N,MATCH(SMALL(CM_Cle_Derive,4),CM_Cle_Derive,0)) | F9: =INDEX(CM_Taux_Marge_N,MATCH(SMALL(CM_Cle_Derive,4),CM_Cle_Derive,0)) | G9: =(D_Taux_Reseau-F9)*100 | H9: =E9*(D_Taux_Reseau-F9) | I9: =Cout_Audit | J9: =H9*Taux_Recup-I9 | K9: =IF(H9>0,I9/H9,"") | L9: 1 | M9: =L9*J9 | N9: =L9*I9 | P9: Île-de-France | Q9: =COUNTIF($D$6:$D$13,P9) | R9: =COUNTIFS($D$6:$D$13,P9,$L$6:$L$13,1) | S9: =IF(Q9=0,"sans objet",IF(R9>=1,"respectée","NON RESPECTÉE"))
B10: =INDEX(CM_Code_Magasin,MATCH(SMALL(CM_Cle_Derive,5),CM_Cle_Derive,0)) | C10: =INDEX(CM_Ville,MATCH(SMALL(CM_Cle_Derive,5),CM_Cle_Derive,0)) | D10: =INDEX(CM_Region,MATCH(SMALL(CM_Cle_Derive,5),CM_Cle_Derive,0)) | E10: =INDEX(CM_CA_Net_N,MATCH(SMALL(CM_Cle_Derive,5),CM_Cle_Derive,0)) | F10: =INDEX(CM_Taux_Marge_N,MATCH(SMALL(CM_Cle_Derive,5),CM_Cle_Derive,0)) | G10: =(D_Taux_Reseau-F10)*100 | H10: =E10*(D_Taux_Reseau-F10) | I10: =Cout_Audit | J10: =H10*Taux_Recup-I10 | K10: =IF(H10>0,I10/H10,"") | L10: 1 | M10: =L10*J10 | N10: =L10*I10 | P10: Sud-Est | Q10: =COUNTIF($D$6:$D$13,P10) | R10: =COUNTIFS($D$6:$D$13,P10,$L$6:$L$13,1) | S10: =IF(Q10=0,"sans objet",IF(R10>=1,"respectée","NON RESPECTÉE"))
B11: =INDEX(CM_Code_Magasin,MATCH(SMALL(CM_Cle_Derive,6),CM_Cle_Derive,0)) | C11: =INDEX(CM_Ville,MATCH(SMALL(CM_Cle_Derive,6),CM_Cle_Derive,0)) | D11: =INDEX(CM_Region,MATCH(SMALL(CM_Cle_Derive,6),CM_Cle_Derive,0)) | E11: =INDEX(CM_CA_Net_N,MATCH(SMALL(CM_Cle_Derive,6),CM_Cle_Derive,0)) | F11: =INDEX(CM_Taux_Marge_N,MATCH(SMALL(CM_Cle_Derive,6),CM_Cle_Derive,0)) | G11: =(D_Taux_Reseau-F11)*100 | H11: =E11*(D_Taux_Reseau-F11) | I11: =Cout_Audit | J11: =H11*Taux_Recup-I11 | K11: =IF(H11>0,I11/H11,"") | L11: 0 | M11: =L11*J11 | N11: =L11*I11 | P11: Nord-Ouest | Q11: =COUNTIF($D$6:$D$13,P11) | R11: =COUNTIFS($D$6:$D$13,P11,$L$6:$L$13,1) | S11: =IF(Q11=0,"sans objet",IF(R11>=1,"respectée","NON RESPECTÉE"))
B12: =INDEX(CM_Code_Magasin,MATCH(SMALL(CM_Cle_Derive,7),CM_Cle_Derive,0)) | C12: =INDEX(CM_Ville,MATCH(SMALL(CM_Cle_Derive,7),CM_Cle_Derive,0)) | D12: =INDEX(CM_Region,MATCH(SMALL(CM_Cle_Derive,7),CM_Cle_Derive,0)) | E12: =INDEX(CM_CA_Net_N,MATCH(SMALL(CM_Cle_Derive,7),CM_Cle_Derive,0)) | F12: =INDEX(CM_Taux_Marge_N,MATCH(SMALL(CM_Cle_Derive,7),CM_Cle_Derive,0)) | G12: =(D_Taux_Reseau-F12)*100 | H12: =E12*(D_Taux_Reseau-F12) | I12: =Cout_Audit | J12: =H12*Taux_Recup-I12 | K12: =IF(H12>0,I12/H12,"") | L12: 0 | M12: =L12*J12 | N12: =L12*I12 | P12: Sud-Ouest | Q12: =COUNTIF($D$6:$D$13,P12) | R12: =COUNTIFS($D$6:$D$13,P12,$L$6:$L$13,1) | S12: =IF(Q12=0,"sans objet",IF(R12>=1,"respectée","NON RESPECTÉE"))
B13: =INDEX(CM_Code_Magasin,MATCH(SMALL(CM_Cle_Derive,8),CM_Cle_Derive,0)) | C13: =INDEX(CM_Ville,MATCH(SMALL(CM_Cle_Derive,8),CM_Cle_Derive,0)) | D13: =INDEX(CM_Region,MATCH(SMALL(CM_Cle_Derive,8),CM_Cle_Derive,0)) | E13: =INDEX(CM_CA_Net_N,MATCH(SMALL(CM_Cle_Derive,8),CM_Cle_Derive,0)) | F13: =INDEX(CM_Taux_Marge_N,MATCH(SMALL(CM_Cle_Derive,8),CM_Cle_Derive,0)) | G13: =(D_Taux_Reseau-F13)*100 | H13: =E13*(D_Taux_Reseau-F13) | I13: =Cout_Audit | J13: =H13*Taux_Recup-I13 | K13: =IF(H13>0,I13/H13,"") | L13: 0 | M13: =L13*J13 | N13: =L13*I13
B14: Total | H14: =SUM(H6:H13) | L14: =SUM(L6:L13) | M14: =SUM(M6:M13) | N14: =SUM(N6:N13) | P14: Gain net de la sélection | Q14: =M14
B15: Écart = taux du réseau − taux du magasin. Seuil récup. = part de l'écart à récupérer pour que l'audit se paie. Décisions pré-remplies avec l'optimum du Solveur au scénario central.
P16: Paramétrage du Solveur
B17: Quatre façons de choisir — ce que l'optimisation apporte | P17: Objectif : $M$14 — Max
B18: Stratégie | F18: Magasins | H18: Coût | J18: Gain net | L18: Lecture | P18: Cellules variables : $L$6:$L$13
B19: Auditer les 8 candidats | F19: =COUNT(H6:H13) | H19: =COUNT(H6:H13)*Cout_Audit | J19: =SUM(J6:J13) | L19: =IF(H19>Enveloppe_Audit,"hors enveloppe ("&FIXED(H19,0)&" € > "&FIXED(Enveloppe_Audit,0)&" €)","") | P19: Contrainte : $L$6:$L$13 = binaire
B20: Classement naïf : les plus gros écarts, jusqu'à l'enveloppe | F20: =MIN(INT(Enveloppe_Audit/Cout_Audit),COUNT(H6:H13)) | H20: =F20*Cout_Audit | J20: =SUMPRODUCT((H6:H13>=LARGE(H6:H13,F20))*J6:J13) | L20: ="dont "&SUMPRODUCT((H6:H13>=LARGE(H6:H13,F20))*(J6:J13<0))&" à perte" | P20: Contrainte : $N$14 <= Enveloppe_Audit
B21: Sans contrainte régionale : gains positifs seuls | F21: =COUNTIF(J6:J13,">0") | H21: =COUNTIF(J6:J13,">0")*Cout_Audit | J21: =SUMIF(J6:J13,">0") | L21: ="enveloppe non saturée" | P21: Contrainte : $R$9:$R$12 >= 1 là où Q > 0
B22: Sélection actuelle (colonne L) | F22: =L14 | H22: =N14 | J22: =M14 | L22: ="contrainte régionale : coût de "&FIXED(J21-J22,0)&" €" | P22: Méthode : Simplex PL (problème linéaire)
P23: Contrôle : remettre L6:L13 à 0 puis lancer le Solveur ; il retrouve la sélection pré-remplie.
B24: ="L'enveloppe permet "&INT(Enveloppe_Audit/Cout_Audit)&" audits, mais seuls "&COUNTIF(J6:J13,">0")&" magasins ont un gain positif : c'est la rentabilité unitaire de l'audit qui limite l'opération, pas le budget. On engage "&FIXED(N14,0)&" € sur "&FIXED(Enveloppe_Audit,0)&" €."
P25: La contrainte régionale s'écrit en pratique sur les seules lignes où Q > 0 (régions présentes parmi les candidats).
B27: Sensibilité du gain net de la sélection — taux de récupération × coût unitaire | L27: Scénarios
B28: récup. ↓ coût → | C28: 30000 | D28: 35000 | E28: 40000 | F28: 45000 | G28: 50000 | H28: 55000 | I28: 60000 | P28: Prudent | Q28: Central | R28: Volontariste
B29: 0.3 | C29: =$B29*SUMPRODUCT($H$6:$H$13,$L$6:$L$13)-C$28*$L$14 | D29: =$B29*SUMPRODUCT($H$6:$H$13,$L$6:$L$13)-D$28*$L$14 | E29: =$B29*SUMPRODUCT($H$6:$H$13,$L$6:$L$13)-E$28*$L$14 | F29: =$B29*SUMPRODUCT($H$6:$H$13,$L$6:$L$13)-F$28*$L$14 | G29: =$B29*SUMPRODUCT($H$6:$H$13,$L$6:$L$13)-G$28*$L$14 | H29: =$B29*SUMPRODUCT($H$6:$H$13,$L$6:$L$13)-H$28*$L$14 | I29: =$B29*SUMPRODUCT($H$6:$H$13,$L$6:$L$13)-I$28*$L$14 | L29: Taux de récupération | P29: 0.4 | Q29: =Taux_Recup | R29: 0.85
B30: 0.4 | C30: =$B30*SUMPRODUCT($H$6:$H$13,$L$6:$L$13)-C$28*$L$14 | D30: =$B30*SUMPRODUCT($H$6:$H$13,$L$6:$L$13)-D$28*$L$14 | E30: =$B30*SUMPRODUCT($H$6:$H$13,$L$6:$L$13)-E$28*$L$14 | F30: =$B30*SUMPRODUCT($H$6:$H$13,$L$6:$L$13)-F$28*$L$14 | G30: =$B30*SUMPRODUCT($H$6:$H$13,$L$6:$L$13)-G$28*$L$14 | H30: =$B30*SUMPRODUCT($H$6:$H$13,$L$6:$L$13)-H$28*$L$14 | I30: =$B30*SUMPRODUCT($H$6:$H$13,$L$6:$L$13)-I$28*$L$14 | L30: Coût unitaire de l'audit | P30: 48000 | Q30: =Cout_Audit | R30: 38000
B31: 0.5 | C31: =$B31*SUMPRODUCT($H$6:$H$13,$L$6:$L$13)-C$28*$L$14 | D31: =$B31*SUMPRODUCT($H$6:$H$13,$L$6:$L$13)-D$28*$L$14 | E31: =$B31*SUMPRODUCT($H$6:$H$13,$L$6:$L$13)-E$28*$L$14 | F31: =$B31*SUMPRODUCT($H$6:$H$13,$L$6:$L$13)-F$28*$L$14 | G31: =$B31*SUMPRODUCT($H$6:$H$13,$L$6:$L$13)-G$28*$L$14 | H31: =$B31*SUMPRODUCT($H$6:$H$13,$L$6:$L$13)-H$28*$L$14 | I31: =$B31*SUMPRODUCT($H$6:$H$13,$L$6:$L$13)-I$28*$L$14 | L31: Baisse des prix d'achat | P31: 0 | Q31: 0 | R31: =Remise_Fournisseur_Volontariste
B32: 0.6 | C32: =$B32*SUMPRODUCT($H$6:$H$13,$L$6:$L$13)-C$28*$L$14 | D32: =$B32*SUMPRODUCT($H$6:$H$13,$L$6:$L$13)-D$28*$L$14 | E32: =$B32*SUMPRODUCT($H$6:$H$13,$L$6:$L$13)-E$28*$L$14 | F32: =$B32*SUMPRODUCT($H$6:$H$13,$L$6:$L$13)-F$28*$L$14 | G32: =$B32*SUMPRODUCT($H$6:$H$13,$L$6:$L$13)-G$28*$L$14 | H32: =$B32*SUMPRODUCT($H$6:$H$13,$L$6:$L$13)-H$28*$L$14 | I32: =$B32*SUMPRODUCT($H$6:$H$13,$L$6:$L$13)-I$28*$L$14 | L32: Gain net de la sélection | P32: =P29*SUMPRODUCT($H$6:$H$13,$L$6:$L$13)-P30*$L$14+P31*SUMPRODUCT($E$6:$E$13*(1-$F$6:$F$13),$L$6:$L$13) | Q32: =Q29*SUMPRODUCT($H$6:$H$13,$L$6:$L$13)-Q30*$L$14+Q31*SUMPRODUCT($E$6:$E$13*(1-$F$6:$F$13),$L$6:$L$13) | R32: =R29*SUMPRODUCT($H$6:$H$13,$L$6:$L$13)-R30*$L$14+R31*SUMPRODUCT($E$6:$E$13*(1-$F$6:$F$13),$L$6:$L$13)
B33: 0.7 | C33: =$B33*SUMPRODUCT($H$6:$H$13,$L$6:$L$13)-C$28*$L$14 | D33: =$B33*SUMPRODUCT($H$6:$H$13,$L$6:$L$13)-D$28*$L$14 | E33: =$B33*SUMPRODUCT($H$6:$H$13,$L$6:$L$13)-E$28*$L$14 | F33: =$B33*SUMPRODUCT($H$6:$H$13,$L$6:$L$13)-F$28*$L$14 | G33: =$B33*SUMPRODUCT($H$6:$H$13,$L$6:$L$13)-G$28*$L$14 | H33: =$B33*SUMPRODUCT($H$6:$H$13,$L$6:$L$13)-H$28*$L$14 | I33: =$B33*SUMPRODUCT($H$6:$H$13,$L$6:$L$13)-I$28*$L$14 | L33: Volontariste : la baisse des prix d'achat s'applique au coût matière des magasins retenus.
B34: 0.8 | C34: =$B34*SUMPRODUCT($H$6:$H$13,$L$6:$L$13)-C$28*$L$14 | D34: =$B34*SUMPRODUCT($H$6:$H$13,$L$6:$L$13)-D$28*$L$14 | E34: =$B34*SUMPRODUCT($H$6:$H$13,$L$6:$L$13)-E$28*$L$14 | F34: =$B34*SUMPRODUCT($H$6:$H$13,$L$6:$L$13)-F$28*$L$14 | G34: =$B34*SUMPRODUCT($H$6:$H$13,$L$6:$L$13)-G$28*$L$14 | H34: =$B34*SUMPRODUCT($H$6:$H$13,$L$6:$L$13)-H$28*$L$14 | I34: =$B34*SUMPRODUCT($H$6:$H$13,$L$6:$L$13)-I$28*$L$14
B35: 0.9 | C35: =$B35*SUMPRODUCT($H$6:$H$13,$L$6:$L$13)-C$28*$L$14 | D35: =$B35*SUMPRODUCT($H$6:$H$13,$L$6:$L$13)-D$28*$L$14 | E35: =$B35*SUMPRODUCT($H$6:$H$13,$L$6:$L$13)-E$28*$L$14 | F35: =$B35*SUMPRODUCT($H$6:$H$13,$L$6:$L$13)-F$28*$L$14 | G35: =$B35*SUMPRODUCT($H$6:$H$13,$L$6:$L$13)-G$28*$L$14 | H35: =$B35*SUMPRODUCT($H$6:$H$13,$L$6:$L$13)-H$28*$L$14 | I35: =$B35*SUMPRODUCT($H$6:$H$13,$L$6:$L$13)-I$28*$L$14 | L35: Valeur cible (résultats attendus)
B36: 1 | C36: =$B36*SUMPRODUCT($H$6:$H$13,$L$6:$L$13)-C$28*$L$14 | D36: =$B36*SUMPRODUCT($H$6:$H$13,$L$6:$L$13)-D$28*$L$14 | E36: =$B36*SUMPRODUCT($H$6:$H$13,$L$6:$L$13)-E$28*$L$14 | F36: =$B36*SUMPRODUCT($H$6:$H$13,$L$6:$L$13)-F$28*$L$14 | G36: =$B36*SUMPRODUCT($H$6:$H$13,$L$6:$L$13)-G$28*$L$14 | H36: =$B36*SUMPRODUCT($H$6:$H$13,$L$6:$L$13)-H$28*$L$14 | I36: =$B36*SUMPRODUCT($H$6:$H$13,$L$6:$L$13)-I$28*$L$14 | L36: Point mort de la sélection (taux de récupération) | R36: =N14/SUMPRODUCT(H6:H13,L6:L13)
L37: ="Taux de coût matière qui ramène "&B6&" au seuil d'alerte" | R37: =1-D_Seuil_Taux_Alerte
B38: ="Point mort de la sélection : "&FIXED(N14/SUMPRODUCT(H6:H13,L6:L13)*100,1)&" % de récupération au coût central. Au coût maximal de la grille, il faut "&FIXED(MAX(C28:I28)*L14/SUMPRODUCT(H6:H13,L6:L13)*100,1)&" %." | L38: ="Taux de coût matière actuel de "&B6 | R38: =1-F6
B39: Grille écrite en formules explicites, équivalente à une table de données à deux entrées.
B41: Monte-Carlo — 1 000 tirages du taux de récupération (feuille MONTE_CARLO)
B42: Gain net moyen | E42: =AVERAGE(MONTE_CARLO!$S$4:$S$1003) | H42: Classe (gain net) | I42: Tirages
B43: Écart-type | E43: =STDEV(MONTE_CARLO!$S$4:$S$1003) | H43: -100000 | I43: =COUNTIFS(MONTE_CARLO!$S$4:$S$1003,"<="&H43,MONTE_CARLO!$S$4:$S$1003,">"&-1E+12)
B44: Percentile 10 % | E44: =PERCENTILE(MONTE_CARLO!$S$4:$S$1003,0.1) | H44: -75000 | I44: =COUNTIFS(MONTE_CARLO!$S$4:$S$1003,"<="&H44,MONTE_CARLO!$S$4:$S$1003,">"&H43)
B45: Médiane | E45: =PERCENTILE(MONTE_CARLO!$S$4:$S$1003,0.5) | H45: -50000 | I45: =COUNTIFS(MONTE_CARLO!$S$4:$S$1003,"<="&H45,MONTE_CARLO!$S$4:$S$1003,">"&H44)
B46: Percentile 90 % | E46: =PERCENTILE(MONTE_CARLO!$S$4:$S$1003,0.9) | H46: -25000 | I46: =COUNTIFS(MONTE_CARLO!$S$4:$S$1003,"<="&H46,MONTE_CARLO!$S$4:$S$1003,">"&H45)
B47: Probabilité de perte | E47: =COUNTIF(MONTE_CARLO!$S$4:$S$1003,"<0")/COUNT(MONTE_CARLO!$S$4:$S$1003) | H47: 0 | I47: =COUNTIFS(MONTE_CARLO!$S$4:$S$1003,"<="&H47,MONTE_CARLO!$S$4:$S$1003,">"&H46)
B48: Recalcul : F9. Chaque tirage tire un taux par magasin, loi normale tronquée à [0 ; 1]. | H48: 25000 | I48: =COUNTIFS(MONTE_CARLO!$S$4:$S$1003,"<="&H48,MONTE_CARLO!$S$4:$S$1003,">"&H47)
H49: 50000 | I49: =COUNTIFS(MONTE_CARLO!$S$4:$S$1003,"<="&H49,MONTE_CARLO!$S$4:$S$1003,">"&H48)
H50: 75000 | I50: =COUNTIFS(MONTE_CARLO!$S$4:$S$1003,"<="&H50,MONTE_CARLO!$S$4:$S$1003,">"&H49)
H51: 100000 | I51: =COUNTIFS(MONTE_CARLO!$S$4:$S$1003,"<="&H51,MONTE_CARLO!$S$4:$S$1003,">"&H50)
H52: 125000 | I52: =COUNTIFS(MONTE_CARLO!$S$4:$S$1003,"<="&H52,MONTE_CARLO!$S$4:$S$1003,">"&H51)
H53: 150000 | I53: =COUNTIFS(MONTE_CARLO!$S$4:$S$1003,"<="&H53,MONTE_CARLO!$S$4:$S$1003,">"&H52)
H54: 175000 | I54: =COUNTIFS(MONTE_CARLO!$S$4:$S$1003,"<="&H54,MONTE_CARLO!$S$4:$S$1003,">"&H53)
H55: 200000 | I55: =COUNTIFS(MONTE_CARLO!$S$4:$S$1003,"<="&H55,MONTE_CARLO!$S$4:$S$1003,">"&H54)
H56: > 200 000 | I56: =COUNTIF(MONTE_CARLO!$S$4:$S$1003,">"&H55)
B59: Recommandation
B60: ="Recommandation : auditer "&L14&" magasins pour "&FIXED(N14,0)&" €. Gain net attendu "&FIXED(E42,0)&" €, entre "&FIXED(E44,0)&" € et "&FIXED(E46,0)&" € dans 80 % des cas, avec "&FIXED(E47*100,1)&" % de risque de perte. Les candidats non retenus ne se traitent pas par un audit : ils se surveillent."

Sheet MONTE_CARLO
A1: MONTE_CARLO — 1 000 tirages (fonctions volatiles : F9 pour relancer)
B2: Taux de récupération tirés | J2: Gain net par magasin (si retenu)
A3: Tirage | B3: ="r "&SIMULATEUR!B6 | C3: ="r "&SIMULATEUR!B7 | D3: ="r "&SIMULATEUR!B8 | E3: ="r "&SIMULATEUR!B9 | F3: ="r "&SIMULATEUR!B10 | G3: ="r "&SIMULATEUR!B11 | H3: ="r "&SIMULATEUR!B12 | I3: ="r "&SIMULATEUR!B13 | J3: ="gain "&SIMULATEUR!B6 | K3: ="gain "&SIMULATEUR!B7 | L3: ="gain "&SIMULATEUR!B8 | M3: ="gain "&SIMULATEUR!B9 | N3: ="gain "&SIMULATEUR!B10 | O3: ="gain "&SIMULATEUR!B11 | P3: ="gain "&SIMULATEUR!B12 | Q3: ="gain "&SIMULATEUR!B13 | S3: Gain total
A4: 1 | B4: =MAX(0,MIN(1,NORMINV(RAND(),Taux_Recup,Ecart_Type_Recup))) | C4: =MAX(0,MIN(1,NORMINV(RAND(),Taux_Recup,Ecart_Type_Recup))) | D4: =MAX(0,MIN(1,NORMINV(RAND(),Taux_Recup,Ecart_Type_Recup))) | E4: =MAX(0,MIN(1,NORMINV(RAND(),Taux_Recup,Ecart_Type_Recup))) | F4: =MAX(0,MIN(1,NORMINV(RAND(),Taux_Recup,Ecart_Type_Recup))) | G4: =MAX(0,MIN(1,NORMINV(RAND(),Taux_Recup,Ecart_Type_Recup))) | H4: =MAX(0,MIN(1,NORMINV(RAND(),Taux_Recup,Ecart_Type_Recup))) | I4: =MAX(0,MIN(1,NORMINV(RAND(),Taux_Recup,Ecart_Type_Recup))) | J4: =SIMULATEUR!$L$6*(SIMULATEUR!$H$6*B4-Cout_Audit) | K4: =SIMULATEUR!$L$7*(SIMULATEUR!$H$7*C4-Cout_Audit) | L4: =SIMULATEUR!$L$8*(SIMULATEUR!$H$8*D4-Cout_Audit) | M4: =SIMULATEUR!$L$9*(SIMULATEUR!$H$9*E4-Cout_Audit) | N4: =SIMULATEUR!$L$10*(SIMULATEUR!$H$10*F4-Cout_Audit) | O4: =SIMULATEUR!$L$11*(SIMULATEUR!$H$11*G4-Cout_Audit) | P4: =SIMULATEUR!$L$12*(SIMULATEUR!$H$12*H4-Cout_Audit) | Q4: =SIMULATEUR!$L$13*(SIMULATEUR!$H$13*I4-Cout_Audit) | S4: =SUM(J4:Q4)
A5: 2 | B5: =MAX(0,MIN(1,NORMINV(RAND(),Taux_Recup,Ecart_Type_Recup))) | C5: =MAX(0,MIN(1,NORMINV(RAND(),Taux_Recup,Ecart_Type_Recup))) | D5: =MAX(0,MIN(1,NORMINV(RAND(),Taux_Recup,Ecart_Type_Recup))) | E5: =MAX(0,MIN(1,NORMINV(RAND(),Taux_Recup,Ecart_Type_Recup))) | F5: =MAX(0,MIN(1,NORMINV(RAND(),Taux_Recup,Ecart_Type_Recup))) | G5: =MAX(0,MIN(1,NORMINV(RAND(),Taux_Recup,Ecart_Type_Recup))) | H5: =MAX(0,MIN(1,NORMINV(RAND(),Taux_Recup,Ecart_Type_Recup))) | I5: =MAX(0,MIN(1,NORMINV(RAND(),Taux_Recup,Ecart_Type_Recup))) | J5: =SIMULATEUR!$L$6*(SIMULATEUR!$H$6*B5-Cout_Audit) | K5: =SIMULATEUR!$L$7*(SIMULATEUR!$H$7*C5-Cout_Audit) | L5: =SIMULATEUR!$L$8*(SIMULATEUR!$H$8*D5-Cout_Audit) | M5: =SIMULATEUR!$L$9*(SIMULATEUR!$H$9*E5-Cout_Audit) | N5: =SIMULATEUR!$L$10*(SIMULATEUR!$H$10*F5-Cout_Audit) | O5: =SIMULATEUR!$L$11*(SIMULATEUR!$H$11*G5-Cout_Audit) | P5: =SIMULATEUR!$L$12*(SIMULATEUR!$H$12*H5-Cout_Audit) | Q5: =SIMULATEUR!$L$13*(SIMULATEUR!$H$13*I5-Cout_Audit) | S5: =SUM(J5:Q5)
A6: 3 | B6: =MAX(0,MIN(1,NORMINV(RAND(),Taux_Recup,Ecart_Type_Recup))) | C6: =MAX(0,MIN(1,NORMINV(RAND(),Taux_Recup,Ecart_Type_Recup))) | D6: =MAX(0,MIN(1,NORMINV(RAND(),Taux_Recup,Ecart_Type_Recup))) | E6: =MAX(0,MIN(1,NORMINV(RAND(),Taux_Recup,Ecart_Type_Recup))) | F6: =MAX(0,MIN(1,NORMINV(RAND(),Taux_Recup,Ecart_Type_Recup))) | G6: =MAX(0,MIN(1,NORMINV(RAND(),Taux_Recup,Ecart_Type_Recup))) | H6: =MAX(0,MIN(1,NORMINV(RAND(),Taux_Recup,Ecart_Type_Recup))) | I6: =MAX(0,MIN(1,NORMINV(RAND(),Taux_Recup,Ecart_Type_Recup))) | J6: =SIMULATEUR!$L$6*(SIMULATEUR!$H$6*B6-Cout_Audit) | K6: =SIMULATEUR!$L$7*(SIMULATEUR!$H$7*C6-Cout_Audit) | L6: =SIMULATEUR!$L$8*(SIMULATEUR!$H$8*D6-Cout_Audit) | M6: =SIMULATEUR!$L$9*(SIMULATEUR!$H$9*E6-Cout_Audit) | N6: =SIMULATEUR!$L$10*(SIMULATEUR!$H$10*F6-Cout_Audit) | O6: =SIMULATEUR!$L$11*(SIMULATEUR!$H$11*G6-Cout_Audit) | P6: =SIMULATEUR!$L$12*(SIMULATEUR!$H$12*H6-Cout_Audit) | Q6: =SIMULATEUR!$L$13*(SIMULATEUR!$H$13*I6-Cout_Audit) | S6: =SUM(J6:Q6)
A7: 4 | B7: =MAX(0,MIN(1,NORMINV(RAND(),Taux_Recup,Ecart_Type_Recup))) | C7: =MAX(0,MIN(1,NORMINV(RAND(),Taux_Recup,Ecart_Type_Recup))) | D7: =MAX(0,MIN(1,NORMINV(RAND(),Taux_Recup,Ecart_Type_Recup))) | E7: =MAX(0,MIN(1,NORMINV(RAND(),Taux_Recup,Ecart_Type_Recup))) | F7: =MAX(0,MIN(1,NORMINV(RAND(),Taux_Recup,Ecart_Type_Recup))) | G7: =MAX(0,MIN(1,NORMINV(RAND(),Taux_Recup,Ecart_Type_Recup))) | H7: =MAX(0,MIN(1,NORMINV(RAND(),Taux_Recup,Ecart_Type_Recup))) | I7: =MAX(0,MIN(1,NORMINV(RAND(),Taux_Recup,Ecart_Type_Recup))) | J7: =SIMULATEUR!$L$6*(SIMULATEUR!$H$6*B7-Cout_Audit) | K7: =SIMULATEUR!$L$7*(SIMULATEUR!$H$7*C7-Cout_Audit) | L7: =SIMULATEUR!$L$8*(SIMULATEUR!$H$8*D7-Cout_Audit) | M7: =SIMULATEUR!$L$9*(SIMULATEUR!$H$9*E7-Cout_Audit) | N7: =SIMULATEUR!$L$10*(SIMULATEUR!$H$10*F7-Cout_Audit) | O7: =SIMULATEUR!$L$11*(SIMULATEUR!$H$11*G7-Cout_Audit) | P7: =SIMULATEUR!$L$12*(SIMULATEUR!$H$12*H7-Cout_Audit) | Q7: =SIMULATEUR!$L$13*(SIMULATEUR!$H$13*I7-Cout_Audit) | S7: =SUM(J7:Q7)
A8: 5 | B8: =MAX(0,MIN(1,NORMINV(RAND(),Taux_Recup,Ecart_Type_Recup))) | C8: =MAX(0,MIN(1,NORMINV(RAND(),Taux_Recup,Ecart_Type_Recup))) | D8: =MAX(0,MIN(1,NORMINV(RAND(),Taux_Recup,Ecart_Type_Recup))) | E8: =MAX(0,MIN(1,NORMINV(RAND(),Taux_Recup,Ecart_Type_Recup))) | F8: =MAX(0,MIN(1,NORMINV(RAND(),Taux_Recup,Ecart_Type_Recup))) | G8: =MAX(0,MIN(1,NORMINV(RAND(),Taux_Recup,Ecart_Type_Recup))) | H8: =MAX(0,MIN(1,NORMINV(RAND(),Taux_Recup,Ecart_Type_Recup))) | I8: =MAX(0,MIN(1,NORMINV(RAND(),Taux_Recup,Ecart_Type_Recup))) | J8: =SIMULATEUR!$L$6*(SIMULATEUR!$H$6*B8-Cout_Audit) | K8: =SIMULATEUR!$L$7*(SIMULATEUR!$H$7*C8-Cout_Audit) | L8: =SIMULATEUR!$L$8*(SIMULATEUR!$H$8*D8-Cout_Audit) | M8: =SIMULATEUR!$L$9*(SIMULATEUR!$H$9*E8-Cout_Audit) | N8: =SIMULATEUR!$L$10*(SIMULATEUR!$H$10*F8-Cout_Audit) | O8: =SIMULATEUR!$L$11*(SIMULATEUR!$H$11*G8-Cout_Audit) | P8: =SIMULATEUR!$L$12*(SIMULATEUR!$H$12*H8-Cout_Audit) | Q8: =SIMULATEUR!$L$13*(SIMULATEUR!$H$13*I8-Cout_Audit) | S8: =SUM(J8:Q8)
A9: 6 | B9: =MAX(0,MIN(1,NORMINV(RAND(),Taux_Recup,Ecart_Type_Recup))) | C9: =MAX(0,MIN(1,NORMINV(RAND(),Taux_Recup,Ecart_Type_Recup))) | D9: =MAX(0,MIN(1,NORMINV(RAND(),Taux_Recup,Ecart_Type_Recup))) | E9: =MAX(0,MIN(1,NORMINV(RAND(),Taux_Recup,Ecart_Type_Recup))) | F9: =MAX(0,MIN(1,NORMINV(RAND(),Taux_Recup,Ecart_Type_Recup))) | G9: =MAX(0,MIN(1,NORMINV(RAND(),Taux_Recup,Ecart_Type_Recup))) | H9: =MAX(0,MIN(1,NORMINV(RAND(),Taux_Recup,Ecart_Type_Recup))) | I9: =MAX(0,MIN(1,NORMINV(RAND(),Taux_Recup,Ecart_Type_Recup))) | J9: =SIMULATEUR!$L$6*(SIMULATEUR!$H$6*B9-Cout_Audit) | K9: =SIMULATEUR!$L$7*(SIMULATEUR!$H$7*C9-Cout_Audit) | L9: =SIMULATEUR!$L$8*(SIMULATEUR!$H$8*D9-Cout_Audit) | M9: =SIMULATEUR!$L$9*(SIMULATEUR!$H$9*E9-Cout_Audit) | N9: =SIMULATEUR!$L$10*(SIMULATEUR!$H$10*F9-Cout_Audit) | O9: =SIMULATEUR!$L$11*(SIMULATEUR!$H$11*G9-Cout_Audit) | P9: =SIMULATEUR!$L$12*(SIMULATEUR!$H$12*H9-Cout_Audit) | Q9: =SIMULATEUR!$L$13*(SIMULATEUR!$H$13*I9-Cout_Audit) | S9: =SUM(J9:Q9)
A10: 7 | B10: =MAX(0,MIN(1,NORMINV(RAND(),Taux_Recup,Ecart_Type_Recup))) | C10: =MAX(0,MIN(1,NORMINV(RAND(),Taux_Recup,Ecart_Type_Recup))) | D10: =MAX(0,MIN(1,NORMINV(RAND(),Taux_Recup,Ecart_Type_Recup))) | E10: =MAX(0,MIN(1,NORMINV(RAND(),Taux_Recup,Ecart_Type_Recup))) | F10: =MAX(0,MIN(1,NORMINV(RAND(),Taux_Recup,Ecart_Type_Recup))) | G10: =MAX(0,MIN(1,NORMINV(RAND(),Taux_Recup,Ecart_Type_Recup))) | H10: =MAX(0,MIN(1,NORMINV(RAND(),Taux_Recup,Ecart_Type_Recup))) | I10: =MAX(0,MIN(1,NORMINV(RAND(),Taux_Recup,Ecart_Type_Recup))) | J10: =SIMULATEUR!$L$6*(SIMULATEUR!$H$6*B10-Cout_Audit) | K10: =SIMULATEUR!$L$7*(SIMULATEUR!$H$7*C10-Cout_Audit) | L10: =SIMULATEUR!$L$8*(SIMULATEUR!$H$8*D10-Cout_Audit) | M10: =SIMULATEUR!$L$9*(SIMULATEUR!$H$9*E10-Cout_Audit) | N10: =SIMULATEUR!$L$10*(SIMULATEUR!$H$10*F10-Cout_Audit) | O10: =SIMULATEUR!$L$11*(SIMULATEUR!$H$11*G10-Cout_Audit) | P10: =SIMULATEUR!$L$12*(SIMULATEUR!$H$12*H10-Cout_Audit) | Q10: =SIMULATEUR!$L$13*(SIMULATEUR!$H$13*I10-Cout_Audit) | S10: =SUM(J10:Q10)
A11: 8 | B11: =MAX(0,MIN(1,NORMINV(RAND(),Taux_Recup,Ecart_Type_Recup))) | C11: =MAX(0,MIN(1,NORMINV(RAND(),Taux_Recup,Ecart_Type_Recup))) | D11: =MAX(0,MIN(1,NORMINV(RAND(),Taux_Recup,Ecart_Type_Recup))) | E11: =MAX(0,MIN(1,NORMINV(RAND(),Taux_Recup,Ecart_Type_Recup))) | F11: =MAX(0,MIN(1,NORMINV(RAND(),Taux_Recup,Ecart_Type_Recup))) | G11: =MAX(0,MIN(1,NORMINV(RAND(),Taux_Recup,Ecart_Type_Recup))) | H11: =MAX(0,MIN(1,NORMINV(RAND(),Taux_Recup,Ecart_Type_Recup))) | I11: =MAX(0,MIN(1,NORMINV(RAND(),Taux_Recup,Ecart_Type_Recup))) | J11: =SIMULATEUR!$L$6*(SIMULATEUR!$H$6*B11-Cout_Audit) | K11: =SIMULATEUR!$L$7*(SIMULATEUR!$H$7*C11-Cout_Audit) | L11: =SIMULATEUR!$L$8*(SIMULATEUR!$H$8*D11-Cout_Audit) | M11: =SIMULATEUR!$L$9*(SIMULATEUR!$H$9*E11-Cout_Audit) | N11: =SIMULATEUR!$L$10*(SIMULATEUR!$H$10*F11-Cout_Audit) | O11: =SIMULATEUR!$L$11*(SIMULATEUR!$H$11*G11-Cout_Audit) | P11: =SIMULATEUR!$L$12*(SIMULATEUR!$H$12*H11-Cout_Audit) | Q11: =SIMULATEUR!$L$13*(SIMULATEUR!$H$13*I11-Cout_Audit) | S11: =SUM(J11:Q11)
A12: 9 | B12: =MAX(0,MIN(1,NORMINV(RAND(),Taux_Recup,Ecart_Type_Recup))) | C12: =MAX(0,MIN(1,NORMINV(RAND(),Taux_Recup,Ecart_Type_Recup))) | D12: =MAX(0,MIN(1,NORMINV(RAND(),Taux_Recup,Ecart_Type_Recup))) | E12: =MAX(0,MIN(1,NORMINV(RAND(),Taux_Recup,Ecart_Type_Recup))) | F12: =MAX(0,MIN(1,NORMINV(RAND(),Taux_Recup,Ecart_Type_Recup))) | G12: =MAX(0,MIN(1,NORMINV(RAND(),Taux_Recup,Ecart_Type_Recup))) | H12: =MAX(0,MIN(1,NORMINV(RAND(),Taux_Recup,Ecart_Type_Recup))) | I12: =MAX(0,MIN(1,NORMINV(RAND(),Taux_Recup,Ecart_Type_Recup))) | J12: =SIMULATEUR!$L$6*(SIMULATEUR!$H$6*B12-Cout_Audit) | K12: =SIMULATEUR!$L$7*(SIMULATEUR!$H$7*C12-Cout_Audit) | L12: =SIMULATEUR!$L$8*(SIMULATEUR!$H$8*D12-Cout_Audit) | M12: =SIMULATEUR!$L$9*(SIMULATEUR!$H$9*E12-Cout_Audit) | N12: =SIMULATEUR!$L$10*(SIMULATEUR!$H$10*F12-Cout_Audit) | O12: =SIMULATEUR!$L$11*(SIMULATEUR!$H$11*G12-Cout_Audit) | P12: =SIMULATEUR!$L$12*(SIMULATEUR!$H$12*H12-Cout_Audit) | Q12: =SIMULATEUR!$L$13*(SIMULATEUR!$H$13*I12-Cout_Audit) | S12: =SUM(J12:Q12)
A13: 10 | B13: =MAX(0,MIN(1,NORMINV(RAND(),Taux_Recup,Ecart_Type_Recup))) | C13: =MAX(0,MIN(1,NORMINV(RAND(),Taux_Recup,Ecart_Type_Recup))) | D13: =MAX(0,MIN(1,NORMINV(RAND(),Taux_Recup,Ecart_Type_Recup))) | E13: =MAX(0,MIN(1,NORMINV(RAND(),Taux_Recup,Ecart_Type_Recup))) | F13: =MAX(0,MIN(1,NORMINV(RAND(),Taux_Recup,Ecart_Type_Recup))) | G13: =MAX(0,MIN(1,NORMINV(RAND(),Taux_Recup,Ecart_Type_Recup))) | H13: =MAX(0,MIN(1,NORMINV(RAND(),Taux_Recup,Ecart_Type_Recup))) | I13: =MAX(0,MIN(1,NORMINV(RAND(),Taux_Recup,Ecart_Type_Recup))) | J13: =SIMULATEUR!$L$6*(SIMULATEUR!$H$6*B13-Cout_Audit) | K13: =SIMULATEUR!$L$7*(SIMULATEUR!$H$7*C13-Cout_Audit) | L13: =SIMULATEUR!$L$8*(SIMULATEUR!$H$8*D13-Cout_Audit) | M13: =SIMULATEUR!$L$9*(SIMULATEUR!$H$9*E13-Cout_Audit) | N13: =SIMULATEUR!$L$10*(SIMULATEUR!$H$10*F13-Cout_Audit) | O13: =SIMULATEUR!$L$11*(SIMULATEUR!$H$11*G13-Cout_Audit) | P13: =SIMULATEUR!$L$12*(SIMULATEUR!$H$12*H13-Cout_Audit) | Q13: =SIMULATEUR!$L$13*(SIMULATEUR!$H$13*I13-Cout_Audit) | S13: =SUM(J13:Q13)
A14: 11 | B14: =MAX(0,MIN(1,NORMINV(RAND(),Taux_Recup,Ecart_Type_Recup))) | C14: =MAX(0,MIN(1,NORMINV(RAND(),Taux_Recup,Ecart_Type_Recup))) | D14: =MAX(0,MIN(1,NORMINV(RAND(),Taux_Recup,Ecart_Type_Recup))) | E14: =MAX(0,MIN(1,NORMINV(RAND(),Taux_Recup,Ecart_Type_Recup))) | F14: =MAX(0,MIN(1,NORMINV(RAND(),Taux_Recup,Ecart_Type_Recup))) | G14: =MAX(0,MIN(1,NORMINV(RAND(),Taux_Recup,Ecart_Type_Recup))) | H14: =MAX(0,MIN(1,NORMINV(RAND(),Taux_Recup,Ecart_Type_Recup))) | I14: =MAX(0,MIN(1,NORMINV(RAND(),Taux_Recup,Ecart_Type_Recup))) | J14: =SIMULATEUR!$L$6*(SIMULATEUR!$H$6*B14-Cout_Audit) | K14: =SIMULATEUR!$L$7*(SIMULATEUR!$H$7*C14-Cout_Audit) | L14: =SIMULATEUR!$L$8*(SIMULATEUR!$H$8*D14-Cout_Audit) | M14: =SIMULATEUR!$L$9*(SIMULATEUR!$H$9*E14-Cout_Audit) | N14: =SIMULATEUR!$L$10*(SIMULATEUR!$H$10*F14-Cout_Audit) | O14: =SIMULATEUR!$L$11*(SIMULATEUR!$H$11*G14-Cout_Audit) | P14: =SIMULATEUR!$L$12*(SIMULATEUR!$H$12*H14-Cout_Audit) | Q14: =SIMULATEUR!$L$13*(SIMULATEUR!$H$13*I14-Cout_Audit) | S14: =SUM(J14:Q14)
A15: 12 | B15: =MAX(0,MIN(1,NORMINV(RAND(),Taux_Recup,Ecart_Type_Recup))) | C15: =MAX(0,MIN(1,NORMINV(RAND(),Taux_Recup,Ecart_Type_Recup))) | D15: =MAX(0,MIN(1,NORMINV(RAND(),Taux_Recup,Ecart_Type_Recup))) | E15: =MAX(0,MIN(1,NORMINV(RAND(),Taux_Recup,Ecart_Type_Recup))) | F15: =MAX(0,MIN(1,NORMINV(RAND(),Taux_Recup,Ecart_Type_Recup))) | G15: =MAX(0,MIN(1,NORMINV(RAND(),Taux_Recup,Ecart_Type_Recup))) | H15: =MAX(0,MIN(1,NORMINV(RAND(),Taux_Recup,Ecart_Type_Recup))) | I15: =MAX(0,MIN(1,NORMINV(RAND(),Taux_Recup,Ecart_Type_Recup))) | J15: =SIMULATEUR!$L$6*(SIMULATEUR!$H$6*B15-Cout_Audit) | K15: =SIMULATEUR!$L$7*(SIMULATEUR!$H$7*C15-Cout_Audit) | L15: =SIMULATEUR!$L$8*(SIMULATEUR!$H$8*D15-Cout_Audit) | M15: =SIMULATEUR!$L$9*(SIMULATEUR!$H$9*E15-Cout_Audit) | N15: =SIMULATEUR!$L$10*(SIMULATEUR!$H$10*F15-Cout_Audit) | O15: =SIMULATEUR!$L$11*(SIMULATEUR!$H$11*G15-Cout_Audit) | P15: =SIMULATEUR!$L$12*(SIMULATEUR!$H$12*H15-Cout_Audit) | Q15: =SIMULATEUR!$L$13*(SIMULATEUR!$H$13*I15-Cout_Audit) | S15: =SUM(J15:Q15)
... A1003: 1000 | B1003: =MAX(0,MIN(1,NORMINV(RAND(),Taux_Recup,Ecart_Type_Recup))) | C1003: =MAX(0,MIN(1,NORMINV(RAND(),Taux_Recup,Ecart_Type_Recup))) | D1003: =MAX(0,MIN(1,NORMINV(RAND(),Taux_Recup,Ecart_Type_Recup))) | E1003: =MAX(0,MIN(1,NORMINV(RAND(),Taux_Recup,Ecart_Type_Recup))) | F1003: =MAX(0,MIN(1,NORMINV(RAND(),Taux_Recup,Ecart_Type_Recup))) | G1003: =MAX(0,MIN(1,NORMINV(RAND(),Taux_Recup,Ecart_Type_Recup))) | H1003: =MAX(0,MIN(1,NORMINV(RAND(),Taux_Recup,Ecart_Type_Recup))) | I1003: =MAX(0,MIN(1,NORMINV(RAND(),Taux_Recup,Ecart_Type_Recup))) | J1003: =SIMULATEUR!$L$6*(SIMULATEUR!$H$6*B1003-Cout_Audit) | K1003: =SIMULATEUR!$L$7*(SIMULATEUR!$H$7*C1003-Cout_Audit) | L1003: =SIMULATEUR!$L$8*(SIMULATEUR!$H$8*D1003-Cout_Audit) | M1003: =SIMULATEUR!$L$9*(SIMULATEUR!$H$9*E1003-Cout_Audit) | N1003: =SIMULATEUR!$L$10*(SIMULATEUR!$H$10*F1003-Cout_Audit) | O1003: =SIMULATEUR!$L$11*(SIMULATEUR!$H$11*G1003-Cout_Audit) | P1003: =SIMULATEUR!$L$12*(SIMULATEUR!$H$12*H1003-Cout_Audit) | Q1003: =SIMULATEUR!$L$13*(SIMULATEUR!$H$13*I1003-Cout_Audit) | S1003: =SUM(J1003:Q1003)

Sheet PARAMETRES
B1: PARAMÈTRES — toutes les constantes du classeur
B2: Aucune formule du classeur ne contient de valeur en dur : seuils, dates et hypothèses vivent ici. Cellules en bleu sur fond jaune = saisissables.
B4: Cle | C4: Valeur | D4: Type | E4: Description
B5: Périmètre temporel
B6: Exercice_Courant | C6: 2025/26 | D6: Texte | E6: Exercice analysé (septembre → août).
B7: Exercice_Precedent | C7: 2024/25 | D7: Texte | E7: Exercice de comparaison N-1.
B8: Debut_Exercice | C8: 45901 | D8: Date | E8: Premier mois de l'exercice courant.
B9: Fin_Exercice | C9: 46265 | D9: Date | E9: Dernier jour de l'exercice courant.
B10: Debut_N1 | C10: 45536 | D10: Date | E10: Premier jour de l'exercice précédent. Sert aussi au périmètre comparable.
B11: Budget_Debut | C11: 46023 | D11: Date | E11: Premier mois du budget comparé (budget en année civile).
B12: Budget_Fin | C12: 46235 | D12: Date | E12: Dernier mois disponible du budget comparé.
B13: Periode_A_Debut | C13: 45536 | D13: Date | E13: Constat n°1 : début de la période de référence (sept.–déc. 2024).
B14: Periode_A_Fin | C14: 45627 | D14: Date | E14: Constat n°1 : fin de la période de référence.
B15: Periode_B_Debut | C15: 46023 | D15: Date | E15: Constat n°1 : début de la période récente (janv.–août 2026).
B16: Periode_B_Fin | C16: 46235 | D16: Date | E16: Constat n°1 : fin de la période récente.
B17: Seuils d'alerte
B18: Seuil_Alerte_Marge_Pt | C18: 0.02 | D18: Fraction | E18: Écart de taux de marge sous le réseau qui déclenche l'alerte (2 pt).
B19: Seuil_Derive_Marge_Pt | C19: -2 | D19: Points | E19: Recul de taux de marge entre périodes A et B qui classe un magasin « en dérive ».
B20: Seuil_Perte_Multiple_Mediane | C20: 2 | D20: Multiple | E20: Taux de perte anormal = plus de 2 fois la médiane du réseau. Un seuil fixe à 4 % manquerait HC-012 (3,45 %).
B21: Seuil_Atteinte_Budget | C21: 0.9 | D21: Fraction | E21: Atteinte budget sous laquelle un magasin est « sous objectif ».
B22: Seuil_Atteinte_Haute | C22: 1.05 | D22: Fraction | E22: Atteinte budget au-dessus de laquelle un magasin dépasse nettement l'objectif.
B23: Tolerance_Prix_Achat | C23: 0.01 | D23: Fraction | E23: Écart d'indice de prix d'achat au réseau toléré avant d'en faire une cause (±1 %).
B24: Tolerance_Mix_Livraison | C24: 0.05 | D24: Fraction | E24: Écart de part livraison au réseau toléré avant d'en faire une cause (±5 pt).
B25: Règles de gestion
B26: Taux_TVA_Restauration | C26: 0.1 | D26: Fraction | E26: TVA restauration. Alcools : 20 %.
B27: Hausse_Tarifaire | C27: 0.045 | D27: Fraction | E27: Hausse de prix appliquée au 01/09/2025. Source : REF_PRODUITS / Historique_Prix du référentiel.
B28: Date_Hausse_Tarifaire | C28: 45901 | D28: Date | E28: Date d'effet de la hausse tarifaire.
B29: Plafond_Remise | C29: 0.08 | D29: Fraction | E29: Remise maximale admise sur un relevé (contrôle du UserForm).
B30: Ratio_Articles_Min | C30: 1.8 | D30: Nombre | E30: Articles par ticket minimum plausible (contrôle de saisie).
B31: Ratio_Articles_Max | C31: 3.4 | D31: Nombre | E31: Articles par ticket maximum plausible (contrôle de saisie).
B32: Simulateur
B33: Cout_Audit | C33: 42000 | D33: Euros | E33: Coût d'un audit de cuisine par magasin : déplacement, formation, deux jours d'exploitation dégradée.
B34: Taux_Recup | C34: 0.65 | D34: Fraction | E34: Part de l'écart de marge récupérée par l'audit — scénario central.
B35: Ecart_Type_Recup | C35: 0.18 | D35: Fraction | E35: Incertitude sur le taux de récupération (écart-type de la loi normale, Monte-Carlo).
B36: Enveloppe_Audit | C36: 260000 | D36: Euros | E36: Budget disponible pour les audits.
B37: Remise_Fournisseur_Volontariste | C37: 0.015 | D37: Fraction | E37: Baisse des prix d'achat obtenue en renégociation (scénario volontariste).
B38: Couche VBA (à renseigner sur votre poste)
B39: Chemin_Donnees | C39: [À RENSEIGNER] C:\...\Horizon_Contrat\ | D39: Texte | E39: Dossier des fichiers sources. Lu par Power Query et par le VBA.
B40: Chemin_Sorties | C40: [À RENSEIGNER] C:\...\Sorties\ | D40: Texte | E40: Dossier où le VBA écrit les PDF.
B41: Mode_Envoi_Reel | C41: FALSE | D41: Booléen | E41: FAUX = les messages vont dans les brouillons Outlook. Ne passer à VRAI qu'une fois tout testé.
B43: Légende : texte bleu sur fond jaune = valeur saisissable. Toute autre cellule du classeur est une formule.

Sheet QUALITE
B1: QUALITÉ DES DONNÉES — ce que le nettoyage a trouvé et corrigé
B2: Section 1 : résultats du nettoyage (valeurs produites par le traitement, figées). Section 2 : contrôles recalculés en direct sur les feuilles DATA_*.
B4: 1. Résultats du nettoyage — fichiers sources
B5: Contrôle | C5: Valeur | D5: Traitement appliqué
B6: Lignes de ventes lues (24 fichiers) | C6: 289506 | D6: Lecture du dossier 02_Ventes, dates et décimales converties selon le format détecté ligne à ligne.
B7: Doublons stricts retirés | C7: 240 | D7: Tous dans Ventes_2025-07. Grain magasin × jour × canal : une combinaison ne peut pas apparaître deux fois.
B8: Lignes sans code magasin rejetées | C8: 422 | D8: Non récupérables. Détail par fichier ci-dessous.
B9: Lignes de ventes conservées | C9: 288844 | D9: Agrégées au mois dans DATA_VENTES.
B10: Fichiers au format de date JJ/MM/AAAA | C10: 3 | D10: Ventes_2024-11, Ventes_2025-04, Ventes_2026-01.
B11: Fichiers à virgule décimale | C11: 2 | D11: Ventes_2025-02, Ventes_2026-05.
B12: Doublons dans la feuille Magasins | C12: 2 | D12: Retirés : 122 → 120 magasins.
B13: Villes en casse incohérente corrigées | C13: 9 | D13: Casse de titre, particules en minuscule (Aix-en-Provence).
B14: Taux horaires stockés en texte | C14: 327 | D14: Convertis (symbole €, espace insécable, virgule), Moyenne après conversion : 13,82 €,
B15: Commandes sans date de livraison | C15: 2251 | D15: Conservées, exclues des calculs de retard (null, pas zéro).
B16: Lignes de budget après dépivotage | C16: 2880 | D16: 120 magasins × 12 mois × 2 années.
B19: Rejets par fichier (codes magasin vides)
B20: Fichier | C20: Lignes rejetées
B21: Ventes_2024-09.csv | C21: 17
B22: Ventes_2024-10.csv | C22: 18
B23: Ventes_2024-11.csv | C23: 17
B24: Ventes_2024-12.csv | C24: 18
B25: Ventes_2025-01.csv | C25: 18
B26: Ventes_2025-02.csv | C26: 16
B27: Ventes_2025-03.csv | C27: 18
B28: Ventes_2025-04.csv | C28: 17
B29: Ventes_2025-05.csv | C29: 18
B30: Ventes_2025-06.csv | C30: 17
B31: Ventes_2025-07.csv | C31: 18
B32: Ventes_2025-08.csv | C32: 18
... B44: Ventes_2026-08.csv | C44: 18
B45: Total | C45: =SUM(C21:C44)
B48: 2. Contrôles en direct sur les données chargées
B49: Contrôle | C49: Valeur | D49: Attendu
B50: Lignes de DATA_VENTES | C50: =COUNTA(V_Mag) | D50: Agrégat magasin × mois × canal.
B51: Magasins distincts dans REF_MAGASINS | C51: =SUMPRODUCT(1/COUNTIF(M_Code,M_Code)) | D51: 120
B52: CA net 24 mois (DATA_VENTES) | C52: =SUM(V_CANet) | D52: 301 027 972 € (CA net des 288 844 lignes conservées).
B53: Tickets 24 mois | C53: =SUM(V_Tickets) | D53: Somme des tickets.
B54: Lignes de DATA_BUDGET | C54: =COUNTA(B_Mag) | D54: 2 880
B55: Écart CA ventes / CA mix produits | C55: =SUM(X_CA)/SUM(V_CANet)-1 | D55: Sous 0,2 % (arrondis).
B56: Codes magasin de DATA_VENTES absents du référentiel | C56: =SUMPRODUCT(--(COUNTIF(M_Code,V_Mag)=0)) | D56: 0

Sheet _DOC
B1: DOCUMENTATION — Horizon_Contrat_Pilotage
B5: Objet
B6: Classeur | C6: Classeur de pilotage entièrement en formules. Il restitue 24 mois d'activité d'un réseau de 120 restaurants (sept. 2024 → août 2026) : tableau de bord, fiche magasin, sept constats, simulateur d'audit.
B7: Principe | C7: Aucun chiffre de restitution n'est saisi : tout est formule sur les feuilles DATA_* et REF_*. Les seules valeurs saisissables sont en bleu sur fond jaune (PARAMETRES, filtres, sélection du magasin, décisions du simulateur).
B9: Feuilles
B10: DASHBOARD | C10: Vue réseau. Filtres Région et Canal en C4 et H4 : ils pilotent cartes, courbe, classement et commentaire.
B11: FICHE_MAGASIN | C11: Drill-down. Région en C4, magasin en E4 (liste en cascade). Indicateurs, rangs, courbe mensuelle, top produits, RH, diagnostic automatique.
B12: ANALYSES | C12: Les sept constats, chacun avec sa question, son tableau et une phrase générée par formule. Plus le contrôle du piège « Gare / Aéroport » et le budget par région.
B13: SIMULATEUR | C13: Choix des magasins à auditer : modèle, contraintes, comparaison des stratégies, grille de sensibilité, scénarios, valeur cible, résultats Monte-Carlo.
B14: MONTE_CARLO | C14: 1 000 tirages du taux de récupération par magasin. Fonctions volatiles : F9 relance.
B15: PARAMETRES | C15: Toutes les constantes, chacune dans une cellule nommée.
B16: QUALITE | C16: Résultats du nettoyage des fichiers sources et contrôles recalculés en direct.
B17: CALC_* | C17: Feuilles de calcul intermédiaires, visibles pour être auditables. CALC_MAGASINS porte une ligne par magasin et 54 indicateurs.
B18: DATA_* / REF_* | C18: Données nettoyées. Ventes, stocks, achats et RH agrégés au mois ; mix produits agrégé à l'exercice ; référentiels dédoublonnés.
B20: Tables de données
B21: DATA_VENTES | C21: Grain magasin × mois × canal. CA_Net_HT = CA_Brut_HT − Remises_HT. Coût matière exprimé sur le CA net. Nb_Jours = jours avec ventes.
B22: DATA_BUDGET | C22: Grain magasin × mois, budgets 2025 et 2026 dépivotés. Le budget est en année civile, l'exercice va de septembre à août : la comparaison porte sur janvier → août 2026.
B23: DATA_STOCKS | C23: Grain magasin × mois. Taux de perte = pertes / sorties.
B24: DATA_ACHATS | C24: Grain fournisseur × mois de commande. Retard = délai réel − délai contractuel, commandes livrées seulement.
B25: DATA_ACHATS_MAG | C25: Grain magasin × exercice. Montant réel et même volume valorisé au prix moyen du réseau : leur rapport donne l'indice de prix d'achat.
B26: DATA_RH | C26: Grain magasin × mois. Nb_Salaries = salariés présents dans le mois : la somme sur l'exercice donne des salariés-mois.
B27: DATA_MIX | C27: Grain magasin × exercice × produit.
B29: Définitions
B30: Taux de marge | C30: 1 − coût matière / CA net. Marge brute sur coût matière : ne contient ni personnel ni loyer.
B31: Ticket moyen | C31: CA net / tickets, en ratio de sommes. Jamais une moyenne de tickets moyens.
B32: Périmètre comparable | C32: Magasins ouverts avant le début de N-1 et non fermés avant la fin de N : 115 magasins.
B33: Écart en points | C33: Différence de deux taux, affichée en « pt ». −0,31 pt n'est pas −0,31 %.
B34: Seuils | C34: Seuil d'alerte marge = taux du réseau − 2 pt. Perte anormale = plus de 2 fois la médiane. Les deux sont relatifs au réseau pour rester valables d'une année à l'autre.
B36: Couches ajoutées par macro (dossier vba/ du dépôt)
B37: Power Query | C37: Le nettoyage des 24 fichiers est chargé dans les feuilles DATA_* (voir QUALITE). La macro ConstruireModele recrée les requêtes Power Query sur les fichiers bruts du dossier Donnees.
B38: Power Pivot / DAX | C38: Remplacé ici par des SUMIFS sur données agrégées au mois. La macro ConstruireModele construit le modèle de données sur les fichiers bruts : 11 tables, 17 relations, 31 mesures DAX.
B39: TCD et segments | C39: Remplacés ici par des tableaux en formules et des listes de validation. La macro ConstruireModele ajoute un TCD de contrôle branché sur le modèle de données.
B40: VBA | C40: Fichier .xlsx, sans macro. Les modules (construction du modèle, actualisation, PDF par magasin, formulaire de saisie, brouillons Outlook, journal) sont dans le dossier vba/ : les importer avec Alt+F11, puis enregistrer en .xlsm. Renseigner d'abord Chemin_Donnees et Chemin_Sorties dans PARAMETRES.
B42: Limites
B43: Agrégation | C43: Données au mois : pas d'analyse au jour ni à la semaine dans ce fichier.
B44: Historique | C44: Une correction rétroactive dans les fichiers sources n'est pas historisée.
B45: Ordre du simulateur | C45: Les décisions de la colonne L sont liées à la position des lignes. Si les données changent l'ordre des candidats, revérifier les décisions.

Sheet CALC_MAGASINS
A1: Code_Magasin | B1: Ville | C1: Region | D1: Type_Emplacement | E1: Date_Ouverture | F1: Date_Fermeture | G1: CA_Net_N | H1: Cout_N | I1: Marge_N | J1: Taux_Marge_N | K1: CA_Net_N1 | L1: Taux_Marge_N1 | M1: Delta_CA | N1: Tickets_N | O1: Ticket_Moyen_N | P1: Jours_Ouverts_N | Q1: Budget_2026 | R1: Reel_2026 | S1: Atteinte_Budget | T1: Sorties_N | U1: Pertes_N | V1: Taux_Perte_N | W1: Taux_Perte_24m | X1: Achats_Reels_N | Y1: Achats_Prix_Reseau_N | Z1: Indice_Prix_Achat | AA1: Part_Livraison_N | AB1: Salaries_Mois_N | AC1: Effectif_Moyen_N | AD1: Heures_N | AE1: Absence_Sal_Mois_N | AF1: HS_Sal_Mois_N | AG1: CA_par_Heure_N | AH1: Absence_Sal_Mois_24m | AI1: HS_Sal_Mois_24m | AJ1: Comparable | AK1: Mouvement | AL1: Taux_Marge_A | AM1: Taux_Marge_B | AN1: Ecart_A_B_pt | AO1: Filtre_Region | AP1: CA_N_Filtre_Canal | AQ1: CA_N1_Filtre_Canal | AR1: Rang_Marge | AS1: Rang_CA | AT1: Rang_Ticket_Moyen | AU1: Rang_Perte | AV1: Cle_Alerte | AW1: Cle_Derive | AX1: Cle_Perte_24m | AY1: Cle_Absence_24m | AZ1: Rang_Mouvement | BA1: En_Derive | BB1: Cle_Atteinte
A2: =REF_MAGASINS!A2 | B2: =REF_MAGASINS!C2 | C2: =REF_MAGASINS!D2 | D2: =REF_MAGASINS!E2 | E2: =REF_MAGASINS!K2 | F2: =IF(REF_MAGASINS!L2="","",REF_MAGASINS!L2) | G2: =SUMIFS(V_CANet,V_Mag,$A2,V_Ex,Exercice_Courant) | H2: =SUMIFS(V_Cout,V_Mag,$A2,V_Ex,Exercice_Courant) | I2: =G2-H2 | J2: =IF(G2>0,I2/G2,"") | K2: =SUMIFS(V_CANet,V_Mag,$A2,V_Ex,Exercice_Precedent) | L2: =IF(K2>0,(K2-SUMIFS(V_Cout,V_Mag,$A2,V_Ex,Exercice_Precedent))/K2,"") | M2: =IF(K2>0,G2/K2-1,"") | N2: =SUMIFS(V_Tickets,V_Mag,$A2,V_Ex,Exercice_Courant) | O2: =IF(N2>0,G2/N2,"") | P2: =SUMIFS(V_Jours,V_Mag,$A2,V_Ex,Exercice_Courant,V_Canal,"Sur place") | Q2: =SUMIFS(B_Budget,B_Mag,$A2,B_Mois,">="&Budget_Debut,B_Mois,"<="&Budget_Fin) | R2: =SUMIFS(V_CANet,V_Mag,$A2,V_Mois,">="&Budget_Debut,V_Mois,"<="&Budget_Fin) | S2: =IF(Q2>0,R2/Q2,"") | T2: =SUMIFS(S_Sorties,S_Mag,$A2,S_Ex,Exercice_Courant) | U2: =SUMIFS(S_Pertes,S_Mag,$A2,S_Ex,Exercice_Courant) | V2: =IF(T2>0,U2/T2,"") | W2: =IF(SUMIFS(S_Sorties,S_Mag,$A2)>0,SUMIFS(S_Pertes,S_Mag,$A2)/SUMIFS(S_Sorties,S_Mag,$A2),"") | X2: =SUMIFS(AM_Reel,AM_Mag,$A2,AM_Ex,Exercice_Courant) | Y2: =SUMIFS(AM_Reseau,AM_Mag,$A2,AM_Ex,Exercice_Courant) | Z2: =IF(Y2>0,X2/Y2-1,"") | AA2: =IF(G2>0,SUMIFS(V_CANet,V_Mag,$A2,V_Ex,Exercice_Courant,V_Canal,"Livraison")/G2,"") | AB2: =SUMIFS(R_Salaries,R_Mag,$A2,R_Ex,Exercice_Courant) | AC2: =IF(COUNTIFS(R_Mag,$A2,R_Ex,Exercice_Courant)>0,AB2/COUNTIFS(R_Mag,$A2,R_Ex,Exercice_Courant),"") | AD2: =SUMIFS(R_Heures,R_Mag,$A2,R_Ex,Exercice_Courant) | AE2: =IF(AB2>0,SUMIFS(R_Abs,R_Mag,$A2,R_Ex,Exercice_Courant)/AB2,"") | AF2: =IF(AB2>0,SUMIFS(R_HS,R_Mag,$A2,R_Ex,Exercice_Courant)/AB2,"") | AG2: =IF(AD2>0,G2/AD2,"") | AH2: =IF(SUMIFS(R_Salaries,R_Mag,$A2)>0,SUMIFS(R_Abs,R_Mag,$A2)/SUMIFS(R_Salaries,R_Mag,$A2),"") | AI2: =IF(SUMIFS(R_Salaries,R_Mag,$A2)>0,SUMIFS(R_HS,R_Mag,$A2)/SUMIFS(R_Salaries,R_Mag,$A2),"") | AJ2: =IF(AND(E2<=Debut_N1,OR(F2="",F2>=Fin_Exercice)),1,0) | AK2: =IF(E2>Debut_N1,"Ouverture",IF(AND(F2<>"",F2<=Fin_Exercice),"Fermeture","")) | AL2: =IF(SUMIFS(V_CANet,V_Mag,$A2,V_Mois,">="&Periode_A_Debut,V_Mois,"<="&Periode_A_Fin)>0,1-SUMIFS(V_Cout,V_Mag,$A2,V_Mois,">="&Periode_A_Debut,V_Mois,"<="&Periode_A_Fin)/SUMIFS(V_CANet,V_Mag,$A2,V_Mois,">="&Periode_A_Debut,V_Mois,"<="&Periode_A_Fin),"") | AM2: =IF(SUMIFS(V_CANet,V_Mag,$A2,V_Mois,">="&Periode_B_Debut,V_Mois,"<="&Periode_B_Fin)>0,1-SUMIFS(V_Cout,V_Mag,$A2,V_Mois,">="&Periode_B_Debut,V_Mois,"<="&Periode_B_Fin)/SUMIFS(V_CANet,V_Mag,$A2,V_Mois,">="&Periode_B_Debut,V_Mois,"<="&Periode_B_Fin),"") | AN2: =IF(AND(ISNUMBER(AL2),ISNUMBER(AM2)),(AM2-AL2)*100,"") | AO2: =IF(OR(Region_Filtre="Toutes",C2=Region_Filtre),1,0) | AP2: =SUMIFS(V_CANet,V_Mag,$A2,V_Ex,Exercice_Courant,V_Canal,Crit_Canal) | AQ2: =SUMIFS(V_CANet,V_Mag,$A2,V_Ex,Exercice_Precedent,V_Canal,Crit_Canal) | AR2: =IF(ISNUMBER(J2),RANK(J2,$J$2:$J$121,0),"") | AS2: =RANK(G2,$G$2:$G$121,0) | AT2: =IF(ISNUMBER(O2),RANK(O2,$O$2:$O$121,0),"") | AU2: =IF(ISNUMBER(V2),RANK(V2,$V$2:$V$121,1),"") | AV2: =IF(AND(AO2=1,ISNUMBER(J2)),J2+ROW()/10^9,9) | AW2: =IF(ISNUMBER(AN2),AN2+ROW()/10^7,999) | AX2: =IF(ISNUMBER(W2),W2+ROW()/10^9,-1) | AY2: =IF(ISNUMBER(AH2),AH2+ROW()/10^9,-1) | AZ2: =IF(AK2="","",SUMPRODUCT(--($AK$2:AK2<>""))) | BA2: =IF(AND(ISNUMBER(AN2),AN2<=Seuil_Derive_Marge_Pt),1,0) | BB2: =IF(ISNUMBER(S2),S2+ROW()/10^9,9)
A3: =REF_MAGASINS!A3 | B3: =REF_MAGASINS!C3 | C3: =REF_MAGASINS!D3 | D3: =REF_MAGASINS!E3 | E3: =REF_MAGASINS!K3 | F3: =IF(REF_MAGASINS!L3="","",REF_MAGASINS!L3) | G3: =SUMIFS(V_CANet,V_Mag,$A3,V_Ex,Exercice_Courant) | H3: =SUMIFS(V_Cout,V_Mag,$A3,V_Ex,Exercice_Courant) | I3: =G3-H3 | J3: =IF(G3>0,I3/G3,"") | K3: =SUMIFS(V_CANet,V_Mag,$A3,V_Ex,Exercice_Precedent) | L3: =IF(K3>0,(K3-SUMIFS(V_Cout,V_Mag,$A3,V_Ex,Exercice_Precedent))/K3,"") | M3: =IF(K3>0,G3/K3-1,"") | N3: =SUMIFS(V_Tickets,V_Mag,$A3,V_Ex,Exercice_Courant) | O3: =IF(N3>0,G3/N3,"") | P3: =SUMIFS(V_Jours,V_Mag,$A3,V_Ex,Exercice_Courant,V_Canal,"Sur place") | Q3: =SUMIFS(B_Budget,B_Mag,$A3,B_Mois,">="&Budget_Debut,B_Mois,"<="&Budget_Fin) | R3: =SUMIFS(V_CANet,V_Mag,$A3,V_Mois,">="&Budget_Debut,V_Mois,"<="&Budget_Fin) | S3: =IF(Q3>0,R3/Q3,"") | T3: =SUMIFS(S_Sorties,S_Mag,$A3,S_Ex,Exercice_Courant) | U3: =SUMIFS(S_Pertes,S_Mag,$A3,S_Ex,Exercice_Courant) | V3: =IF(T3>0,U3/T3,"") | W3: =IF(SUMIFS(S_Sorties,S_Mag,$A3)>0,SUMIFS(S_Pertes,S_Mag,$A3)/SUMIFS(S_Sorties,S_Mag,$A3),"") | X3: =SUMIFS(AM_Reel,AM_Mag,$A3,AM_Ex,Exercice_Courant) | Y3: =SUMIFS(AM_Reseau,AM_Mag,$A3,AM_Ex,Exercice_Courant) | Z3: =IF(Y3>0,X3/Y3-1,"") | AA3: =IF(G3>0,SUMIFS(V_CANet,V_Mag,$A3,V_Ex,Exercice_Courant,V_Canal,"Livraison")/G3,"") | AB3: =SUMIFS(R_Salaries,R_Mag,$A3,R_Ex,Exercice_Courant) | AC3: =IF(COUNTIFS(R_Mag,$A3,R_Ex,Exercice_Courant)>0,AB3/COUNTIFS(R_Mag,$A3,R_Ex,Exercice_Courant),"") | AD3: =SUMIFS(R_Heures,R_Mag,$A3,R_Ex,Exercice_Courant) | AE3: =IF(AB3>0,SUMIFS(R_Abs,R_Mag,$A3,R_Ex,Exercice_Courant)/AB3,"") | AF3: =IF(AB3>0,SUMIFS(R_HS,R_Mag,$A3,R_Ex,Exercice_Courant)/AB3,"") | AG3: =IF(AD3>0,G3/AD3,"") | AH3: =IF(SUMIFS(R_Salaries,R_Mag,$A3)>0,SUMIFS(R_Abs,R_Mag,$A3)/SUMIFS(R_Salaries,R_Mag,$A3),"") | AI3: =IF(SUMIFS(R_Salaries,R_Mag,$A3)>0,SUMIFS(R_HS,R_Mag,$A3)/SUMIFS(R_Salaries,R_Mag,$A3),"") | AJ3: =IF(AND(E3<=Debut_N1,OR(F3="",F3>=Fin_Exercice)),1,0) | AK3: =IF(E3>Debut_N1,"Ouverture",IF(AND(F3<>"",F3<=Fin_Exercice),"Fermeture","")) | AL3: =IF(SUMIFS(V_CANet,V_Mag,$A3,V_Mois,">="&Periode_A_Debut,V_Mois,"<="&Periode_A_Fin)>0,1-SUMIFS(V_Cout,V_Mag,$A3,V_Mois,">="&Periode_A_Debut,V_Mois,"<="&Periode_A_Fin)/SUMIFS(V_CANet,V_Mag,$A3,V_Mois,">="&Periode_A_Debut,V_Mois,"<="&Periode_A_Fin),"") | AM3: =IF(SUMIFS(V_CANet,V_Mag,$A3,V_Mois,">="&Periode_B_Debut,V_Mois,"<="&Periode_B_Fin)>0,1-SUMIFS(V_Cout,V_Mag,$A3,V_Mois,">="&Periode_B_Debut,V_Mois,"<="&Periode_B_Fin)/SUMIFS(V_CANet,V_Mag,$A3,V_Mois,">="&Periode_B_Debut,V_Mois,"<="&Periode_B_Fin),"") | AN3: =IF(AND(ISNUMBER(AL3),ISNUMBER(AM3)),(AM3-AL3)*100,"") | AO3: =IF(OR(Region_Filtre="Toutes",C3=Region_Filtre),1,0) | AP3: =SUMIFS(V_CANet,V_Mag,$A3,V_Ex,Exercice_Courant,V_Canal,Crit_Canal) | AQ3: =SUMIFS(V_CANet,V_Mag,$A3,V_Ex,Exercice_Precedent,V_Canal,Crit_Canal) | AR3: =IF(ISNUMBER(J3),RANK(J3,$J$2:$J$121,0),"") | AS3: =RANK(G3,$G$2:$G$121,0) | AT3: =IF(ISNUMBER(O3),RANK(O3,$O$2:$O$121,0),"") | AU3: =IF(ISNUMBER(V3),RANK(V3,$V$2:$V$121,1),"") | AV3: =IF(AND(AO3=1,ISNUMBER(J3)),J3+ROW()/10^9,9) | AW3: =IF(ISNUMBER(AN3),AN3+ROW()/10^7,999) | AX3: =IF(ISNUMBER(W3),W3+ROW()/10^9,-1) | AY3: =IF(ISNUMBER(AH3),AH3+ROW()/10^9,-1) | AZ3: =IF(AK3="","",SUMPRODUCT(--($AK$2:AK3<>""))) | BA3: =IF(AND(ISNUMBER(AN3),AN3<=Seuil_Derive_Marge_Pt),1,0) | BB3: =IF(ISNUMBER(S3),S3+ROW()/10^9,9)
A4: =REF_MAGASINS!A4 | B4: =REF_MAGASINS!C4 | C4: =REF_MAGASINS!D4 | D4: =REF_MAGASINS!E4 | E4: =REF_MAGASINS!K4 | F4: =IF(REF_MAGASINS!L4="","",REF_MAGASINS!L4) | G4: =SUMIFS(V_CANet,V_Mag,$A4,V_Ex,Exercice_Courant) | H4: =SUMIFS(V_Cout,V_Mag,$A4,V_Ex,Exercice_Courant) | I4: =G4-H4 | J4: =IF(G4>0,I4/G4,"") | K4: =SUMIFS(V_CANet,V_Mag,$A4,V_Ex,Exercice_Precedent) | L4: =IF(K4>0,(K4-SUMIFS(V_Cout,V_Mag,$A4,V_Ex,Exercice_Precedent))/K4,"") | M4: =IF(K4>0,G4/K4-1,"") | N4: =SUMIFS(V_Tickets,V_Mag,$A4,V_Ex,Exercice_Courant) | O4: =IF(N4>0,G4/N4,"") | P4: =SUMIFS(V_Jours,V_Mag,$A4,V_Ex,Exercice_Courant,V_Canal,"Sur place") | Q4: =SUMIFS(B_Budget,B_Mag,$A4,B_Mois,">="&Budget_Debut,B_Mois,"<="&Budget_Fin) | R4: =SUMIFS(V_CANet,V_Mag,$A4,V_Mois,">="&Budget_Debut,V_Mois,"<="&Budget_Fin) | S4: =IF(Q4>0,R4/Q4,"") | T4: =SUMIFS(S_Sorties,S_Mag,$A4,S_Ex,Exercice_Courant) | U4: =SUMIFS(S_Pertes,S_Mag,$A4,S_Ex,Exercice_Courant) | V4: =IF(T4>0,U4/T4,"") | W4: =IF(SUMIFS(S_Sorties,S_Mag,$A4)>0,SUMIFS(S_Pertes,S_Mag,$A4)/SUMIFS(S_Sorties,S_Mag,$A4),"") | X4: =SUMIFS(AM_Reel,AM_Mag,$A4,AM_Ex,Exercice_Courant) | Y4: =SUMIFS(AM_Reseau,AM_Mag,$A4,AM_Ex,Exercice_Courant) | Z4: =IF(Y4>0,X4/Y4-1,"") | AA4: =IF(G4>0,SUMIFS(V_CANet,V_Mag,$A4,V_Ex,Exercice_Courant,V_Canal,"Livraison")/G4,"") | AB4: =SUMIFS(R_Salaries,R_Mag,$A4,R_Ex,Exercice_Courant) | AC4: =IF(COUNTIFS(R_Mag,$A4,R_Ex,Exercice_Courant)>0,AB4/COUNTIFS(R_Mag,$A4,R_Ex,Exercice_Courant),"") | AD4: =SUMIFS(R_Heures,R_Mag,$A4,R_Ex,Exercice_Courant) | AE4: =IF(AB4>0,SUMIFS(R_Abs,R_Mag,$A4,R_Ex,Exercice_Courant)/AB4,"") | AF4: =IF(AB4>0,SUMIFS(R_HS,R_Mag,$A4,R_Ex,Exercice_Courant)/AB4,"") | AG4: =IF(AD4>0,G4/AD4,"") | AH4: =IF(SUMIFS(R_Salaries,R_Mag,$A4)>0,SUMIFS(R_Abs,R_Mag,$A4)/SUMIFS(R_Salaries,R_Mag,$A4),"") | AI4: =IF(SUMIFS(R_Salaries,R_Mag,$A4)>0,SUMIFS(R_HS,R_Mag,$A4)/SUMIFS(R_Salaries,R_Mag,$A4),"") | AJ4: =IF(AND(E4<=Debut_N1,OR(F4="",F4>=Fin_Exercice)),1,0) | AK4: =IF(E4>Debut_N1,"Ouverture",IF(AND(F4<>"",F4<=Fin_Exercice),"Fermeture","")) | AL4: =IF(SUMIFS(V_CANet,V_Mag,$A4,V_Mois,">="&Periode_A_Debut,V_Mois,"<="&Periode_A_Fin)>0,1-SUMIFS(V_Cout,V_Mag,$A4,V_Mois,">="&Periode_A_Debut,V_Mois,"<="&Periode_A_Fin)/SUMIFS(V_CANet,V_Mag,$A4,V_Mois,">="&Periode_A_Debut,V_Mois,"<="&Periode_A_Fin),"") | AM4: =IF(SUMIFS(V_CANet,V_Mag,$A4,V_Mois,">="&Periode_B_Debut,V_Mois,"<="&Periode_B_Fin)>0,1-SUMIFS(V_Cout,V_Mag,$A4,V_Mois,">="&Periode_B_Debut,V_Mois,"<="&Periode_B_Fin)/SUMIFS(V_CANet,V_Mag,$A4,V_Mois,">="&Periode_B_Debut,V_Mois,"<="&Periode_B_Fin),"") | AN4: =IF(AND(ISNUMBER(AL4),ISNUMBER(AM4)),(AM4-AL4)*100,"") | AO4: =IF(OR(Region_Filtre="Toutes",C4=Region_Filtre),1,0) | AP4: =SUMIFS(V_CANet,V_Mag,$A4,V_Ex,Exercice_Courant,V_Canal,Crit_Canal) | AQ4: =SUMIFS(V_CANet,V_Mag,$A4,V_Ex,Exercice_Precedent,V_Canal,Crit_Canal) | AR4: =IF(ISNUMBER(J4),RANK(J4,$J$2:$J$121,0),"") | AS4: =RANK(G4,$G$2:$G$121,0) | AT4: =IF(ISNUMBER(O4),RANK(O4,$O$2:$O$121,0),"") | AU4: =IF(ISNUMBER(V4),RANK(V4,$V$2:$V$121,1),"") | AV4: =IF(AND(AO4=1,ISNUMBER(J4)),J4+ROW()/10^9,9) | AW4: =IF(ISNUMBER(AN4),AN4+ROW()/10^7,999) | AX4: =IF(ISNUMBER(W4),W4+ROW()/10^9,-1) | AY4: =IF(ISNUMBER(AH4),AH4+ROW()/10^9,-1) | AZ4: =IF(AK4="","",SUMPRODUCT(--($AK$2:AK4<>""))) | BA4: =IF(AND(ISNUMBER(AN4),AN4<=Seuil_Derive_Marge_Pt),1,0) | BB4: =IF(ISNUMBER(S4),S4+ROW()/10^9,9)
A5: =REF_MAGASINS!A5 | B5: =REF_MAGASINS!C5 | C5: =REF_MAGASINS!D5 | D5: =REF_MAGASINS!E5 | E5: =REF_MAGASINS!K5 | F5: =IF(REF_MAGASINS!L5="","",REF_MAGASINS!L5) | G5: =SUMIFS(V_CANet,V_Mag,$A5,V_Ex,Exercice_Courant) | H5: =SUMIFS(V_Cout,V_Mag,$A5,V_Ex,Exercice_Courant) | I5: =G5-H5 | J5: =IF(G5>0,I5/G5,"") | K5: =SUMIFS(V_CANet,V_Mag,$A5,V_Ex,Exercice_Precedent) | L5: =IF(K5>0,(K5-SUMIFS(V_Cout,V_Mag,$A5,V_Ex,Exercice_Precedent))/K5,"") | M5: =IF(K5>0,G5/K5-1,"") | N5: =SUMIFS(V_Tickets,V_Mag,$A5,V_Ex,Exercice_Courant) | O5: =IF(N5>0,G5/N5,"") | P5: =SUMIFS(V_Jours,V_Mag,$A5,V_Ex,Exercice_Courant,V_Canal,"Sur place") | Q5: =SUMIFS(B_Budget,B_Mag,$A5,B_Mois,">="&Budget_Debut,B_Mois,"<="&Budget_Fin) | R5: =SUMIFS(V_CANet,V_Mag,$A5,V_Mois,">="&Budget_Debut,V_Mois,"<="&Budget_Fin) | S5: =IF(Q5>0,R5/Q5,"") | T5: =SUMIFS(S_Sorties,S_Mag,$A5,S_Ex,Exercice_Courant) | U5: =SUMIFS(S_Pertes,S_Mag,$A5,S_Ex,Exercice_Courant) | V5: =IF(T5>0,U5/T5,"") | W5: =IF(SUMIFS(S_Sorties,S_Mag,$A5)>0,SUMIFS(S_Pertes,S_Mag,$A5)/SUMIFS(S_Sorties,S_Mag,$A5),"") | X5: =SUMIFS(AM_Reel,AM_Mag,$A5,AM_Ex,Exercice_Courant) | Y5: =SUMIFS(AM_Reseau,AM_Mag,$A5,AM_Ex,Exercice_Courant) | Z5: =IF(Y5>0,X5/Y5-1,"") | AA5: =IF(G5>0,SUMIFS(V_CANet,V_Mag,$A5,V_Ex,Exercice_Courant,V_Canal,"Livraison")/G5,"") | AB5: =SUMIFS(R_Salaries,R_Mag,$A5,R_Ex,Exercice_Courant) | AC5: =IF(COUNTIFS(R_Mag,$A5,R_Ex,Exercice_Courant)>0,AB5/COUNTIFS(R_Mag,$A5,R_Ex,Exercice_Courant),"") | AD5: =SUMIFS(R_Heures,R_Mag,$A5,R_Ex,Exercice_Courant) | AE5: =IF(AB5>0,SUMIFS(R_Abs,R_Mag,$A5,R_Ex,Exercice_Courant)/AB5,"") | AF5: =IF(AB5>0,SUMIFS(R_HS,R_Mag,$A5,R_Ex,Exercice_Courant)/AB5,"") | AG5: =IF(AD5>0,G5/AD5,"") | AH5: =IF(SUMIFS(R_Salaries,R_Mag,$A5)>0,SUMIFS(R_Abs,R_Mag,$A5)/SUMIFS(R_Salaries,R_Mag,$A5),"") | AI5: =IF(SUMIFS(R_Salaries,R_Mag,$A5)>0,SUMIFS(R_HS,R_Mag,$A5)/SUMIFS(R_Salaries,R_Mag,$A5),"") | AJ5: =IF(AND(E5<=Debut_N1,OR(F5="",F5>=Fin_Exercice)),1,0) | AK5: =IF(E5>Debut_N1,"Ouverture",IF(AND(F5<>"",F5<=Fin_Exercice),"Fermeture","")) | AL5: =IF(SUMIFS(V_CANet,V_Mag,$A5,V_Mois,">="&Periode_A_Debut,V_Mois,"<="&Periode_A_Fin)>0,1-SUMIFS(V_Cout,V_Mag,$A5,V_Mois,">="&Periode_A_Debut,V_Mois,"<="&Periode_A_Fin)/SUMIFS(V_CANet,V_Mag,$A5,V_Mois,">="&Periode_A_Debut,V_Mois,"<="&Periode_A_Fin),"") | AM5: =IF(SUMIFS(V_CANet,V_Mag,$A5,V_Mois,">="&Periode_B_Debut,V_Mois,"<="&Periode_B_Fin)>0,1-SUMIFS(V_Cout,V_Mag,$A5,V_Mois,">="&Periode_B_Debut,V_Mois,"<="&Periode_B_Fin)/SUMIFS(V_CANet,V_Mag,$A5,V_Mois,">="&Periode_B_Debut,V_Mois,"<="&Periode_B_Fin),"") | AN5: =IF(AND(ISNUMBER(AL5),ISNUMBER(AM5)),(AM5-AL5)*100,"") | AO5: =IF(OR(Region_Filtre="Toutes",C5=Region_Filtre),1,0) | AP5: =SUMIFS(V_CANet,V_Mag,$A5,V_Ex,Exercice_Courant,V_Canal,Crit_Canal) | AQ5: =SUMIFS(V_CANet,V_Mag,$A5,V_Ex,Exercice_Precedent,V_Canal,Crit_Canal) | AR5: =IF(ISNUMBER(J5),RANK(J5,$J$2:$J$121,0),"") | AS5: =RANK(G5,$G$2:$G$121,0) | AT5: =IF(ISNUMBER(O5),RANK(O5,$O$2:$O$121,0),"") | AU5: =IF(ISNUMBER(V5),RANK(V5,$V$2:$V$121,1),"") | AV5: =IF(AND(AO5=1,ISNUMBER(J5)),J5+ROW()/10^9,9) | AW5: =IF(ISNUMBER(AN5),AN5+ROW()/10^7,999) | AX5: =IF(ISNUMBER(W5),W5+ROW()/10^9,-1) | AY5: =IF(ISNUMBER(AH5),AH5+ROW()/10^9,-1) | AZ5: =IF(AK5="","",SUMPRODUCT(--($AK$2:AK5<>""))) | BA5: =IF(AND(ISNUMBER(AN5),AN5<=Seuil_Derive_Marge_Pt),1,0) | BB5: =IF(ISNUMBER(S5),S5+ROW()/10^9,9)
A6: =REF_MAGASINS!A6 | B6: =REF_MAGASINS!C6 | C6: =REF_MAGASINS!D6 | D6: =REF_MAGASINS!E6 | E6: =REF_MAGASINS!K6 | F6: =IF(REF_MAGASINS!L6="","",REF_MAGASINS!L6) | G6: =SUMIFS(V_CANet,V_Mag,$A6,V_Ex,Exercice_Courant) | H6: =SUMIFS(V_Cout,V_Mag,$A6,V_Ex,Exercice_Courant) | I6: =G6-H6 | J6: =IF(G6>0,I6/G6,"") | K6: =SUMIFS(V_CANet,V_Mag,$A6,V_Ex,Exercice_Precedent) | L6: =IF(K6>0,(K6-SUMIFS(V_Cout,V_Mag,$A6,V_Ex,Exercice_Precedent))/K6,"") | M6: =IF(K6>0,G6/K6-1,"") | N6: =SUMIFS(V_Tickets,V_Mag,$A6,V_Ex,Exercice_Courant) | O6: =IF(N6>0,G6/N6,"") | P6: =SUMIFS(V_Jours,V_Mag,$A6,V_Ex,Exercice_Courant,V_Canal,"Sur place") | Q6: =SUMIFS(B_Budget,B_Mag,$A6,B_Mois,">="&Budget_Debut,B_Mois,"<="&Budget_Fin) | R6: =SUMIFS(V_CANet,V_Mag,$A6,V_Mois,">="&Budget_Debut,V_Mois,"<="&Budget_Fin) | S6: =IF(Q6>0,R6/Q6,"") | T6: =SUMIFS(S_Sorties,S_Mag,$A6,S_Ex,Exercice_Courant) | U6: =SUMIFS(S_Pertes,S_Mag,$A6,S_Ex,Exercice_Courant) | V6: =IF(T6>0,U6/T6,"") | W6: =IF(SUMIFS(S_Sorties,S_Mag,$A6)>0,SUMIFS(S_Pertes,S_Mag,$A6)/SUMIFS(S_Sorties,S_Mag,$A6),"") | X6: =SUMIFS(AM_Reel,AM_Mag,$A6,AM_Ex,Exercice_Courant) | Y6: =SUMIFS(AM_Reseau,AM_Mag,$A6,AM_Ex,Exercice_Courant) | Z6: =IF(Y6>0,X6/Y6-1,"") | AA6: =IF(G6>0,SUMIFS(V_CANet,V_Mag,$A6,V_Ex,Exercice_Courant,V_Canal,"Livraison")/G6,"") | AB6: =SUMIFS(R_Salaries,R_Mag,$A6,R_Ex,Exercice_Courant) | AC6: =IF(COUNTIFS(R_Mag,$A6,R_Ex,Exercice_Courant)>0,AB6/COUNTIFS(R_Mag,$A6,R_Ex,Exercice_Courant),"") | AD6: =SUMIFS(R_Heures,R_Mag,$A6,R_Ex,Exercice_Courant) | AE6: =IF(AB6>0,SUMIFS(R_Abs,R_Mag,$A6,R_Ex,Exercice_Courant)/AB6,"") | AF6: =IF(AB6>0,SUMIFS(R_HS,R_Mag,$A6,R_Ex,Exercice_Courant)/AB6,"") | AG6: =IF(AD6>0,G6/AD6,"") | AH6: =IF(SUMIFS(R_Salaries,R_Mag,$A6)>0,SUMIFS(R_Abs,R_Mag,$A6)/SUMIFS(R_Salaries,R_Mag,$A6),"") | AI6: =IF(SUMIFS(R_Salaries,R_Mag,$A6)>0,SUMIFS(R_HS,R_Mag,$A6)/SUMIFS(R_Salaries,R_Mag,$A6),"") | AJ6: =IF(AND(E6<=Debut_N1,OR(F6="",F6>=Fin_Exercice)),1,0) | AK6: =IF(E6>Debut_N1,"Ouverture",IF(AND(F6<>"",F6<=Fin_Exercice),"Fermeture","")) | AL6: =IF(SUMIFS(V_CANet,V_Mag,$A6,V_Mois,">="&Periode_A_Debut,V_Mois,"<="&Periode_A_Fin)>0,1-SUMIFS(V_Cout,V_Mag,$A6,V_Mois,">="&Periode_A_Debut,V_Mois,"<="&Periode_A_Fin)/SUMIFS(V_CANet,V_Mag,$A6,V_Mois,">="&Periode_A_Debut,V_Mois,"<="&Periode_A_Fin),"") | AM6: =IF(SUMIFS(V_CANet,V_Mag,$A6,V_Mois,">="&Periode_B_Debut,V_Mois,"<="&Periode_B_Fin)>0,1-SUMIFS(V_Cout,V_Mag,$A6,V_Mois,">="&Periode_B_Debut,V_Mois,"<="&Periode_B_Fin)/SUMIFS(V_CANet,V_Mag,$A6,V_Mois,">="&Periode_B_Debut,V_Mois,"<="&Periode_B_Fin),"") | AN6: =IF(AND(ISNUMBER(AL6),ISNUMBER(AM6)),(AM6-AL6)*100,"") | AO6: =IF(OR(Region_Filtre="Toutes",C6=Region_Filtre),1,0) | AP6: =SUMIFS(V_CANet,V_Mag,$A6,V_Ex,Exercice_Courant,V_Canal,Crit_Canal) | AQ6: =SUMIFS(V_CANet,V_Mag,$A6,V_Ex,Exercice_Precedent,V_Canal,Crit_Canal) | AR6: =IF(ISNUMBER(J6),RANK(J6,$J$2:$J$121,0),"") | AS6: =RANK(G6,$G$2:$G$121,0) | AT6: =IF(ISNUMBER(O6),RANK(O6,$O$2:$O$121,0),"") | AU6: =IF(ISNUMBER(V6),RANK(V6,$V$2:$V$121,1),"") | AV6: =IF(AND(AO6=1,ISNUMBER(J6)),J6+ROW()/10^9,9) | AW6: =IF(ISNUMBER(AN6),AN6+ROW()/10^7,999) | AX6: =IF(ISNUMBER(W6),W6+ROW()/10^9,-1) | AY6: =IF(ISNUMBER(AH6),AH6+ROW()/10^9,-1) | AZ6: =IF(AK6="","",SUMPRODUCT(--($AK$2:AK6<>""))) | BA6: =IF(AND(ISNUMBER(AN6),AN6<=Seuil_Derive_Marge_Pt),1,0) | BB6: =IF(ISNUMBER(S6),S6+ROW()/10^9,9)
A7: =REF_MAGASINS!A7 | B7: =REF_MAGASINS!C7 | C7: =REF_MAGASINS!D7 | D7: =REF_MAGASINS!E7 | E7: =REF_MAGASINS!K7 | F7: =IF(REF_MAGASINS!L7="","",REF_MAGASINS!L7) | G7: =SUMIFS(V_CANet,V_Mag,$A7,V_Ex,Exercice_Courant) | H7: =SUMIFS(V_Cout,V_Mag,$A7,V_Ex,Exercice_Courant) | I7: =G7-H7 | J7: =IF(G7>0,I7/G7,"") | K7: =SUMIFS(V_CANet,V_Mag,$A7,V_Ex,Exercice_Precedent) | L7: =IF(K7>0,(K7-SUMIFS(V_Cout,V_Mag,$A7,V_Ex,Exercice_Precedent))/K7,"") | M7: =IF(K7>0,G7/K7-1,"") | N7: =SUMIFS(V_Tickets,V_Mag,$A7,V_Ex,Exercice_Courant) | O7: =IF(N7>0,G7/N7,"") | P7: =SUMIFS(V_Jours,V_Mag,$A7,V_Ex,Exercice_Courant,V_Canal,"Sur place") | Q7: =SUMIFS(B_Budget,B_Mag,$A7,B_Mois,">="&Budget_Debut,B_Mois,"<="&Budget_Fin) | R7: =SUMIFS(V_CANet,V_Mag,$A7,V_Mois,">="&Budget_Debut,V_Mois,"<="&Budget_Fin) | S7: =IF(Q7>0,R7/Q7,"") | T7: =SUMIFS(S_Sorties,S_Mag,$A7,S_Ex,Exercice_Courant) | U7: =SUMIFS(S_Pertes,S_Mag,$A7,S_Ex,Exercice_Courant) | V7: =IF(T7>0,U7/T7,"") | W7: =IF(SUMIFS(S_Sorties,S_Mag,$A7)>0,SUMIFS(S_Pertes,S_Mag,$A7)/SUMIFS(S_Sorties,S_Mag,$A7),"") | X7: =SUMIFS(AM_Reel,AM_Mag,$A7,AM_Ex,Exercice_Courant) | Y7: =SUMIFS(AM_Reseau,AM_Mag,$A7,AM_Ex,Exercice_Courant) | Z7: =IF(Y7>0,X7/Y7-1,"") | AA7: =IF(G7>0,SUMIFS(V_CANet,V_Mag,$A7,V_Ex,Exercice_Courant,V_Canal,"Livraison")/G7,"") | AB7: =SUMIFS(R_Salaries,R_Mag,$A7,R_Ex,Exercice_Courant) | AC7: =IF(COUNTIFS(R_Mag,$A7,R_Ex,Exercice_Courant)>0,AB7/COUNTIFS(R_Mag,$A7,R_Ex,Exercice_Courant),"") | AD7: =SUMIFS(R_Heures,R_Mag,$A7,R_Ex,Exercice_Courant) | AE7: =IF(AB7>0,SUMIFS(R_Abs,R_Mag,$A7,R_Ex,Exercice_Courant)/AB7,"") | AF7: =IF(AB7>0,SUMIFS(R_HS,R_Mag,$A7,R_Ex,Exercice_Courant)/AB7,"") | AG7: =IF(AD7>0,G7/AD7,"") | AH7: =IF(SUMIFS(R_Salaries,R_Mag,$A7)>0,SUMIFS(R_Abs,R_Mag,$A7)/SUMIFS(R_Salaries,R_Mag,$A7),"") | AI7: =IF(SUMIFS(R_Salaries,R_Mag,$A7)>0,SUMIFS(R_HS,R_Mag,$A7)/SUMIFS(R_Salaries,R_Mag,$A7),"") | AJ7: =IF(AND(E7<=Debut_N1,OR(F7="",F7>=Fin_Exercice)),1,0) | AK7: =IF(E7>Debut_N1,"Ouverture",IF(AND(F7<>"",F7<=Fin_Exercice),"Fermeture","")) | AL7: =IF(SUMIFS(V_CANet,V_Mag,$A7,V_Mois,">="&Periode_A_Debut,V_Mois,"<="&Periode_A_Fin)>0,1-SUMIFS(V_Cout,V_Mag,$A7,V_Mois,">="&Periode_A_Debut,V_Mois,"<="&Periode_A_Fin)/SUMIFS(V_CANet,V_Mag,$A7,V_Mois,">="&Periode_A_Debut,V_Mois,"<="&Periode_A_Fin),"") | AM7: =IF(SUMIFS(V_CANet,V_Mag,$A7,V_Mois,">="&Periode_B_Debut,V_Mois,"<="&Periode_B_Fin)>0,1-SUMIFS(V_Cout,V_Mag,$A7,V_Mois,">="&Periode_B_Debut,V_Mois,"<="&Periode_B_Fin)/SUMIFS(V_CANet,V_Mag,$A7,V_Mois,">="&Periode_B_Debut,V_Mois,"<="&Periode_B_Fin),"") | AN7: =IF(AND(ISNUMBER(AL7),ISNUMBER(AM7)),(AM7-AL7)*100,"") | AO7: =IF(OR(Region_Filtre="Toutes",C7=Region_Filtre),1,0) | AP7: =SUMIFS(V_CANet,V_Mag,$A7,V_Ex,Exercice_Courant,V_Canal,Crit_Canal) | AQ7: =SUMIFS(V_CANet,V_Mag,$A7,V_Ex,Exercice_Precedent,V_Canal,Crit_Canal) | AR7: =IF(ISNUMBER(J7),RANK(J7,$J$2:$J$121,0),"") | AS7: =RANK(G7,$G$2:$G$121,0) | AT7: =IF(ISNUMBER(O7),RANK(O7,$O$2:$O$121,0),"") | AU7: =IF(ISNUMBER(V7),RANK(V7,$V$2:$V$121,1),"") | AV7: =IF(AND(AO7=1,ISNUMBER(J7)),J7+ROW()/10^9,9) | AW7: =IF(ISNUMBER(AN7),AN7+ROW()/10^7,999) | AX7: =IF(ISNUMBER(W7),W7+ROW()/10^9,-1) | AY7: =IF(ISNUMBER(AH7),AH7+ROW()/10^9,-1) | AZ7: =IF(AK7="","",SUMPRODUCT(--($AK$2:AK7<>""))) | BA7: =IF(AND(ISNUMBER(AN7),AN7<=Seuil_Derive_Marge_Pt),1,0) | BB7: =IF(ISNUMBER(S7),S7+ROW()/10^9,9)
A8: =REF_MAGASINS!A8 | B8: =REF_MAGASINS!C8 | C8: =REF_MAGASINS!D8 | D8: =REF_MAGASINS!E8 | E8: =REF_MAGASINS!K8 | F8: =IF(REF_MAGASINS!L8="","",REF_MAGASINS!L8) | G8: =SUMIFS(V_CANet,V_Mag,$A8,V_Ex,Exercice_Courant) | H8: =SUMIFS(V_Cout,V_Mag,$A8,V_Ex,Exercice_Courant) | I8: =G8-H8 | J8: =IF(G8>0,I8/G8,"") | K8: =SUMIFS(V_CANet,V_Mag,$A8,V_Ex,Exercice_Precedent) | L8: =IF(K8>0,(K8-SUMIFS(V_Cout,V_Mag,$A8,V_Ex,Exercice_Precedent))/K8,"") | M8: =IF(K8>0,G8/K8-1,"") | N8: =SUMIFS(V_Tickets,V_Mag,$A8,V_Ex,Exercice_Courant) | O8: =IF(N8>0,G8/N8,"") | P8: =SUMIFS(V_Jours,V_Mag,$A8,V_Ex,Exercice_Courant,V_Canal,"Sur place") | Q8: =SUMIFS(B_Budget,B_Mag,$A8,B_Mois,">="&Budget_Debut,B_Mois,"<="&Budget_Fin) | R8: =SUMIFS(V_CANet,V_Mag,$A8,V_Mois,">="&Budget_Debut,V_Mois,"<="&Budget_Fin) | S8: =IF(Q8>0,R8/Q8,"") | T8: =SUMIFS(S_Sorties,S_Mag,$A8,S_Ex,Exercice_Courant) | U8: =SUMIFS(S_Pertes,S_Mag,$A8,S_Ex,Exercice_Courant) | V8: =IF(T8>0,U8/T8,"") | W8: =IF(SUMIFS(S_Sorties,S_Mag,$A8)>0,SUMIFS(S_Pertes,S_Mag,$A8)/SUMIFS(S_Sorties,S_Mag,$A8),"") | X8: =SUMIFS(AM_Reel,AM_Mag,$A8,AM_Ex,Exercice_Courant) | Y8: =SUMIFS(AM_Reseau,AM_Mag,$A8,AM_Ex,Exercice_Courant) | Z8: =IF(Y8>0,X8/Y8-1,"") | AA8: =IF(G8>0,SUMIFS(V_CANet,V_Mag,$A8,V_Ex,Exercice_Courant,V_Canal,"Livraison")/G8,"") | AB8: =SUMIFS(R_Salaries,R_Mag,$A8,R_Ex,Exercice_Courant) | AC8: =IF(COUNTIFS(R_Mag,$A8,R_Ex,Exercice_Courant)>0,AB8/COUNTIFS(R_Mag,$A8,R_Ex,Exercice_Courant),"") | AD8: =SUMIFS(R_Heures,R_Mag,$A8,R_Ex,Exercice_Courant) | AE8: =IF(AB8>0,SUMIFS(R_Abs,R_Mag,$A8,R_Ex,Exercice_Courant)/AB8,"") | AF8: =IF(AB8>0,SUMIFS(R_HS,R_Mag,$A8,R_Ex,Exercice_Courant)/AB8,"") | AG8: =IF(AD8>0,G8/AD8,"") | AH8: =IF(SUMIFS(R_Salaries,R_Mag,$A8)>0,SUMIFS(R_Abs,R_Mag,$A8)/SUMIFS(R_Salaries,R_Mag,$A8),"") | AI8: =IF(SUMIFS(R_Salaries,R_Mag,$A8)>0,SUMIFS(R_HS,R_Mag,$A8)/SUMIFS(R_Salaries,R_Mag,$A8),"") | AJ8: =IF(AND(E8<=Debut_N1,OR(F8="",F8>=Fin_Exercice)),1,0) | AK8: =IF(E8>Debut_N1,"Ouverture",IF(AND(F8<>"",F8<=Fin_Exercice),"Fermeture","")) | AL8: =IF(SUMIFS(V_CANet,V_Mag,$A8,V_Mois,">="&Periode_A_Debut,V_Mois,"<="&Periode_A_Fin)>0,1-SUMIFS(V_Cout,V_Mag,$A8,V_Mois,">="&Periode_A_Debut,V_Mois,"<="&Periode_A_Fin)/SUMIFS(V_CANet,V_Mag,$A8,V_Mois,">="&Periode_A_Debut,V_Mois,"<="&Periode_A_Fin),"") | AM8: =IF(SUMIFS(V_CANet,V_Mag,$A8,V_Mois,">="&Periode_B_Debut,V_Mois,"<="&Periode_B_Fin)>0,1-SUMIFS(V_Cout,V_Mag,$A8,V_Mois,">="&Periode_B_Debut,V_Mois,"<="&Periode_B_Fin)/SUMIFS(V_CANet,V_Mag,$A8,V_Mois,">="&Periode_B_Debut,V_Mois,"<="&Periode_B_Fin),"") | AN8: =IF(AND(ISNUMBER(AL8),ISNUMBER(AM8)),(AM8-AL8)*100,"") | AO8: =IF(OR(Region_Filtre="Toutes",C8=Region_Filtre),1,0) | AP8: =SUMIFS(V_CANet,V_Mag,$A8,V_Ex,Exercice_Courant,V_Canal,Crit_Canal) | AQ8: =SUMIFS(V_CANet,V_Mag,$A8,V_Ex,Exercice_Precedent,V_Canal,Crit_Canal) | AR8: =IF(ISNUMBER(J8),RANK(J8,$J$2:$J$121,0),"") | AS8: =RANK(G8,$G$2:$G$121,0) | AT8: =IF(ISNUMBER(O8),RANK(O8,$O$2:$O$121,0),"") | AU8: =IF(ISNUMBER(V8),RANK(V8,$V$2:$V$121,1),"") | AV8: =IF(AND(AO8=1,ISNUMBER(J8)),J8+ROW()/10^9,9) | AW8: =IF(ISNUMBER(AN8),AN8+ROW()/10^7,999) | AX8: =IF(ISNUMBER(W8),W8+ROW()/10^9,-1) | AY8: =IF(ISNUMBER(AH8),AH8+ROW()/10^9,-1) | AZ8: =IF(AK8="","",SUMPRODUCT(--($AK$2:AK8<>""))) | BA8: =IF(AND(ISNUMBER(AN8),AN8<=Seuil_Derive_Marge_Pt),1,0) | BB8: =IF(ISNUMBER(S8),S8+ROW()/10^9,9)
A9: =REF_MAGASINS!A9 | B9: =REF_MAGASINS!C9 | C9: =REF_MAGASINS!D9 | D9: =REF_MAGASINS!E9 | E9: =REF_MAGASINS!K9 | F9: =IF(REF_MAGASINS!L9="","",REF_MAGASINS!L9) | G9: =SUMIFS(V_CANet,V_Mag,$A9,V_Ex,Exercice_Courant) | H9: =SUMIFS(V_Cout,V_Mag,$A9,V_Ex,Exercice_Courant) | I9: =G9-H9 | J9: =IF(G9>0,I9/G9,"") | K9: =SUMIFS(V_CANet,V_Mag,$A9,V_Ex,Exercice_Precedent) | L9: =IF(K9>0,(K9-SUMIFS(V_Cout,V_Mag,$A9,V_Ex,Exercice_Precedent))/K9,"") | M9: =IF(K9>0,G9/K9-1,"") | N9: =SUMIFS(V_Tickets,V_Mag,$A9,V_Ex,Exercice_Courant) | O9: =IF(N9>0,G9/N9,"") | P9: =SUMIFS(V_Jours,V_Mag,$A9,V_Ex,Exercice_Courant,V_Canal,"Sur place") | Q9: =SUMIFS(B_Budget,B_Mag,$A9,B_Mois,">="&Budget_Debut,B_Mois,"<="&Budget_Fin) | R9: =SUMIFS(V_CANet,V_Mag,$A9,V_Mois,">="&Budget_Debut,V_Mois,"<="&Budget_Fin) | S9: =IF(Q9>0,R9/Q9,"") | T9: =SUMIFS(S_Sorties,S_Mag,$A9,S_Ex,Exercice_Courant) | U9: =SUMIFS(S_Pertes,S_Mag,$A9,S_Ex,Exercice_Courant) | V9: =IF(T9>0,U9/T9,"") | W9: =IF(SUMIFS(S_Sorties,S_Mag,$A9)>0,SUMIFS(S_Pertes,S_Mag,$A9)/SUMIFS(S_Sorties,S_Mag,$A9),"") | X9: =SUMIFS(AM_Reel,AM_Mag,$A9,AM_Ex,Exercice_Courant) | Y9: =SUMIFS(AM_Reseau,AM_Mag,$A9,AM_Ex,Exercice_Courant) | Z9: =IF(Y9>0,X9/Y9-1,"") | AA9: =IF(G9>0,SUMIFS(V_CANet,V_Mag,$A9,V_Ex,Exercice_Courant,V_Canal,"Livraison")/G9,"") | AB9: =SUMIFS(R_Salaries,R_Mag,$A9,R_Ex,Exercice_Courant) | AC9: =IF(COUNTIFS(R_Mag,$A9,R_Ex,Exercice_Courant)>0,AB9/COUNTIFS(R_Mag,$A9,R_Ex,Exercice_Courant),"") | AD9: =SUMIFS(R_Heures,R_Mag,$A9,R_Ex,Exercice_Courant) | AE9: =IF(AB9>0,SUMIFS(R_Abs,R_Mag,$A9,R_Ex,Exercice_Courant)/AB9,"") | AF9: =IF(AB9>0,SUMIFS(R_HS,R_Mag,$A9,R_Ex,Exercice_Courant)/AB9,"") | AG9: =IF(AD9>0,G9/AD9,"") | AH9: =IF(SUMIFS(R_Salaries,R_Mag,$A9)>0,SUMIFS(R_Abs,R_Mag,$A9)/SUMIFS(R_Salaries,R_Mag,$A9),"") | AI9: =IF(SUMIFS(R_Salaries,R_Mag,$A9)>0,SUMIFS(R_HS,R_Mag,$A9)/SUMIFS(R_Salaries,R_Mag,$A9),"") | AJ9: =IF(AND(E9<=Debut_N1,OR(F9="",F9>=Fin_Exercice)),1,0) | AK9: =IF(E9>Debut_N1,"Ouverture",IF(AND(F9<>"",F9<=Fin_Exercice),"Fermeture","")) | AL9: =IF(SUMIFS(V_CANet,V_Mag,$A9,V_Mois,">="&Periode_A_Debut,V_Mois,"<="&Periode_A_Fin)>0,1-SUMIFS(V_Cout,V_Mag,$A9,V_Mois,">="&Periode_A_Debut,V_Mois,"<="&Periode_A_Fin)/SUMIFS(V_CANet,V_Mag,$A9,V_Mois,">="&Periode_A_Debut,V_Mois,"<="&Periode_A_Fin),"") | AM9: =IF(SUMIFS(V_CANet,V_Mag,$A9,V_Mois,">="&Periode_B_Debut,V_Mois,"<="&Periode_B_Fin)>0,1-SUMIFS(V_Cout,V_Mag,$A9,V_Mois,">="&Periode_B_Debut,V_Mois,"<="&Periode_B_Fin)/SUMIFS(V_CANet,V_Mag,$A9,V_Mois,">="&Periode_B_Debut,V_Mois,"<="&Periode_B_Fin),"") | AN9: =IF(AND(ISNUMBER(AL9),ISNUMBER(AM9)),(AM9-AL9)*100,"") | AO9: =IF(OR(Region_Filtre="Toutes",C9=Region_Filtre),1,0) | AP9: =SUMIFS(V_CANet,V_Mag,$A9,V_Ex,Exercice_Courant,V_Canal,Crit_Canal) | AQ9: =SUMIFS(V_CANet,V_Mag,$A9,V_Ex,Exercice_Precedent,V_Canal,Crit_Canal) | AR9: =IF(ISNUMBER(J9),RANK(J9,$J$2:$J$121,0),"") | AS9: =RANK(G9,$G$2:$G$121,0) | AT9: =IF(ISNUMBER(O9),RANK(O9,$O$2:$O$121,0),"") | AU9: =IF(ISNUMBER(V9),RANK(V9,$V$2:$V$121,1),"") | AV9: =IF(AND(AO9=1,ISNUMBER(J9)),J9+ROW()/10^9,9) | AW9: =IF(ISNUMBER(AN9),AN9+ROW()/10^7,999) | AX9: =IF(ISNUMBER(W9),W9+ROW()/10^9,-1) | AY9: =IF(ISNUMBER(AH9),AH9+ROW()/10^9,-1) | AZ9: =IF(AK9="","",SUMPRODUCT(--($AK$2:AK9<>""))) | BA9: =IF(AND(ISNUMBER(AN9),AN9<=Seuil_Derive_Marge_Pt),1,0) | BB9: =IF(ISNUMBER(S9),S9+ROW()/10^9,9)
A10: =REF_MAGASINS!A10 | B10: =REF_MAGASINS!C10 | C10: =REF_MAGASINS!D10 | D10: =REF_MAGASINS!E10 | E10: =REF_MAGASINS!K10 | F10: =IF(REF_MAGASINS!L10="","",REF_MAGASINS!L10) | G10: =SUMIFS(V_CANet,V_Mag,$A10,V_Ex,Exercice_Courant) | H10: =SUMIFS(V_Cout,V_Mag,$A10,V_Ex,Exercice_Courant) | I10: =G10-H10 | J10: =IF(G10>0,I10/G10,"") | K10: =SUMIFS(V_CANet,V_Mag,$A10,V_Ex,Exercice_Precedent) | L10: =IF(K10>0,(K10-SUMIFS(V_Cout,V_Mag,$A10,V_Ex,Exercice_Precedent))/K10,"") | M10: =IF(K10>0,G10/K10-1,"") | N10: =SUMIFS(V_Tickets,V_Mag,$A10,V_Ex,Exercice_Courant) | O10: =IF(N10>0,G10/N10,"") | P10: =SUMIFS(V_Jours,V_Mag,$A10,V_Ex,Exercice_Courant,V_Canal,"Sur place") | Q10: =SUMIFS(B_Budget,B_Mag,$A10,B_Mois,">="&Budget_Debut,B_Mois,"<="&Budget_Fin) | R10: =SUMIFS(V_CANet,V_Mag,$A10,V_Mois,">="&Budget_Debut,V_Mois,"<="&Budget_Fin) | S10: =IF(Q10>0,R10/Q10,"") | T10: =SUMIFS(S_Sorties,S_Mag,$A10,S_Ex,Exercice_Courant) | U10: =SUMIFS(S_Pertes,S_Mag,$A10,S_Ex,Exercice_Courant) | V10: =IF(T10>0,U10/T10,"") | W10: =IF(SUMIFS(S_Sorties,S_Mag,$A10)>0,SUMIFS(S_Pertes,S_Mag,$A10)/SUMIFS(S_Sorties,S_Mag,$A10),"") | X10: =SUMIFS(AM_Reel,AM_Mag,$A10,AM_Ex,Exercice_Courant) | Y10: =SUMIFS(AM_Reseau,AM_Mag,$A10,AM_Ex,Exercice_Courant) | Z10: =IF(Y10>0,X10/Y10-1,"") | AA10: =IF(G10>0,SUMIFS(V_CANet,V_Mag,$A10,V_Ex,Exercice_Courant,V_Canal,"Livraison")/G10,"") | AB10: =SUMIFS(R_Salaries,R_Mag,$A10,R_Ex,Exercice_Courant) | AC10: =IF(COUNTIFS(R_Mag,$A10,R_Ex,Exercice_Courant)>0,AB10/COUNTIFS(R_Mag,$A10,R_Ex,Exercice_Courant),"") | AD10: =SUMIFS(R_Heures,R_Mag,$A10,R_Ex,Exercice_Courant) | AE10: =IF(AB10>0,SUMIFS(R_Abs,R_Mag,$A10,R_Ex,Exercice_Courant)/AB10,"") | AF10: =IF(AB10>0,SUMIFS(R_HS,R_Mag,$A10,R_Ex,Exercice_Courant)/AB10,"") | AG10: =IF(AD10>0,G10/AD10,"") | AH10: =IF(SUMIFS(R_Salaries,R_Mag,$A10)>0,SUMIFS(R_Abs,R_Mag,$A10)/SUMIFS(R_Salaries,R_Mag,$A10),"") | AI10: =IF(SUMIFS(R_Salaries,R_Mag,$A10)>0,SUMIFS(R_HS,R_Mag,$A10)/SUMIFS(R_Salaries,R_Mag,$A10),"") | AJ10: =IF(AND(E10<=Debut_N1,OR(F10="",F10>=Fin_Exercice)),1,0) | AK10: =IF(E10>Debut_N1,"Ouverture",IF(AND(F10<>"",F10<=Fin_Exercice),"Fermeture","")) | AL10: =IF(SUMIFS(V_CANet,V_Mag,$A10,V_Mois,">="&Periode_A_Debut,V_Mois,"<="&Periode_A_Fin)>0,1-SUMIFS(V_Cout,V_Mag,$A10,V_Mois,">="&Periode_A_Debut,V_Mois,"<="&Periode_A_Fin)/SUMIFS(V_CANet,V_Mag,$A10,V_Mois,">="&Periode_A_Debut,V_Mois,"<="&Periode_A_Fin),"") | AM10: =IF(SUMIFS(V_CANet,V_Mag,$A10,V_Mois,">="&Periode_B_Debut,V_Mois,"<="&Periode_B_Fin)>0,1-SUMIFS(V_Cout,V_Mag,$A10,V_Mois,">="&Periode_B_Debut,V_Mois,"<="&Periode_B_Fin)/SUMIFS(V_CANet,V_Mag,$A10,V_Mois,">="&Periode_B_Debut,V_Mois,"<="&Periode_B_Fin),"") | AN10: =IF(AND(ISNUMBER(AL10),ISNUMBER(AM10)),(AM10-AL10)*100,"") | AO10: =IF(OR(Region_Filtre="Toutes",C10=Region_Filtre),1,0) | AP10: =SUMIFS(V_CANet,V_Mag,$A10,V_Ex,Exercice_Courant,V_Canal,Crit_Canal) | AQ10: =SUMIFS(V_CANet,V_Mag,$A10,V_Ex,Exercice_Precedent,V_Canal,Crit_Canal) | AR10: =IF(ISNUMBER(J10),RANK(J10,$J$2:$J$121,0),"") | AS10: =RANK(G10,$G$2:$G$121,0) | AT10: =IF(ISNUMBER(O10),RANK(O10,$O$2:$O$121,0),"") | AU10: =IF(ISNUMBER(V10),RANK(V10,$V$2:$V$121,1),"") | AV10: =IF(AND(AO10=1,ISNUMBER(J10)),J10+ROW()/10^9,9) | AW10: =IF(ISNUMBER(AN10),AN10+ROW()/10^7,999) | AX10: =IF(ISNUMBER(W10),W10+ROW()/10^9,-1) | AY10: =IF(ISNUMBER(AH10),AH10+ROW()/10^9,-1) | AZ10: =IF(AK10="","",SUMPRODUCT(--($AK$2:AK10<>""))) | BA10: =IF(AND(ISNUMBER(AN10),AN10<=Seuil_Derive_Marge_Pt),1,0) | BB10: =IF(ISNUMBER(S10),S10+ROW()/10^9,9)
A11: =REF_MAGASINS!A11 | B11: =REF_MAGASINS!C11 | C11: =REF_MAGASINS!D11 | D11: =REF_MAGASINS!E11 | E11: =REF_MAGASINS!K11 | F11: =IF(REF_MAGASINS!L11="","",REF_MAGASINS!L11) | G11: =SUMIFS(V_CANet,V_Mag,$A11,V_Ex,Exercice_Courant) | H11: =SUMIFS(V_Cout,V_Mag,$A11,V_Ex,Exercice_Courant) | I11: =G11-H11 | J11: =IF(G11>0,I11/G11,"") | K11: =SUMIFS(V_CANet,V_Mag,$A11,V_Ex,Exercice_Precedent) | L11: =IF(K11>0,(K11-SUMIFS(V_Cout,V_Mag,$A11,V_Ex,Exercice_Precedent))/K11,"") | M11: =IF(K11>0,G11/K11-1,"") | N11: =SUMIFS(V_Tickets,V_Mag,$A11,V_Ex,Exercice_Courant) | O11: =IF(N11>0,G11/N11,"") | P11: =SUMIFS(V_Jours,V_Mag,$A11,V_Ex,Exercice_Courant,V_Canal,"Sur place") | Q11: =SUMIFS(B_Budget,B_Mag,$A11,B_Mois,">="&Budget_Debut,B_Mois,"<="&Budget_Fin) | R11: =SUMIFS(V_CANet,V_Mag,$A11,V_Mois,">="&Budget_Debut,V_Mois,"<="&Budget_Fin) | S11: =IF(Q11>0,R11/Q11,"") | T11: =SUMIFS(S_Sorties,S_Mag,$A11,S_Ex,Exercice_Courant) | U11: =SUMIFS(S_Pertes,S_Mag,$A11,S_Ex,Exercice_Courant) | V11: =IF(T11>0,U11/T11,"") | W11: =IF(SUMIFS(S_Sorties,S_Mag,$A11)>0,SUMIFS(S_Pertes,S_Mag,$A11)/SUMIFS(S_Sorties,S_Mag,$A11),"") | X11: =SUMIFS(AM_Reel,AM_Mag,$A11,AM_Ex,Exercice_Courant) | Y11: =SUMIFS(AM_Reseau,AM_Mag,$A11,AM_Ex,Exercice_Courant) | Z11: =IF(Y11>0,X11/Y11-1,"") | AA11: =IF(G11>0,SUMIFS(V_CANet,V_Mag,$A11,V_Ex,Exercice_Courant,V_Canal,"Livraison")/G11,"") | AB11: =SUMIFS(R_Salaries,R_Mag,$A11,R_Ex,Exercice_Courant) | AC11: =IF(COUNTIFS(R_Mag,$A11,R_Ex,Exercice_Courant)>0,AB11/COUNTIFS(R_Mag,$A11,R_Ex,Exercice_Courant),"") | AD11: =SUMIFS(R_Heures,R_Mag,$A11,R_Ex,Exercice_Courant) | AE11: =IF(AB11>0,SUMIFS(R_Abs,R_Mag,$A11,R_Ex,Exercice_Courant)/AB11,"") | AF11: =IF(AB11>0,SUMIFS(R_HS,R_Mag,$A11,R_Ex,Exercice_Courant)/AB11,"") | AG11: =IF(AD11>0,G11/AD11,"") | AH11: =IF(SUMIFS(R_Salaries,R_Mag,$A11)>0,SUMIFS(R_Abs,R_Mag,$A11)/SUMIFS(R_Salaries,R_Mag,$A11),"") | AI11: =IF(SUMIFS(R_Salaries,R_Mag,$A11)>0,SUMIFS(R_HS,R_Mag,$A11)/SUMIFS(R_Salaries,R_Mag,$A11),"") | AJ11: =IF(AND(E11<=Debut_N1,OR(F11="",F11>=Fin_Exercice)),1,0) | AK11: =IF(E11>Debut_N1,"Ouverture",IF(AND(F11<>"",F11<=Fin_Exercice),"Fermeture","")) | AL11: =IF(SUMIFS(V_CANet,V_Mag,$A11,V_Mois,">="&Periode_A_Debut,V_Mois,"<="&Periode_A_Fin)>0,1-SUMIFS(V_Cout,V_Mag,$A11,V_Mois,">="&Periode_A_Debut,V_Mois,"<="&Periode_A_Fin)/SUMIFS(V_CANet,V_Mag,$A11,V_Mois,">="&Periode_A_Debut,V_Mois,"<="&Periode_A_Fin),"") | AM11: =IF(SUMIFS(V_CANet,V_Mag,$A11,V_Mois,">="&Periode_B_Debut,V_Mois,"<="&Periode_B_Fin)>0,1-SUMIFS(V_Cout,V_Mag,$A11,V_Mois,">="&Periode_B_Debut,V_Mois,"<="&Periode_B_Fin)/SUMIFS(V_CANet,V_Mag,$A11,V_Mois,">="&Periode_B_Debut,V_Mois,"<="&Periode_B_Fin),"") | AN11: =IF(AND(ISNUMBER(AL11),ISNUMBER(AM11)),(AM11-AL11)*100,"") | AO11: =IF(OR(Region_Filtre="Toutes",C11=Region_Filtre),1,0) | AP11: =SUMIFS(V_CANet,V_Mag,$A11,V_Ex,Exercice_Courant,V_Canal,Crit_Canal) | AQ11: =SUMIFS(V_CANet,V_Mag,$A11,V_Ex,Exercice_Precedent,V_Canal,Crit_Canal) | AR11: =IF(ISNUMBER(J11),RANK(J11,$J$2:$J$121,0),"") | AS11: =RANK(G11,$G$2:$G$121,0) | AT11: =IF(ISNUMBER(O11),RANK(O11,$O$2:$O$121,0),"") | AU11: =IF(ISNUMBER(V11),RANK(V11,$V$2:$V$121,1),"") | AV11: =IF(AND(AO11=1,ISNUMBER(J11)),J11+ROW()/10^9,9) | AW11: =IF(ISNUMBER(AN11),AN11+ROW()/10^7,999) | AX11: =IF(ISNUMBER(W11),W11+ROW()/10^9,-1) | AY11: =IF(ISNUMBER(AH11),AH11+ROW()/10^9,-1) | AZ11: =IF(AK11="","",SUMPRODUCT(--($AK$2:AK11<>""))) | BA11: =IF(AND(ISNUMBER(AN11),AN11<=Seuil_Derive_Marge_Pt),1,0) | BB11: =IF(ISNUMBER(S11),S11+ROW()/10^9,9)
A12: =REF_MAGASINS!A12 | B12: =REF_MAGASINS!C12 | C12: =REF_MAGASINS!D12 | D12: =REF_MAGASINS!E12 | E12: =REF_MAGASINS!K12 | F12: =IF(REF_MAGASINS!L12="","",REF_MAGASINS!L12) | G12: =SUMIFS(V_CANet,V_Mag,$A12,V_Ex,Exercice_Courant) | H12: =SUMIFS(V_Cout,V_Mag,$A12,V_Ex,Exercice_Courant) | I12: =G12-H12 | J12: =IF(G12>0,I12/G12,"") | K12: =SUMIFS(V_CANet,V_Mag,$A12,V_Ex,Exercice_Precedent) | L12: =IF(K12>0,(K12-SUMIFS(V_Cout,V_Mag,$A12,V_Ex,Exercice_Precedent))/K12,"") | M12: =IF(K12>0,G12/K12-1,"") | N12: =SUMIFS(V_Tickets,V_Mag,$A12,V_Ex,Exercice_Courant) | O12: =IF(N12>0,G12/N12,"") | P12: =SUMIFS(V_Jours,V_Mag,$A12,V_Ex,Exercice_Courant,V_Canal,"Sur place") | Q12: =SUMIFS(B_Budget,B_Mag,$A12,B_Mois,">="&Budget_Debut,B_Mois,"<="&Budget_Fin) | R12: =SUMIFS(V_CANet,V_Mag,$A12,V_Mois,">="&Budget_Debut,V_Mois,"<="&Budget_Fin) | S12: =IF(Q12>0,R12/Q12,"") | T12: =SUMIFS(S_Sorties,S_Mag,$A12,S_Ex,Exercice_Courant) | U12: =SUMIFS(S_Pertes,S_Mag,$A12,S_Ex,Exercice_Courant) | V12: =IF(T12>0,U12/T12,"") | W12: =IF(SUMIFS(S_Sorties,S_Mag,$A12)>0,SUMIFS(S_Pertes,S_Mag,$A12)/SUMIFS(S_Sorties,S_Mag,$A12),"") | X12: =SUMIFS(AM_Reel,AM_Mag,$A12,AM_Ex,Exercice_Courant) | Y12: =SUMIFS(AM_Reseau,AM_Mag,$A12,AM_Ex,Exercice_Courant) | Z12: =IF(Y12>0,X12/Y12-1,"") | AA12: =IF(G12>0,SUMIFS(V_CANet,V_Mag,$A12,V_Ex,Exercice_Courant,V_Canal,"Livraison")/G12,"") | AB12: =SUMIFS(R_Salaries,R_Mag,$A12,R_Ex,Exercice_Courant) | AC12: =IF(COUNTIFS(R_Mag,$A12,R_Ex,Exercice_Courant)>0,AB12/COUNTIFS(R_Mag,$A12,R_Ex,Exercice_Courant),"") | AD12: =SUMIFS(R_Heures,R_Mag,$A12,R_Ex,Exercice_Courant) | AE12: =IF(AB12>0,SUMIFS(R_Abs,R_Mag,$A12,R_Ex,Exercice_Courant)/AB12,"") | AF12: =IF(AB12>0,SUMIFS(R_HS,R_Mag,$A12,R_Ex,Exercice_Courant)/AB12,"") | AG12: =IF(AD12>0,G12/AD12,"") | AH12: =IF(SUMIFS(R_Salaries,R_Mag,$A12)>0,SUMIFS(R_Abs,R_Mag,$A12)/SUMIFS(R_Salaries,R_Mag,$A12),"") | AI12: =IF(SUMIFS(R_Salaries,R_Mag,$A12)>0,SUMIFS(R_HS,R_Mag,$A12)/SUMIFS(R_Salaries,R_Mag,$A12),"") | AJ12: =IF(AND(E12<=Debut_N1,OR(F12="",F12>=Fin_Exercice)),1,0) | AK12: =IF(E12>Debut_N1,"Ouverture",IF(AND(F12<>"",F12<=Fin_Exercice),"Fermeture","")) | AL12: =IF(SUMIFS(V_CANet,V_Mag,$A12,V_Mois,">="&Periode_A_Debut,V_Mois,"<="&Periode_A_Fin)>0,1-SUMIFS(V_Cout,V_Mag,$A12,V_Mois,">="&Periode_A_Debut,V_Mois,"<="&Periode_A_Fin)/SUMIFS(V_CANet,V_Mag,$A12,V_Mois,">="&Periode_A_Debut,V_Mois,"<="&Periode_A_Fin),"") | AM12: =IF(SUMIFS(V_CANet,V_Mag,$A12,V_Mois,">="&Periode_B_Debut,V_Mois,"<="&Periode_B_Fin)>0,1-SUMIFS(V_Cout,V_Mag,$A12,V_Mois,">="&Periode_B_Debut,V_Mois,"<="&Periode_B_Fin)/SUMIFS(V_CANet,V_Mag,$A12,V_Mois,">="&Periode_B_Debut,V_Mois,"<="&Periode_B_Fin),"") | AN12: =IF(AND(ISNUMBER(AL12),ISNUMBER(AM12)),(AM12-AL12)*100,"") | AO12: =IF(OR(Region_Filtre="Toutes",C12=Region_Filtre),1,0) | AP12: =SUMIFS(V_CANet,V_Mag,$A12,V_Ex,Exercice_Courant,V_Canal,Crit_Canal) | AQ12: =SUMIFS(V_CANet,V_Mag,$A12,V_Ex,Exercice_Precedent,V_Canal,Crit_Canal) | AR12: =IF(ISNUMBER(J12),RANK(J12,$J$2:$J$121,0),"") | AS12: =RANK(G12,$G$2:$G$121,0) | AT12: =IF(ISNUMBER(O12),RANK(O12,$O$2:$O$121,0),"") | AU12: =IF(ISNUMBER(V12),RANK(V12,$V$2:$V$121,1),"") | AV12: =IF(AND(AO12=1,ISNUMBER(J12)),J12+ROW()/10^9,9) | AW12: =IF(ISNUMBER(AN12),AN12+ROW()/10^7,999) | AX12: =IF(ISNUMBER(W12),W12+ROW()/10^9,-1) | AY12: =IF(ISNUMBER(AH12),AH12+ROW()/10^9,-1) | AZ12: =IF(AK12="","",SUMPRODUCT(--($AK$2:AK12<>""))) | BA12: =IF(AND(ISNUMBER(AN12),AN12<=Seuil_Derive_Marge_Pt),1,0) | BB12: =IF(ISNUMBER(S12),S12+ROW()/10^9,9)
A13: =REF_MAGASINS!A13 | B13: =REF_MAGASINS!C13 | C13: =REF_MAGASINS!D13 | D13: =REF_MAGASINS!E13 | E13: =REF_MAGASINS!K13 | F13: =IF(REF_MAGASINS!L13="","",REF_MAGASINS!L13) | G13: =SUMIFS(V_CANet,V_Mag,$A13,V_Ex,Exercice_Courant) | H13: =SUMIFS(V_Cout,V_Mag,$A13,V_Ex,Exercice_Courant) | I13: =G13-H13 | J13: =IF(G13>0,I13/G13,"") | K13: =SUMIFS(V_CANet,V_Mag,$A13,V_Ex,Exercice_Precedent) | L13: =IF(K13>0,(K13-SUMIFS(V_Cout,V_Mag,$A13,V_Ex,Exercice_Precedent))/K13,"") | M13: =IF(K13>0,G13/K13-1,"") | N13: =SUMIFS(V_Tickets,V_Mag,$A13,V_Ex,Exercice_Courant) | O13: =IF(N13>0,G13/N13,"") | P13: =SUMIFS(V_Jours,V_Mag,$A13,V_Ex,Exercice_Courant,V_Canal,"Sur place") | Q13: =SUMIFS(B_Budget,B_Mag,$A13,B_Mois,">="&Budget_Debut,B_Mois,"<="&Budget_Fin) | R13: =SUMIFS(V_CANet,V_Mag,$A13,V_Mois,">="&Budget_Debut,V_Mois,"<="&Budget_Fin) | S13: =IF(Q13>0,R13/Q13,"") | T13: =SUMIFS(S_Sorties,S_Mag,$A13,S_Ex,Exercice_Courant) | U13: =SUMIFS(S_Pertes,S_Mag,$A13,S_Ex,Exercice_Courant) | V13: =IF(T13>0,U13/T13,"") | W13: =IF(SUMIFS(S_Sorties,S_Mag,$A13)>0,SUMIFS(S_Pertes,S_Mag,$A13)/SUMIFS(S_Sorties,S_Mag,$A13),"") | X13: =SUMIFS(AM_Reel,AM_Mag,$A13,AM_Ex,Exercice_Courant) | Y13: =SUMIFS(AM_Reseau,AM_Mag,$A13,AM_Ex,Exercice_Courant) | Z13: =IF(Y13>0,X13/Y13-1,"") | AA13: =IF(G13>0,SUMIFS(V_CANet,V_Mag,$A13,V_Ex,Exercice_Courant,V_Canal,"Livraison")/G13,"") | AB13: =SUMIFS(R_Salaries,R_Mag,$A13,R_Ex,Exercice_Courant) | AC13: =IF(COUNTIFS(R_Mag,$A13,R_Ex,Exercice_Courant)>0,AB13/COUNTIFS(R_Mag,$A13,R_Ex,Exercice_Courant),"") | AD13: =SUMIFS(R_Heures,R_Mag,$A13,R_Ex,Exercice_Courant) | AE13: =IF(AB13>0,SUMIFS(R_Abs,R_Mag,$A13,R_Ex,Exercice_Courant)/AB13,"") | AF13: =IF(AB13>0,SUMIFS(R_HS,R_Mag,$A13,R_Ex,Exercice_Courant)/AB13,"") | AG13: =IF(AD13>0,G13/AD13,"") | AH13: =IF(SUMIFS(R_Salaries,R_Mag,$A13)>0,SUMIFS(R_Abs,R_Mag,$A13)/SUMIFS(R_Salaries,R_Mag,$A13),"") | AI13: =IF(SUMIFS(R_Salaries,R_Mag,$A13)>0,SUMIFS(R_HS,R_Mag,$A13)/SUMIFS(R_Salaries,R_Mag,$A13),"") | AJ13: =IF(AND(E13<=Debut_N1,OR(F13="",F13>=Fin_Exercice)),1,0) | AK13: =IF(E13>Debut_N1,"Ouverture",IF(AND(F13<>"",F13<=Fin_Exercice),"Fermeture","")) | AL13: =IF(SUMIFS(V_CANet,V_Mag,$A13,V_Mois,">="&Periode_A_Debut,V_Mois,"<="&Periode_A_Fin)>0,1-SUMIFS(V_Cout,V_Mag,$A13,V_Mois,">="&Periode_A_Debut,V_Mois,"<="&Periode_A_Fin)/SUMIFS(V_CANet,V_Mag,$A13,V_Mois,">="&Periode_A_Debut,V_Mois,"<="&Periode_A_Fin),"") | AM13: =IF(SUMIFS(V_CANet,V_Mag,$A13,V_Mois,">="&Periode_B_Debut,V_Mois,"<="&Periode_B_Fin)>0,1-SUMIFS(V_Cout,V_Mag,$A13,V_Mois,">="&Periode_B_Debut,V_Mois,"<="&Periode_B_Fin)/SUMIFS(V_CANet,V_Mag,$A13,V_Mois,">="&Periode_B_Debut,V_Mois,"<="&Periode_B_Fin),"") | AN13: =IF(AND(ISNUMBER(AL13),ISNUMBER(AM13)),(AM13-AL13)*100,"") | AO13: =IF(OR(Region_Filtre="Toutes",C13=Region_Filtre),1,0) | AP13: =SUMIFS(V_CANet,V_Mag,$A13,V_Ex,Exercice_Courant,V_Canal,Crit_Canal) | AQ13: =SUMIFS(V_CANet,V_Mag,$A13,V_Ex,Exercice_Precedent,V_Canal,Crit_Canal) | AR13: =IF(ISNUMBER(J13),RANK(J13,$J$2:$J$121,0),"") | AS13: =RANK(G13,$G$2:$G$121,0) | AT13: =IF(ISNUMBER(O13),RANK(O13,$O$2:$O$121,0),"") | AU13: =IF(ISNUMBER(V13),RANK(V13,$V$2:$V$121,1),"") | AV13: =IF(AND(AO13=1,ISNUMBER(J13)),J13+ROW()/10^9,9) | AW13: =IF(ISNUMBER(AN13),AN13+ROW()/10^7,999) | AX13: =IF(ISNUMBER(W13),W13+ROW()/10^9,-1) | AY13: =IF(ISNUMBER(AH13),AH13+ROW()/10^9,-1) | AZ13: =IF(AK13="","",SUMPRODUCT(--($AK$2:AK13<>""))) | BA13: =IF(AND(ISNUMBER(AN13),AN13<=Seuil_Derive_Marge_Pt),1,0) | BB13: =IF(ISNUMBER(S13),S13+ROW()/10^9,9)
... A121: =REF_MAGASINS!A121 | B121: =REF_MAGASINS!C121 | C121: =REF_MAGASINS!D121 | D121: =REF_MAGASINS!E121 | E121: =REF_MAGASINS!K121 | F121: =IF(REF_MAGASINS!L121="","",REF_MAGASINS!L121) | G121: =SUMIFS(V_CANet,V_Mag,$A121,V_Ex,Exercice_Courant) | H121: =SUMIFS(V_Cout,V_Mag,$A121,V_Ex,Exercice_Courant) | I121: =G121-H121 | J121: =IF(G121>0,I121/G121,"") | K121: =SUMIFS(V_CANet,V_Mag,$A121,V_Ex,Exercice_Precedent) | L121: =IF(K121>0,(K121-SUMIFS(V_Cout,V_Mag,$A121,V_Ex,Exercice_Precedent))/K121,"") | M121: =IF(K121>0,G121/K121-1,"") | N121: =SUMIFS(V_Tickets,V_Mag,$A121,V_Ex,Exercice_Courant) | O121: =IF(N121>0,G121/N121,"") | P121: =SUMIFS(V_Jours,V_Mag,$A121,V_Ex,Exercice_Courant,V_Canal,"Sur place") | Q121: =SUMIFS(B_Budget,B_Mag,$A121,B_Mois,">="&Budget_Debut,B_Mois,"<="&Budget_Fin) | R121: =SUMIFS(V_CANet,V_Mag,$A121,V_Mois,">="&Budget_Debut,V_Mois,"<="&Budget_Fin) | S121: =IF(Q121>0,R121/Q121,"") | T121: =SUMIFS(S_Sorties,S_Mag,$A121,S_Ex,Exercice_Courant) | U121: =SUMIFS(S_Pertes,S_Mag,$A121,S_Ex,Exercice_Courant) | V121: =IF(T121>0,U121/T121,"") | W121: =IF(SUMIFS(S_Sorties,S_Mag,$A121)>0,SUMIFS(S_Pertes,S_Mag,$A121)/SUMIFS(S_Sorties,S_Mag,$A121),"") | X121: =SUMIFS(AM_Reel,AM_Mag,$A121,AM_Ex,Exercice_Courant) | Y121: =SUMIFS(AM_Reseau,AM_Mag,$A121,AM_Ex,Exercice_Courant) | Z121: =IF(Y121>0,X121/Y121-1,"") | AA121: =IF(G121>0,SUMIFS(V_CANet,V_Mag,$A121,V_Ex,Exercice_Courant,V_Canal,"Livraison")/G121,"") | AB121: =SUMIFS(R_Salaries,R_Mag,$A121,R_Ex,Exercice_Courant) | AC121: =IF(COUNTIFS(R_Mag,$A121,R_Ex,Exercice_Courant)>0,AB121/COUNTIFS(R_Mag,$A121,R_Ex,Exercice_Courant),"") | AD121: =SUMIFS(R_Heures,R_Mag,$A121,R_Ex,Exercice_Courant) | AE121: =IF(AB121>0,SUMIFS(R_Abs,R_Mag,$A121,R_Ex,Exercice_Courant)/AB121,"") | AF121: =IF(AB121>0,SUMIFS(R_HS,R_Mag,$A121,R_Ex,Exercice_Courant)/AB121,"") | AG121: =IF(AD121>0,G121/AD121,"") | AH121: =IF(SUMIFS(R_Salaries,R_Mag,$A121)>0,SUMIFS(R_Abs,R_Mag,$A121)/SUMIFS(R_Salaries,R_Mag,$A121),"") | AI121: =IF(SUMIFS(R_Salaries,R_Mag,$A121)>0,SUMIFS(R_HS,R_Mag,$A121)/SUMIFS(R_Salaries,R_Mag,$A121),"") | AJ121: =IF(AND(E121<=Debut_N1,OR(F121="",F121>=Fin_Exercice)),1,0) | AK121: =IF(E121>Debut_N1,"Ouverture",IF(AND(F121<>"",F121<=Fin_Exercice),"Fermeture","")) | AL121: =IF(SUMIFS(V_CANet,V_Mag,$A121,V_Mois,">="&Periode_A_Debut,V_Mois,"<="&Periode_A_Fin)>0,1-SUMIFS(V_Cout,V_Mag,$A121,V_Mois,">="&Periode_A_Debut,V_Mois,"<="&Periode_A_Fin)/SUMIFS(V_CANet,V_Mag,$A121,V_Mois,">="&Periode_A_Debut,V_Mois,"<="&Periode_A_Fin),"") | AM121: =IF(SUMIFS(V_CANet,V_Mag,$A121,V_Mois,">="&Periode_B_Debut,V_Mois,"<="&Periode_B_Fin)>0,1-SUMIFS(V_Cout,V_Mag,$A121,V_Mois,">="&Periode_B_Debut,V_Mois,"<="&Periode_B_Fin)/SUMIFS(V_CANet,V_Mag,$A121,V_Mois,">="&Periode_B_Debut,V_Mois,"<="&Periode_B_Fin),"") | AN121: =IF(AND(ISNUMBER(AL121),ISNUMBER(AM121)),(AM121-AL121)*100,"") | AO121: =IF(OR(Region_Filtre="Toutes",C121=Region_Filtre),1,0) | AP121: =SUMIFS(V_CANet,V_Mag,$A121,V_Ex,Exercice_Courant,V_Canal,Crit_Canal) | AQ121: =SUMIFS(V_CANet,V_Mag,$A121,V_Ex,Exercice_Precedent,V_Canal,Crit_Canal) | AR121: =IF(ISNUMBER(J121),RANK(J121,$J$2:$J$121,0),"") | AS121: =RANK(G121,$G$2:$G$121,0) | AT121: =IF(ISNUMBER(O121),RANK(O121,$O$2:$O$121,0),"") | AU121: =IF(ISNUMBER(V121),RANK(V121,$V$2:$V$121,1),"") | AV121: =IF(AND(AO121=1,ISNUMBER(J121)),J121+ROW()/10^9,9) | AW121: =IF(ISNUMBER(AN121),AN121+ROW()/10^7,999) | AX121: =IF(ISNUMBER(W121),W121+ROW()/10^9,-1) | AY121: =IF(ISNUMBER(AH121),AH121+ROW()/10^9,-1) | AZ121: =IF(AK121="","",SUMPRODUCT(--($AK$2:AK121<>""))) | BA121: =IF(AND(ISNUMBER(AN121),AN121<=Seuil_Derive_Marge_Pt),1,0) | BB121: =IF(ISNUMBER(S121),S121+ROW()/10^9,9)
A123: Une ligne par magasin, dans l'ordre de REF_MAGASINS. Toutes les colonnes sont des formules sur les feuilles DATA_*. Les colonnes Cle_* servent aux classements (SMALL/LARGE + MATCH) : le terme ROW()/10^9 départage les ex-æquo.

Sheet CALC_DASH
A1: CALC_DASH — calculs du tableau de bord (filtres appliqués)
A2: Critère région | B2: =IF(Region_Filtre="Toutes","<>",Region_Filtre) | C2: « <> » = toute valeur non vide : le critère qui sélectionne tout sans joker.
A3: Critère canal | B3: =IF(Canal_Filtre="Tous","<>",Canal_Filtre)
A5: Indicateur | B5: Valeur
A6: CA_N | B6: =SUMIFS(V_CANet,V_Ex,Exercice_Courant,V_Reg,Crit_Region,V_Canal,Crit_Canal)
A7: CA_N1 | B7: =SUMIFS(V_CANet,V_Ex,Exercice_Precedent,V_Reg,Crit_Region,V_Canal,Crit_Canal)
A8: Cout_N | B8: =SUMIFS(V_Cout,V_Ex,Exercice_Courant,V_Reg,Crit_Region,V_Canal,Crit_Canal)
A9: Cout_N1 | B9: =SUMIFS(V_Cout,V_Ex,Exercice_Precedent,V_Reg,Crit_Region,V_Canal,Crit_Canal)
A10: Taux_N | B10: =IF(D_CA_N>0,1-D_Cout_N/D_CA_N,0)
A11: Taux_N1 | B11: =IF(D_CA_N1>0,1-D_Cout_N1/D_CA_N1,0)
A12: Delta_Taux_pt | B12: =(D_Taux_N-D_Taux_N1)*100
A13: Delta_CA | B13: =IF(D_CA_N1>0,D_CA_N/D_CA_N1-1,0)
A14: Tickets_N | B14: =SUMIFS(V_Tickets,V_Ex,Exercice_Courant,V_Reg,Crit_Region,V_Canal,Crit_Canal)
A15: Tickets_N1 | B15: =SUMIFS(V_Tickets,V_Ex,Exercice_Precedent,V_Reg,Crit_Region,V_Canal,Crit_Canal)
A16: Delta_Tickets | B16: =IF(D_Tickets_N1>0,D_Tickets_N/D_Tickets_N1-1,0)
A17: TM_N | B17: =IF(D_Tickets_N>0,D_CA_N/D_Tickets_N,0)
A18: TM_N1 | B18: =IF(D_Tickets_N1>0,D_CA_N1/D_Tickets_N1,0)
A19: Delta_TM | B19: =IF(D_TM_N1>0,D_TM_N/D_TM_N1-1,0)
A20: CA_Comp_N | B20: =SUMPRODUCT(CM_Comparable,CM_Filtre_Region,CM_CA_N_Filtre_Canal)
A21: CA_Comp_N1 | B21: =SUMPRODUCT(CM_Comparable,CM_Filtre_Region,CM_CA_N1_Filtre_Canal)
A22: Delta_Comp | B22: =IF(D_CA_Comp_N1>0,D_CA_Comp_N/D_CA_Comp_N1-1,0)
A23: Nb_Comparables | B23: =SUMPRODUCT(CM_Comparable,CM_Filtre_Region)
A24: Nb_Magasins | B24: =SUM(CM_Filtre_Region)
A25: Budget | B25: =SUMIFS(B_Budget,B_Reg,Crit_Region,B_Mois,">="&Budget_Debut,B_Mois,"<="&Budget_Fin)
A26: Reel_Budget | B26: =SUMIFS(V_CANet,V_Reg,Crit_Region,V_Mois,">="&Budget_Debut,V_Mois,"<="&Budget_Fin)
A27: Atteinte | B27: =IF(D_Budget>0,D_Reel_Budget/D_Budget,0)
A28: Nb_Sous_Objectif | B28: =COUNTIFS(CM_Atteinte_Budget,"<"&Seuil_Atteinte_Budget,CM_Region,Crit_Region)
A29: Taux_Reseau | B29: =1-SUM(CM_Cout_N)/SUM(CM_CA_Net_N)
A30: TM_Reseau | B30: =SUM(CM_CA_Net_N)/SUM(CM_Tickets_N)
A31: Part_Livraison_Reseau | B31: =SUMIFS(V_CANet,V_Ex,Exercice_Courant,V_Canal,"Livraison")/SUM(CM_CA_Net_N)
A32: Mediane_Perte_N | B32: =MEDIAN(CM_Taux_Perte_N)
A33: Mediane_Perte_24m | B33: =MEDIAN(CM_Taux_Perte_24m)
A34: Seuil_Taux_Alerte | B34: =D_Taux_Reseau-Seuil_Alerte_Marge_Pt
A35: Nb_Sous_Seuil | B35: =COUNTIFS(CM_Taux_Marge_N,"<"&D_Seuil_Taux_Alerte,CM_Region,Crit_Region)
A37: Série mensuelle (graphique 1)
A38: Mois de l'exercice | B38: Mois N | C38: Mois N-1 | D38: Libellé | E38: CA net N (M€) | F38: CA net N-1 (M€)
A39: 1 | B39: =EDATE(Debut_Exercice,A39-1) | C39: =EDATE(Debut_N1,A39-1) | D39: =CHOOSE(MONTH(B39),"janv","févr","mars","avr","mai","juin","juil","août","sept","oct","nov","déc") | E39: =SUMIFS(V_CANet,V_Mois,B39,V_Reg,Crit_Region,V_Canal,Crit_Canal)/10^6 | F39: =SUMIFS(V_CANet,V_Mois,C39,V_Reg,Crit_Region,V_Canal,Crit_Canal)/10^6
A40: 2 | B40: =EDATE(Debut_Exercice,A40-1) | C40: =EDATE(Debut_N1,A40-1) | D40: =CHOOSE(MONTH(B40),"janv","févr","mars","avr","mai","juin","juil","août","sept","oct","nov","déc") | E40: =SUMIFS(V_CANet,V_Mois,B40,V_Reg,Crit_Region,V_Canal,Crit_Canal)/10^6 | F40: =SUMIFS(V_CANet,V_Mois,C40,V_Reg,Crit_Region,V_Canal,Crit_Canal)/10^6
A41: 3 | B41: =EDATE(Debut_Exercice,A41-1) | C41: =EDATE(Debut_N1,A41-1) | D41: =CHOOSE(MONTH(B41),"janv","févr","mars","avr","mai","juin","juil","août","sept","oct","nov","déc") | E41: =SUMIFS(V_CANet,V_Mois,B41,V_Reg,Crit_Region,V_Canal,Crit_Canal)/10^6 | F41: =SUMIFS(V_CANet,V_Mois,C41,V_Reg,Crit_Region,V_Canal,Crit_Canal)/10^6
A42: 4 | B42: =EDATE(Debut_Exercice,A42-1) | C42: =EDATE(Debut_N1,A42-1) | D42: =CHOOSE(MONTH(B42),"janv","févr","mars","avr","mai","juin","juil","août","sept","oct","nov","déc") | E42: =SUMIFS(V_CANet,V_Mois,B42,V_Reg,Crit_Region,V_Canal,Crit_Canal)/10^6 | F42: =SUMIFS(V_CANet,V_Mois,C42,V_Reg,Crit_Region,V_Canal,Crit_Canal)/10^6
A43: 5 | B43: =EDATE(Debut_Exercice,A43-1) | C43: =EDATE(Debut_N1,A43-1) | D43: =CHOOSE(MONTH(B43),"janv","févr","mars","avr","mai","juin","juil","août","sept","oct","nov","déc") | E43: =SUMIFS(V_CANet,V_Mois,B43,V_Reg,Crit_Region,V_Canal,Crit_Canal)/10^6 | F43: =SUMIFS(V_CANet,V_Mois,C43,V_Reg,Crit_Region,V_Canal,Crit_Canal)/10^6
A44: 6 | B44: =EDATE(Debut_Exercice,A44-1) | C44: =EDATE(Debut_N1,A44-1) | D44: =CHOOSE(MONTH(B44),"janv","févr","mars","avr","mai","juin","juil","août","sept","oct","nov","déc") | E44: =SUMIFS(V_CANet,V_Mois,B44,V_Reg,Crit_Region,V_Canal,Crit_Canal)/10^6 | F44: =SUMIFS(V_CANet,V_Mois,C44,V_Reg,Crit_Region,V_Canal,Crit_Canal)/10^6
A45: 7 | B45: =EDATE(Debut_Exercice,A45-1) | C45: =EDATE(Debut_N1,A45-1) | D45: =CHOOSE(MONTH(B45),"janv","févr","mars","avr","mai","juin","juil","août","sept","oct","nov","déc") | E45: =SUMIFS(V_CANet,V_Mois,B45,V_Reg,Crit_Region,V_Canal,Crit_Canal)/10^6 | F45: =SUMIFS(V_CANet,V_Mois,C45,V_Reg,Crit_Region,V_Canal,Crit_Canal)/10^6
A46: 8 | B46: =EDATE(Debut_Exercice,A46-1) | C46: =EDATE(Debut_N1,A46-1) | D46: =CHOOSE(MONTH(B46),"janv","févr","mars","avr","mai","juin","juil","août","sept","oct","nov","déc") | E46: =SUMIFS(V_CANet,V_Mois,B46,V_Reg,Crit_Region,V_Canal,Crit_Canal)/10^6 | F46: =SUMIFS(V_CANet,V_Mois,C46,V_Reg,Crit_Region,V_Canal,Crit_Canal)/10^6
A47: 9 | B47: =EDATE(Debut_Exercice,A47-1) | C47: =EDATE(Debut_N1,A47-1) | D47: =CHOOSE(MONTH(B47),"janv","févr","mars","avr","mai","juin","juil","août","sept","oct","nov","déc") | E47: =SUMIFS(V_CANet,V_Mois,B47,V_Reg,Crit_Region,V_Canal,Crit_Canal)/10^6 | F47: =SUMIFS(V_CANet,V_Mois,C47,V_Reg,Crit_Region,V_Canal,Crit_Canal)/10^6
A48: 10 | B48: =EDATE(Debut_Exercice,A48-1) | C48: =EDATE(Debut_N1,A48-1) | D48: =CHOOSE(MONTH(B48),"janv","févr","mars","avr","mai","juin","juil","août","sept","oct","nov","déc") | E48: =SUMIFS(V_CANet,V_Mois,B48,V_Reg,Crit_Region,V_Canal,Crit_Canal)/10^6 | F48: =SUMIFS(V_CANet,V_Mois,C48,V_Reg,Crit_Region,V_Canal,Crit_Canal)/10^6
A49: 11 | B49: =EDATE(Debut_Exercice,A49-1) | C49: =EDATE(Debut_N1,A49-1) | D49: =CHOOSE(MONTH(B49),"janv","févr","mars","avr","mai","juin","juil","août","sept","oct","nov","déc") | E49: =SUMIFS(V_CANet,V_Mois,B49,V_Reg,Crit_Region,V_Canal,Crit_Canal)/10^6 | F49: =SUMIFS(V_CANet,V_Mois,C49,V_Reg,Crit_Region,V_Canal,Crit_Canal)/10^6
A50: 12 | B50: =EDATE(Debut_Exercice,A50-1) | C50: =EDATE(Debut_N1,A50-1) | D50: =CHOOSE(MONTH(B50),"janv","févr","mars","avr","mai","juin","juil","août","sept","oct","nov","déc") | E50: =SUMIFS(V_CANet,V_Mois,B50,V_Reg,Crit_Region,V_Canal,Crit_Canal)/10^6 | F50: =SUMIFS(V_CANet,V_Mois,C50,V_Reg,Crit_Region,V_Canal,Crit_Canal)/10^6
A52: Mix canal (graphique 2) — filtre région seul
A53: Canal | B53: CA net N | C53: Part
A54: Sur place | B54: =SUMIFS(V_CANet,V_Ex,Exercice_Courant,V_Reg,Crit_Region,V_Canal,A54) | C54: =IF(SUM($B$54:$B$57)>0,B54/SUM($B$54:$B$57),0)
A55: À emporter | B55: =SUMIFS(V_CANet,V_Ex,Exercice_Courant,V_Reg,Crit_Region,V_Canal,A55) | C55: =IF(SUM($B$54:$B$57)>0,B55/SUM($B$54:$B$57),0)
A56: Livraison | B56: =SUMIFS(V_CANet,V_Ex,Exercice_Courant,V_Reg,Crit_Region,V_Canal,A56) | C56: =IF(SUM($B$54:$B$57)>0,B56/SUM($B$54:$B$57),0)
A57: Drive | B57: =SUMIFS(V_CANet,V_Ex,Exercice_Courant,V_Reg,Crit_Region,V_Canal,A57) | C57: =IF(SUM($B$54:$B$57)>0,B57/SUM($B$54:$B$57),0)
A60: CA par région (graphique 3) — filtre canal seul
A61: Région | B61: CA net N (M€) | C61: CA net N-1 (M€) | D61: Évolution
A62: Île-de-France | B62: =SUMIFS(V_CANet,V_Ex,Exercice_Courant,V_Reg,A62,V_Canal,Crit_Canal)/10^6 | C62: =SUMIFS(V_CANet,V_Ex,Exercice_Precedent,V_Reg,A62,V_Canal,Crit_Canal)/10^6 | D62: =IF(C62>0,B62/C62-1,0)
A63: Sud-Est | B63: =SUMIFS(V_CANet,V_Ex,Exercice_Courant,V_Reg,A63,V_Canal,Crit_Canal)/10^6 | C63: =SUMIFS(V_CANet,V_Ex,Exercice_Precedent,V_Reg,A63,V_Canal,Crit_Canal)/10^6 | D63: =IF(C63>0,B63/C63-1,0)
A64: Nord-Ouest | B64: =SUMIFS(V_CANet,V_Ex,Exercice_Courant,V_Reg,A64,V_Canal,Crit_Canal)/10^6 | C64: =SUMIFS(V_CANet,V_Ex,Exercice_Precedent,V_Reg,A64,V_Canal,Crit_Canal)/10^6 | D64: =IF(C64>0,B64/C64-1,0)
A65: Sud-Ouest | B65: =SUMIFS(V_CANet,V_Ex,Exercice_Courant,V_Reg,A65,V_Canal,Crit_Canal)/10^6 | C65: =SUMIFS(V_CANet,V_Ex,Exercice_Precedent,V_Reg,A65,V_Canal,Crit_Canal)/10^6 | D65: =IF(C65>0,B65/C65-1,0)
A68: Classement des taux de marge les plus faibles (tableau d'alerte)
A69: Rang | B69: Clé | C69: Ligne | D69: Code | E69: Ville | F69: Région | G69: CA net N | H69: Taux de marge | I69: Écart réseau (pt)
A70: 1 | B70: =SMALL(CM_Cle_Alerte,A70) | C70: =MATCH(B70,CM_Cle_Alerte,0) | D70: =INDEX(CM_Code_Magasin,C70) | E70: =INDEX(CM_Ville,C70) | F70: =INDEX(CM_Region,C70) | G70: =INDEX(CM_CA_Net_N,C70) | H70: =INDEX(CM_Taux_Marge_N,C70) | I70: =(H70-D_Taux_Reseau)*100
A71: 2 | B71: =SMALL(CM_Cle_Alerte,A71) | C71: =MATCH(B71,CM_Cle_Alerte,0) | D71: =INDEX(CM_Code_Magasin,C71) | E71: =INDEX(CM_Ville,C71) | F71: =INDEX(CM_Region,C71) | G71: =INDEX(CM_CA_Net_N,C71) | H71: =INDEX(CM_Taux_Marge_N,C71) | I71: =(H71-D_Taux_Reseau)*100
A72: 3 | B72: =SMALL(CM_Cle_Alerte,A72) | C72: =MATCH(B72,CM_Cle_Alerte,0) | D72: =INDEX(CM_Code_Magasin,C72) | E72: =INDEX(CM_Ville,C72) | F72: =INDEX(CM_Region,C72) | G72: =INDEX(CM_CA_Net_N,C72) | H72: =INDEX(CM_Taux_Marge_N,C72) | I72: =(H72-D_Taux_Reseau)*100
A73: 4 | B73: =SMALL(CM_Cle_Alerte,A73) | C73: =MATCH(B73,CM_Cle_Alerte,0) | D73: =INDEX(CM_Code_Magasin,C73) | E73: =INDEX(CM_Ville,C73) | F73: =INDEX(CM_Region,C73) | G73: =INDEX(CM_CA_Net_N,C73) | H73: =INDEX(CM_Taux_Marge_N,C73) | I73: =(H73-D_Taux_Reseau)*100
A74: 5 | B74: =SMALL(CM_Cle_Alerte,A74) | C74: =MATCH(B74,CM_Cle_Alerte,0) | D74: =INDEX(CM_Code_Magasin,C74) | E74: =INDEX(CM_Ville,C74) | F74: =INDEX(CM_Region,C74) | G74: =INDEX(CM_CA_Net_N,C74) | H74: =INDEX(CM_Taux_Marge_N,C74) | I74: =(H74-D_Taux_Reseau)*100
A75: 6 | B75: =SMALL(CM_Cle_Alerte,A75) | C75: =MATCH(B75,CM_Cle_Alerte,0) | D75: =INDEX(CM_Code_Magasin,C75) | E75: =INDEX(CM_Ville,C75) | F75: =INDEX(CM_Region,C75) | G75: =INDEX(CM_CA_Net_N,C75) | H75: =INDEX(CM_Taux_Marge_N,C75) | I75: =(H75-D_Taux_Reseau)*100

Sheet CALC_FICHE
A1: CALC_FICHE — calculs de la fiche magasin
A3: Code | B3: =Mag_Selectionne
A4: Ligne_CALC | B4: =MATCH(Mag_Selectionne,CM_Code_Magasin,0)
A5: Ligne_REF | B5: =MATCH(Mag_Selectionne,M_Code,0)
A6: Valide | B6: =IF(ISNUMBER(B4),INDEX(M_Region,B5)=Region_Fiche,FALSE)
A8: Série mensuelle du magasin (graphique)
A9: Mois | B9: Libellé | C9: CA net (k€) | D9: Coût matière | E9: Taux de marge (%) | F9: Index | G9: Taux (régression)
A10: =EDATE(Debut_Exercice,0) | B10: =CHOOSE(MONTH(A10),"janv","févr","mars","avr","mai","juin","juil","août","sept","oct","nov","déc") | C10: =SUMIFS(V_CANet,V_Mag,Mag_Selectionne,V_Mois,A10)/1000 | D10: =SUMIFS(V_Cout,V_Mag,Mag_Selectionne,V_Mois,A10) | E10: =IF(C10>0,(1-D10/(C10*1000))*100,NA()) | F10: 1 | G10: =IF(ISNUMBER(E10),E10,"")
A11: =EDATE(Debut_Exercice,1) | B11: =CHOOSE(MONTH(A11),"janv","févr","mars","avr","mai","juin","juil","août","sept","oct","nov","déc") | C11: =SUMIFS(V_CANet,V_Mag,Mag_Selectionne,V_Mois,A11)/1000 | D11: =SUMIFS(V_Cout,V_Mag,Mag_Selectionne,V_Mois,A11) | E11: =IF(C11>0,(1-D11/(C11*1000))*100,NA()) | F11: 2 | G11: =IF(ISNUMBER(E11),E11,"")
A12: =EDATE(Debut_Exercice,2) | B12: =CHOOSE(MONTH(A12),"janv","févr","mars","avr","mai","juin","juil","août","sept","oct","nov","déc") | C12: =SUMIFS(V_CANet,V_Mag,Mag_Selectionne,V_Mois,A12)/1000 | D12: =SUMIFS(V_Cout,V_Mag,Mag_Selectionne,V_Mois,A12) | E12: =IF(C12>0,(1-D12/(C12*1000))*100,NA()) | F12: 3 | G12: =IF(ISNUMBER(E12),E12,"")
A13: =EDATE(Debut_Exercice,3) | B13: =CHOOSE(MONTH(A13),"janv","févr","mars","avr","mai","juin","juil","août","sept","oct","nov","déc") | C13: =SUMIFS(V_CANet,V_Mag,Mag_Selectionne,V_Mois,A13)/1000 | D13: =SUMIFS(V_Cout,V_Mag,Mag_Selectionne,V_Mois,A13) | E13: =IF(C13>0,(1-D13/(C13*1000))*100,NA()) | F13: 4 | G13: =IF(ISNUMBER(E13),E13,"")
A14: =EDATE(Debut_Exercice,4) | B14: =CHOOSE(MONTH(A14),"janv","févr","mars","avr","mai","juin","juil","août","sept","oct","nov","déc") | C14: =SUMIFS(V_CANet,V_Mag,Mag_Selectionne,V_Mois,A14)/1000 | D14: =SUMIFS(V_Cout,V_Mag,Mag_Selectionne,V_Mois,A14) | E14: =IF(C14>0,(1-D14/(C14*1000))*100,NA()) | F14: 5 | G14: =IF(ISNUMBER(E14),E14,"")
A15: =EDATE(Debut_Exercice,5) | B15: =CHOOSE(MONTH(A15),"janv","févr","mars","avr","mai","juin","juil","août","sept","oct","nov","déc") | C15: =SUMIFS(V_CANet,V_Mag,Mag_Selectionne,V_Mois,A15)/1000 | D15: =SUMIFS(V_Cout,V_Mag,Mag_Selectionne,V_Mois,A15) | E15: =IF(C15>0,(1-D15/(C15*1000))*100,NA()) | F15: 6 | G15: =IF(ISNUMBER(E15),E15,"")
A16: =EDATE(Debut_Exercice,6) | B16: =CHOOSE(MONTH(A16),"janv","févr","mars","avr","mai","juin","juil","août","sept","oct","nov","déc") | C16: =SUMIFS(V_CANet,V_Mag,Mag_Selectionne,V_Mois,A16)/1000 | D16: =SUMIFS(V_Cout,V_Mag,Mag_Selectionne,V_Mois,A16) | E16: =IF(C16>0,(1-D16/(C16*1000))*100,NA()) | F16: 7 | G16: =IF(ISNUMBER(E16),E16,"")
A17: =EDATE(Debut_Exercice,7) | B17: =CHOOSE(MONTH(A17),"janv","févr","mars","avr","mai","juin","juil","août","sept","oct","nov","déc") | C17: =SUMIFS(V_CANet,V_Mag,Mag_Selectionne,V_Mois,A17)/1000 | D17: =SUMIFS(V_Cout,V_Mag,Mag_Selectionne,V_Mois,A17) | E17: =IF(C17>0,(1-D17/(C17*1000))*100,NA()) | F17: 8 | G17: =IF(ISNUMBER(E17),E17,"")
A18: =EDATE(Debut_Exercice,8) | B18: =CHOOSE(MONTH(A18),"janv","févr","mars","avr","mai","juin","juil","août","sept","oct","nov","déc") | C18: =SUMIFS(V_CANet,V_Mag,Mag_Selectionne,V_Mois,A18)/1000 | D18: =SUMIFS(V_Cout,V_Mag,Mag_Selectionne,V_Mois,A18) | E18: =IF(C18>0,(1-D18/(C18*1000))*100,NA()) | F18: 9 | G18: =IF(ISNUMBER(E18),E18,"")
A19: =EDATE(Debut_Exercice,9) | B19: =CHOOSE(MONTH(A19),"janv","févr","mars","avr","mai","juin","juil","août","sept","oct","nov","déc") | C19: =SUMIFS(V_CANet,V_Mag,Mag_Selectionne,V_Mois,A19)/1000 | D19: =SUMIFS(V_Cout,V_Mag,Mag_Selectionne,V_Mois,A19) | E19: =IF(C19>0,(1-D19/(C19*1000))*100,NA()) | F19: 10 | G19: =IF(ISNUMBER(E19),E19,"")
A20: =EDATE(Debut_Exercice,10) | B20: =CHOOSE(MONTH(A20),"janv","févr","mars","avr","mai","juin","juil","août","sept","oct","nov","déc") | C20: =SUMIFS(V_CANet,V_Mag,Mag_Selectionne,V_Mois,A20)/1000 | D20: =SUMIFS(V_Cout,V_Mag,Mag_Selectionne,V_Mois,A20) | E20: =IF(C20>0,(1-D20/(C20*1000))*100,NA()) | F20: 11 | G20: =IF(ISNUMBER(E20),E20,"")
A21: =EDATE(Debut_Exercice,11) | B21: =CHOOSE(MONTH(A21),"janv","févr","mars","avr","mai","juin","juil","août","sept","oct","nov","déc") | C21: =SUMIFS(V_CANet,V_Mag,Mag_Selectionne,V_Mois,A21)/1000 | D21: =SUMIFS(V_Cout,V_Mag,Mag_Selectionne,V_Mois,A21) | E21: =IF(C21>0,(1-D21/(C21*1000))*100,NA()) | F21: 12 | G21: =IF(ISNUMBER(E21),E21,"")
A23: Pente du taux de marge (pt/mois) | B23: =IFERROR(SLOPE(G10:G21,F10:F21),"") | C23: Régression linéaire sur les mois avec activité (NA() en colonne E pour que le graphique laisse un trou).
A26: Produits du magasin sur l'exercice
A27: Code_Produit | B27: Libellé | C27: Catégorie | D27: CA net | E27: Coût matière | F27: Taux de marge | G27: Clé tri CA
A28: =REF_PRODUITS!A2 | B28: =REF_PRODUITS!B2 | C28: =REF_PRODUITS!C2 | D28: =SUMIFS(X_CA,X_Mag,Mag_Selectionne,X_Ex,Exercice_Courant,X_Prod,A28) | E28: =SUMIFS(X_Cout,X_Mag,Mag_Selectionne,X_Ex,Exercice_Courant,X_Prod,A28) | F28: =IF(D28>0,1-E28/D28,"") | G28: =IF(D28>0,D28+ROW()/10^6,-1)
A29: =REF_PRODUITS!A3 | B29: =REF_PRODUITS!B3 | C29: =REF_PRODUITS!C3 | D29: =SUMIFS(X_CA,X_Mag,Mag_Selectionne,X_Ex,Exercice_Courant,X_Prod,A29) | E29: =SUMIFS(X_Cout,X_Mag,Mag_Selectionne,X_Ex,Exercice_Courant,X_Prod,A29) | F29: =IF(D29>0,1-E29/D29,"") | G29: =IF(D29>0,D29+ROW()/10^6,-1)
A30: =REF_PRODUITS!A4 | B30: =REF_PRODUITS!B4 | C30: =REF_PRODUITS!C4 | D30: =SUMIFS(X_CA,X_Mag,Mag_Selectionne,X_Ex,Exercice_Courant,X_Prod,A30) | E30: =SUMIFS(X_Cout,X_Mag,Mag_Selectionne,X_Ex,Exercice_Courant,X_Prod,A30) | F30: =IF(D30>0,1-E30/D30,"") | G30: =IF(D30>0,D30+ROW()/10^6,-1)
A31: =REF_PRODUITS!A5 | B31: =REF_PRODUITS!B5 | C31: =REF_PRODUITS!C5 | D31: =SUMIFS(X_CA,X_Mag,Mag_Selectionne,X_Ex,Exercice_Courant,X_Prod,A31) | E31: =SUMIFS(X_Cout,X_Mag,Mag_Selectionne,X_Ex,Exercice_Courant,X_Prod,A31) | F31: =IF(D31>0,1-E31/D31,"") | G31: =IF(D31>0,D31+ROW()/10^6,-1)
A32: =REF_PRODUITS!A6 | B32: =REF_PRODUITS!B6 | C32: =REF_PRODUITS!C6 | D32: =SUMIFS(X_CA,X_Mag,Mag_Selectionne,X_Ex,Exercice_Courant,X_Prod,A32) | E32: =SUMIFS(X_Cout,X_Mag,Mag_Selectionne,X_Ex,Exercice_Courant,X_Prod,A32) | F32: =IF(D32>0,1-E32/D32,"") | G32: =IF(D32>0,D32+ROW()/10^6,-1)
A33: =REF_PRODUITS!A7 | B33: =REF_PRODUITS!B7 | C33: =REF_PRODUITS!C7 | D33: =SUMIFS(X_CA,X_Mag,Mag_Selectionne,X_Ex,Exercice_Courant,X_Prod,A33) | E33: =SUMIFS(X_Cout,X_Mag,Mag_Selectionne,X_Ex,Exercice_Courant,X_Prod,A33) | F33: =IF(D33>0,1-E33/D33,"") | G33: =IF(D33>0,D33+ROW()/10^6,-1)
A34: =REF_PRODUITS!A8 | B34: =REF_PRODUITS!B8 | C34: =REF_PRODUITS!C8 | D34: =SUMIFS(X_CA,X_Mag,Mag_Selectionne,X_Ex,Exercice_Courant,X_Prod,A34) | E34: =SUMIFS(X_Cout,X_Mag,Mag_Selectionne,X_Ex,Exercice_Courant,X_Prod,A34) | F34: =IF(D34>0,1-E34/D34,"") | G34: =IF(D34>0,D34+ROW()/10^6,-1)
A35: =REF_PRODUITS!A9 | B35: =REF_PRODUITS!B9 | C35: =REF_PRODUITS!C9 | D35: =SUMIFS(X_CA,X_Mag,Mag_Selectionne,X_Ex,Exercice_Courant,X_Prod,A35) | E35: =SUMIFS(X_Cout,X_Mag,Mag_Selectionne,X_Ex,Exercice_Courant,X_Prod,A35) | F35: =IF(D35>0,1-E35/D35,"") | G35: =IF(D35>0,D35+ROW()/10^6,-1)
A36: =REF_PRODUITS!A10 | B36: =REF_PRODUITS!B10 | C36: =REF_PRODUITS!C10 | D36: =SUMIFS(X_CA,X_Mag,Mag_Selectionne,X_Ex,Exercice_Courant,X_Prod,A36) | E36: =SUMIFS(X_Cout,X_Mag,Mag_Selectionne,X_Ex,Exercice_Courant,X_Prod,A36) | F36: =IF(D36>0,1-E36/D36,"") | G36: =IF(D36>0,D36+ROW()/10^6,-1)
A37: =REF_PRODUITS!A11 | B37: =REF_PRODUITS!B11 | C37: =REF_PRODUITS!C11 | D37: =SUMIFS(X_CA,X_Mag,Mag_Selectionne,X_Ex,Exercice_Courant,X_Prod,A37) | E37: =SUMIFS(X_Cout,X_Mag,Mag_Selectionne,X_Ex,Exercice_Courant,X_Prod,A37) | F37: =IF(D37>0,1-E37/D37,"") | G37: =IF(D37>0,D37+ROW()/10^6,-1)
A38: =REF_PRODUITS!A12 | B38: =REF_PRODUITS!B12 | C38: =REF_PRODUITS!C12 | D38: =SUMIFS(X_CA,X_Mag,Mag_Selectionne,X_Ex,Exercice_Courant,X_Prod,A38) | E38: =SUMIFS(X_Cout,X_Mag,Mag_Selectionne,X_Ex,Exercice_Courant,X_Prod,A38) | F38: =IF(D38>0,1-E38/D38,"") | G38: =IF(D38>0,D38+ROW()/10^6,-1)
A39: =REF_PRODUITS!A13 | B39: =REF_PRODUITS!B13 | C39: =REF_PRODUITS!C13 | D39: =SUMIFS(X_CA,X_Mag,Mag_Selectionne,X_Ex,Exercice_Courant,X_Prod,A39) | E39: =SUMIFS(X_Cout,X_Mag,Mag_Selectionne,X_Ex,Exercice_Courant,X_Prod,A39) | F39: =IF(D39>0,1-E39/D39,"") | G39: =IF(D39>0,D39+ROW()/10^6,-1)
... A69: =REF_PRODUITS!A43 | B69: =REF_PRODUITS!B43 | C69: =REF_PRODUITS!C43 | D69: =SUMIFS(X_CA,X_Mag,Mag_Selectionne,X_Ex,Exercice_Courant,X_Prod,A69) | E69: =SUMIFS(X_Cout,X_Mag,Mag_Selectionne,X_Ex,Exercice_Courant,X_Prod,A69) | F69: =IF(D69>0,1-E69/D69,"") | G69: =IF(D69>0,D69+ROW()/10^6,-1)
A71: Top 6 produits par CA
A72: Rang | B72: Clé | C72: Ligne | D72: Libellé | E72: Catégorie | F72: CA net | G72: Taux de marge
A73: 1 | B73: =LARGE($G$28:$G$69,A73) | C73: =MATCH(B73,$G$28:$G$69,0) | D73: =INDEX($B$28:$B$69,C73) | E73: =INDEX($C$28:$C$69,C73) | F73: =INDEX($D$28:$D$69,C73) | G73: =INDEX($F$28:$F$69,C73)
A74: 2 | B74: =LARGE($G$28:$G$69,A74) | C74: =MATCH(B74,$G$28:$G$69,0) | D74: =INDEX($B$28:$B$69,C74) | E74: =INDEX($C$28:$C$69,C74) | F74: =INDEX($D$28:$D$69,C74) | G74: =INDEX($F$28:$F$69,C74)
A75: 3 | B75: =LARGE($G$28:$G$69,A75) | C75: =MATCH(B75,$G$28:$G$69,0) | D75: =INDEX($B$28:$B$69,C75) | E75: =INDEX($C$28:$C$69,C75) | F75: =INDEX($D$28:$D$69,C75) | G75: =INDEX($F$28:$F$69,C75)
A76: 4 | B76: =LARGE($G$28:$G$69,A76) | C76: =MATCH(B76,$G$28:$G$69,0) | D76: =INDEX($B$28:$B$69,C76) | E76: =INDEX($C$28:$C$69,C76) | F76: =INDEX($D$28:$D$69,C76) | G76: =INDEX($F$28:$F$69,C76)
A77: 5 | B77: =LARGE($G$28:$G$69,A77) | C77: =MATCH(B77,$G$28:$G$69,0) | D77: =INDEX($B$28:$B$69,C77) | E77: =INDEX($C$28:$C$69,C77) | F77: =INDEX($D$28:$D$69,C77) | G77: =INDEX($F$28:$F$69,C77)
A78: 6 | B78: =LARGE($G$28:$G$69,A78) | C78: =MATCH(B78,$G$28:$G$69,0) | D78: =INDEX($B$28:$B$69,C78) | E78: =INDEX($C$28:$C$69,C78) | F78: =INDEX($D$28:$D$69,C78) | G78: =INDEX($F$28:$F$69,C78)

Sheet DATA_VENTES
A1: Mois | B1: Exercice | C1: Code_Magasin | D1: Region | E1: Canal | F1: Nb_Jours | G1: Nb_Tickets | H1: Nb_Articles | I1: CA_Brut_HT | J1: Remises_HT | K1: CA_Net_HT | L1: Cout_Matiere_HT
A2: 45536 | B2: 2024/25 | C2: HC-001 | D2: Île-de-France | E2: Livraison | F2: 30 | G2: 1299 | H2: 3370 | I2: 21356.08 | J2: 1265.21 | K2: 20090.87 | L2: 6281.32
A3: 45536 | B3: 2024/25 | C3: HC-001 | D3: Île-de-France | E3: Sur place | F3: 29 | G3: 5283 | H3: 13744 | I3: 67590.93 | J3: 1936.23 | K3: 65654.7 | L3: 19358.44
A4: 45536 | B4: 2024/25 | C4: HC-001 | D4: Île-de-France | E4: À emporter | F4: 29 | G4: 3808 | H4: 9641 | I4: 44681.72 | J4: 1071.08 | K4: 43610.64 | L4: 13006.4
A5: 45536 | B5: 2024/25 | C5: HC-002 | D5: Nord-Ouest | E5: Drive | F5: 30 | G5: 986 | H5: 2537 | I5: 13467.96 | J5: 371.12 | K5: 13096.84 | L5: 3942.6
A6: 45536 | B6: 2024/25 | C6: HC-002 | D6: Nord-Ouest | E6: Livraison | F6: 30 | G6: 712 | H6: 1828 | I6: 11514.36 | J6: 682.42 | K6: 10831.94 | L6: 3354.93
A7: 45536 | B7: 2024/25 | C7: HC-002 | D7: Nord-Ouest | E7: Sur place | F7: 30 | G7: 2570 | H7: 6557 | I7: 33263.33 | J7: 1193.98 | K7: 32069.35 | L7: 9549.61
A8: 45536 | B8: 2024/25 | C8: HC-002 | D8: Nord-Ouest | E8: À emporter | F8: 29 | G8: 1926 | H8: 4800 | I8: 22854.71 | J8: 689.36 | K8: 22165.35 | L8: 6633.06
A9: 45536 | B9: 2024/25 | C9: HC-003 | D9: Sud-Est | E9: Drive | F9: 30 | G9: 1103 | H9: 2763 | I9: 15163.47 | J9: 411.24 | K9: 14752.23 | L9: 4406.12
A10: 45536 | B10: 2024/25 | C10: HC-003 | D10: Sud-Est | E10: Livraison | F10: 30 | G10: 963 | H10: 2535 | I10: 15026.49 | J10: 772.76 | K10: 14253.73 | L10: 4364.66
A11: 45536 | B11: 2024/25 | C11: HC-003 | D11: Sud-Est | E11: Sur place | F11: 28 | G11: 2716 | H11: 7004 | I11: 34997.19 | J11: 1043.93 | K11: 33953.26 | L11: 10037.53
A12: 45536 | B12: 2024/25 | C12: HC-003 | D12: Sud-Est | E12: À emporter | F12: 30 | G12: 2149 | H12: 5378 | I12: 25530.7 | J12: 747.06 | K12: 24783.64 | L12: 7398.29
A13: 45536 | B13: 2024/25 | C13: HC-004 | D13: Sud-Ouest | E13: Drive | F13: 29 | G13: 1170 | H13: 2989 | I13: 15913.35 | J13: 505.85 | K13: 15407.5 | L13: 4590.1
... A9516: 46235 | B9516: 2025/26 | C9516: HC-120 | D9516: Sud-Ouest | E9516: À emporter | F9516: 31 | G9516: 1803 | H9516: 4603 | I9516: 22237.09 | J9516: 684.42 | K9516: 21552.67 | L9516: 6432.78

Sheet DATA_BUDGET
A1: Mois | B1: Exercice | C1: Code_Magasin | D1: Region | E1: Budget_CA_HT
A2: 45658 | B2: 2024/25 | C2: HC-001 | D2: Île-de-France | E2: 122948
A3: 45658 | B3: 2024/25 | C3: HC-002 | D3: Nord-Ouest | E3: 81481
A4: 45658 | B4: 2024/25 | C4: HC-003 | D4: Sud-Est | E4: 81846
A5: 45658 | B5: 2024/25 | C5: HC-004 | D5: Sud-Ouest | E5: 87104
A6: 45658 | B6: 2024/25 | C6: HC-005 | D6: Île-de-France | E6: 113950
A7: 45658 | B7: 2024/25 | C7: HC-006 | D7: Nord-Ouest | E7: 71516
A8: 45658 | B8: 2024/25 | C8: HC-007 | D8: Sud-Est | E8: 71248
A9: 45658 | B9: 2024/25 | C9: HC-008 | D9: Sud-Ouest | E9: 95746
A10: 45658 | B10: 2024/25 | C10: HC-009 | D10: Île-de-France | E10: 123497
A11: 45658 | B11: 2024/25 | C11: HC-010 | D11: Nord-Ouest | E11: 138067
A12: 45658 | B12: 2024/25 | C12: HC-011 | D12: Sud-Est | E12: 118882
A13: 45658 | B13: 2024/25 | C13: HC-012 | D13: Sud-Ouest | E13: 64186
... A2881: 46357 | B2881: 2026/27 | C2881: HC-120 | D2881: Sud-Ouest | E2881: 97503

Sheet DATA_STOCKS
A1: Mois | B1: Exercice | C1: Code_Magasin | D1: Sorties | E1: Pertes
A2: 45536 | B2: 2024/25 | C2: HC-001 | D2: 28807 | E2: 463
A3: 45536 | B3: 2024/25 | C3: HC-002 | D3: 17124 | E3: 292
A4: 45536 | B4: 2024/25 | C4: HC-003 | D4: 19259 | E4: 305
A5: 45536 | B5: 2024/25 | C5: HC-004 | D5: 21145 | E5: 301
A6: 45536 | B6: 2024/25 | C6: HC-005 | D6: 26071 | E6: 409
A7: 45536 | B7: 2024/25 | C7: HC-006 | D7: 16260 | E7: 280
A8: 45536 | B8: 2024/25 | C8: HC-007 | D8: 20467 | E8: 350
A9: 45536 | B9: 2024/25 | C9: HC-008 | D9: 21026 | E9: 345
A10: 45536 | B10: 2024/25 | C10: HC-009 | D10: 27699 | E10: 461
A11: 45536 | B11: 2024/25 | C11: HC-010 | D11: 31092 | E11: 503
A12: 45536 | B12: 2024/25 | C12: HC-011 | D12: 28213 | E12: 493
A13: 45536 | B13: 2024/25 | C13: HC-012 | D13: 13948 | E13: 475
... A2831: 46235 | B2831: 2025/26 | C2831: HC-120 | D2831: 18352 | E2831: 316

Sheet DATA_ACHATS
A1: Mois | B1: Exercice | C1: Code_Fournisseur | D1: Nb_Lignes | E1: Nb_Livrees | F1: Somme_Retard_Jours | G1: Nb_En_Retard | H1: Montant_HT
A2: 45536 | B2: 2024/25 | C2: F01 | D2: 271 | E2: 262 | F2: 39 | G2: 23 | H2: 299424.04
A3: 45536 | B3: 2024/25 | C3: F02 | D3: 510 | E3: 502 | F3: 72 | G3: 45 | H3: 528398.51
A4: 45536 | B4: 2024/25 | C4: F03 | D4: 270 | E4: 265 | F4: 38 | G4: 19 | H4: 376860.02
A5: 45536 | B5: 2024/25 | C5: F04 | D5: 208 | E5: 204 | F5: 24 | G5: 16 | H5: 151574.64
A6: 45536 | B6: 2024/25 | C6: F05 | D6: 298 | E6: 289 | F6: 6 | G6: 2 | H6: 356816.4
A7: 45536 | B7: 2024/25 | C7: F06 | D7: 250 | E7: 246 | F7: 15 | G7: 8 | H7: 64715.66
A8: 45536 | B8: 2024/25 | C8: F07 | D8: 572 | E8: 565 | F8: 231 | G8: 153 | H8: 338152.58
A9: 45536 | B9: 2024/25 | C9: F08 | D9: 228 | E9: 224 | F9: 120 | G9: 78 | H9: 58209.03
A10: 45536 | B10: 2024/25 | C10: F09 | D10: 168 | E10: 166 | F10: 24 | G10: 8 | H10: 124425.91
A11: 45536 | B11: 2024/25 | C11: F10 | D11: 36 | E11: 35 | F11: 2 | G11: 2 | H11: 12576.28
A12: 45536 | B12: 2024/25 | C12: F12 | D12: 232 | E12: 227 | F12: 16 | G12: 8 | H12: 157290.89
A13: 45536 | B13: 2024/25 | C13: F13 | D13: 533 | E13: 525 | F13: 91 | G13: 39 | H13: 312411.93
... A333: 46235 | B333: 2025/26 | C333: F15 | D333: 937 | E333: 914 | F333: 136 | G333: 76 | H333: 924585.16

Sheet DATA_ACHATS_MAG
A1: Exercice | B1: Code_Magasin | C1: Montant_Reel_HT | D1: Montant_Prix_Reseau_HT
A2: 2024/25 | B2: HC-001 | C2: 519516.87 | D2: 519503.93
A3: 2024/25 | B3: HC-002 | C3: 304055.95 | D3: 303117.89
A4: 2024/25 | B4: HC-003 | C4: 353675.03 | D4: 354160.55
A5: 2024/25 | B5: HC-004 | C5: 376179.49 | D5: 376459.76
A6: 2024/25 | B6: HC-005 | C6: 449233.76 | D6: 449816.96
A7: 2024/25 | B7: HC-006 | C7: 288234.11 | D7: 287810.38
A8: 2024/25 | B8: HC-007 | C8: 348067.14 | D8: 348104.79
A9: 2024/25 | B9: HC-008 | C9: 389539.08 | D9: 390198.77
A10: 2024/25 | B10: HC-009 | C10: 487738.07 | D10: 487645.56
A11: 2024/25 | B11: HC-010 | C11: 555782.49 | D11: 555466.94
A12: 2024/25 | B12: HC-011 | C12: 495957.68 | D12: 494642.43
A13: 2024/25 | B13: HC-012 | C13: 245673.6 | D13: 246169.54
... A239: 2025/26 | B239: HC-120 | C239: 318716.64 | D239: 317858.22

Sheet DATA_RH
A1: Mois | B1: Exercice | C1: Code_Magasin | D1: Nb_Salaries | E1: Heures_Travaillees | F1: Heures_Sup | G1: Jours_Absence
A2: 45536 | B2: 2024/25 | C2: HC-001 | D2: 20 | E2: 2798.04 | F2: 130.78 | G2: 12.3
A3: 45536 | B3: 2024/25 | C3: HC-002 | D3: 13 | E3: 1818.18 | F3: 109.6 | G3: 6.5
A4: 45536 | B4: 2024/25 | C4: HC-003 | D4: 13 | E4: 1830.75 | F4: 62.29 | G4: 8.6
A5: 45536 | B5: 2024/25 | C5: HC-004 | D5: 14 | E5: 1957.02 | F5: 65.93 | G5: 16
A6: 45536 | B6: 2024/25 | C6: HC-005 | D6: 18 | E6: 2513.44 | F6: 132.25 | G6: 10.8
A7: 45536 | B7: 2024/25 | C7: HC-006 | D7: 12 | E7: 1716.7 | F7: 105.07 | G7: 10.3
A8: 45536 | B8: 2024/25 | C8: HC-007 | D8: 13 | E8: 1830.54 | F8: 74.88 | G8: 7.2
A9: 45536 | B9: 2024/25 | C9: HC-008 | D9: 13 | E9: 1812.78 | F9: 68.66 | G9: 11.9
A10: 45536 | B10: 2024/25 | C10: HC-009 | D10: 19 | E10: 2697.08 | F10: 73.54 | G10: 7.9
A11: 45536 | B11: 2024/25 | C11: HC-010 | D11: 20 | E11: 2805.18 | F11: 118.93 | G11: 19.5
A12: 45536 | B12: 2024/25 | C12: HC-011 | D12: 20 | E12: 2789.64 | F12: 125.42 | G12: 15.2
A13: 45536 | B13: 2024/25 | C13: HC-012 | D13: 12 | E13: 1694.11 | F13: 62.93 | G13: 10.9
... A2831: 46235 | B2831: 2025/26 | C2831: HC-120 | D2831: 13 | E2831: 1773.61 | F2831: 70.06 | G2831: 9.1

Sheet DATA_MIX
A1: Exercice | B1: Code_Magasin | C1: Code_Produit | D1: Quantite | E1: CA_Net_HT | F1: Cout_Matiere_HT
A2: 2024/25 | B2: HC-001 | C2: P001 | D2: 6313 | E2: 56805.59 | F2: 19909.23
A3: 2024/25 | B3: HC-001 | C3: P002 | D3: 9069 | E3: 94814.17 | F3: 35243.42
A4: 2024/25 | B4: HC-001 | C4: P003 | D4: 12454 | E4: 83800.31 | F4: 27591.44
A5: 2024/25 | B5: HC-001 | C5: P004 | D5: 5213 | E5: 40754.61 | F5: 12986.79
A6: 2024/25 | B6: HC-001 | C6: P005 | D6: 11820 | E6: 88102.54 | F6: 27140.72
A7: 2024/25 | B7: HC-001 | C7: P006 | D7: 11431 | E7: 92489.01 | F7: 26523.6
A8: 2024/25 | B8: HC-001 | C8: P007 | D8: 10654 | E8: 80378.07 | F8: 21344.01
A9: 2024/25 | B9: HC-001 | C9: P008 | D9: 9291 | E9: 68409.39 | F9: 24704.37
A10: 2024/25 | B10: HC-001 | C10: P009 | D10: 4511 | E10: 57003.68 | F10: 23005.7
A11: 2024/25 | B11: HC-001 | C11: P010 | D11: 12237 | E11: 72304.66 | F11: 23037.82
A12: 2024/25 | B12: HC-001 | C12: P011 | D12: 11237 | E12: 32690.47 | F12: 7638.23
A13: 2024/25 | B13: HC-001 | C13: P012 | D13: 12916 | E13: 48137.34 | F13: 14314.77
... A9993: 2025/26 | B9993: HC-120 | C9993: P042 | D9993: 583 | E9993: 2432.22 | F9993: 602.03

Sheet REF_MAGASINS
A1: Code_Magasin | B1: Nom_Magasin | C1: Ville | D1: Region | E1: Type_Emplacement | F1: Statut | G1: Surface_m2 | H1: Nb_Places_Assises | I1: Drive | J1: Franchise_Responsable | K1: Date_Ouverture | L1: Date_Fermeture
A2: HC-002 | B2: Horizon_Contrat Lille Périphérie | C2: Lille | D2: Nord-Ouest | E2: Périphérie | F2: Franchise | G2: 277 | H2: 100 | I2: Oui | J2: Karim Dupuis | K2: 43240
A3: HC-006 | B3: Horizon_Contrat Rouen Centre-ville | C3: Rouen | D3: Nord-Ouest | E3: Centre-ville | F3: Succursale | G3: 116 | H3: 53 | I3: Non | J3: Aïcha Girard | K3: 44753
A4: HC-010 | B4: Horizon_Contrat Caen Gare | C4: Caen | D4: Nord-Ouest | E4: Gare / Aéroport | F4: Franchise | G4: 185 | H4: 71 | I4: Oui | J4: Claire Benali | K4: 45169
A5: HC-014 | B5: Horizon_Contrat Rennes Centre | C5: Rennes | D5: Nord-Ouest | E5: Centre commercial | F5: Franchise | G5: 360 | H5: 131 | I5: Non | J5: Émilie Moreau | K5: 44436
A6: HC-018 | B6: Horizon_Contrat Nantes Périphérie | C6: Nantes | D6: Nord-Ouest | E6: Périphérie | F6: Franchise | G6: 242 | H6: 84 | I6: Oui | J6: Amélie Aubert | K6: 45144
A7: HC-022 | B7: Horizon_Contrat Amiens Centre-ville | C7: Amiens | D7: Nord-Ouest | E7: Centre-ville | F7: Franchise | G7: 371 | H7: 140 | I7: Non | J7: Camille Leroy | K7: 43226
A8: HC-026 | B8: Horizon_Contrat Le Havre Périphérie | C8: Le Havre | D8: Nord-Ouest | E8: Périphérie | F8: Succursale | G8: 356 | H8: 162 | I8: Oui | J8: Laura Guérin | K8: 44972
A9: HC-030 | B9: Horizon_Contrat Brest Centre-ville | C9: Brest | D9: Nord-Ouest | E9: Centre-ville | F9: Franchise | G9: 270 | H9: 143 | I9: Non | J9: Manon Faure | K9: 43065
A10: HC-034 | B10: Horizon_Contrat Tourcoing Gare | C10: Tourcoing | D10: Nord-Ouest | E10: Gare / Aéroport | F10: Franchise | G10: 362 | H10: 135 | I10: Non | J10: Nadia Robin | K10: 43547
A11: HC-038 | B11: Horizon_Contrat Angers Périphérie | C11: Angers | D11: Nord-Ouest | E11: Périphérie | F11: Franchise | G11: 131 | H11: 62 | I11: Oui | J11: Léa Marchand | K11: 45113
A12: HC-042 | B12: Horizon_Contrat Lille Périphérie | C12: Lille | D12: Nord-Ouest | E12: Périphérie | F12: Franchise | G12: 367 | H12: 173 | I12: Oui | J12: Fatou Colin | K12: 43793
A13: HC-046 | B13: Horizon_Contrat Rouen Centre | C13: Rouen | D13: Nord-Ouest | E13: Centre commercial | F13: Succursale | G13: 239 | H13: 124 | I13: Non | J13: Sabrina Perrin | K13: 42902
... A46: HC-059 | B46: Horizon_Contrat Saint-Étienne Gare | C46: Saint-Étienne | D46: Sud-Est | E46: Gare / Aéroport | F46: Franchise | G46: 313 | H46: 142 | I46: Non | J46: Guillaume Da Silva | K46: 44244
A47: HC-063 | B47: Horizon_Contrat Toulon Gare | C47: Toulon | D47: Sud-Est | E47: Gare / Aéroport | F47: Franchise | G47: 333 | H47: 125 | I47: Non | J47: Julien Noël | K47: 43678 | L47: 46142
A48: HC-067 | B48: Horizon_Contrat Aix-en-Provence Centre-ville | C48: Aix-en-Provence | D48: Sud-Est | E48: Centre-ville | F48: Franchise | G48: 355 | H48: 160 | I48: Non | J48: Marc Chevalier | K48: 43870
A49: HC-071 | B49: Horizon_Contrat Dijon Périphérie | C49: Dijon | D49: Sud-Est | E49: Périphérie | F49: Succursale | G49: 121 | H49: 61 | I49: Oui | J49: Bruno Fontaine | K49: 45286
A50: HC-075 | B50: Horizon_Contrat Annecy Gare | C50: Annecy | D50: Sud-Est | E50: Gare / Aéroport | F50: Franchise | G50: 221 | H50: 101 | I50: Oui | J50: Hugo Traoré | K50: 42552
A51: HC-079 | B51: Horizon_Contrat Avignon Centre | C51: Avignon | D51: Sud-Est | E51: Centre commercial | F51: Franchise | G51: 346 | H51: 174 | I51: Oui | J51: Nicolas Rossi | K51: 44312
A52: HC-083 | B52: Horizon_Contrat Lyon Centre | C52: Lyon | D52: Sud-Est | E52: Centre commercial | F52: Franchise | G52: 306 | H52: 148 | I52: Non | J52: Mehdi Durand | K52: 42531
A53: HC-087 | B53: Horizon_Contrat Marseille Périphérie | C53: Marseille | D53: Sud-Est | E53: Périphérie | F53: Franchise | G53: 289 | H53: 153 | I53: Oui | J53: Franck Lefebvre | K53: 45093
A54: HC-091 | B54: Horizon_Contrat Nice Centre-ville | C54: Nice | D54: Sud-Est | E54: Centre-ville | F54: Succursale | G54: 268 | H54: 103 | I54: Non | J54: Sophie Bertrand | K54: 45180
A55: HC-095 | B55: Horizon_Contrat Grenoble Gare | C55: Grenoble | D55: Sud-Est | E55: Gare / Aéroport | F55: Franchise | G55: 131 | H55: 66 | I55: Oui | J55: Thomas Barbier | K55: 45971
A56: HC-099 | B56: Horizon_Contrat Saint-Étienne Gare | C56: Saint-Étienne | D56: Sud-Est | E56: Gare / Aéroport | F56: Franchise | G56: 218 | H56: 78 | I56: Non | J56: Youssef Muller | K56: 43706
A57: HC-103 | B57: Horizon_Contrat Toulon Centre | C57: Toulon | D57: Sud-Est | E57: Centre commercial | F57: Franchise | G57: 242 | H57: 108 | I57: Non | J57: Antoine Blanc | K57: 44169
A58: HC-107 | B58: Horizon_Contrat Aix-en-Provence Centre-ville | C58: Aix-en-Provence | D58: Sud-Est | E58: Centre-ville | F58: Franchise | G58: 369 | H58: 131 | I58: Non | J58: Pierre Nguyen | K58: 43351
A59: HC-111 | B59: Horizon_Contrat Dijon Centre | C59: Dijon | D59: Sud-Est | E59: Centre commercial | F59: Succursale | G59: 169 | H59: 81 | I59: Non | J59: David Gauthier | K59: 44341
... A121: HC-117 | B121: Horizon_Contrat Évry-Courcouronnes Périphérie | C121: Évry-Courcouronnes | D121: Île-de-France | E121: Périphérie | F121: Franchise | G121: 338 | H121: 119 | I121: Oui | J121: Franck Lefebvre | K121: 43061

Sheet REF_PRODUITS
A1: Code_Produit | B1: Libelle_Produit | C1: Categorie | D1: Sous_Categorie | E1: Taux_TVA | F1: Taux_Cout_Matiere | G1: Prix_Vente_TTC_Actuel | H1: Actif
A2: P001 | B2: Burger Signature Horizon | C2: Burgers | D2: Boeuf | E2: 0.1 | F2: 0.33 | G2: 10.35 | H2: Oui
A3: P002 | B3: Double Contrat Beef | C3: Burgers | D3: Boeuf | E3: 0.1 | F3: 0.35 | G3: 12.02 | H3: Oui
A4: P003 | B4: Burger Classique | C4: Burgers | D4: Boeuf | E4: 0.1 | F4: 0.31 | G4: 7.73 | H4: Oui
A5: P004 | B5: Burger Poulet Croustillant | C5: Burgers | D5: Volaille | E5: 0.1 | F5: 0.3 | G5: 8.99 | H5: Oui
A6: P005 | B6: Burger Poulet Grillé | C6: Burgers | D6: Volaille | E6: 0.1 | F6: 0.29 | G6: 8.57 | H6: Oui
A7: P006 | B7: Burger Veggie Halloumi | C7: Burgers | D7: Végétarien | E7: 0.1 | F7: 0.27 | G7: 9.3 | H7: Oui
A8: P007 | B8: Burger Veggie Falafel | C8: Burgers | D8: Végétarien | E8: 0.1 | F8: 0.25 | G8: 8.67 | H8: Oui
A9: P008 | B9: Burger Fish | C9: Burgers | D9: Poisson | E9: 0.1 | F9: 0.34 | G9: 8.46 | H9: Oui
A10: P009 | B10: Burger Truffe Édition | C10: Burgers | D10: Premium | E10: 0.1 | F10: 0.38 | G10: 14.53 | H10: Non
A11: P010 | B11: Mini Burger Duo | C11: Burgers | D11: Boeuf | E11: 0.1 | F11: 0.3 | G11: 6.79 | H11: Oui
A12: P011 | B12: Frites Maison | C12: Accompagnements | D12: Frites | E12: 0.1 | F12: 0.22 | G12: 3.34 | H12: Oui
A13: P012 | B13: Frites Patate Douce | C13: Accompagnements | D13: Frites | E13: 0.1 | F13: 0.28 | G13: 4.28 | H13: Oui
... A43: P042 | B43: Chocolat Chaud Viennois | C43: Offres Saisonnières | D43: Hiver | E43: 0.1 | F43: 0.23 | G43: 4.6 | H43: Oui

Sheet REF_FOURNISSEURS
A1: Code_Fournisseur | B1: Nom_Fournisseur | C1: Categorie_Approvisionnee | D1: Delai_Livraison_Contractuel_Jours | E1: Conditions_Paiement | F1: Note_Qualite
A2: F01 | B2: Boucherie Centrale Rungis | C2: Viandes | D2: 2 | E2: 30 jours fin de mois | F2: 4.6
A3: F02 | B3: Volailles du Gâtinais | C3: Volailles | D3: 3 | E3: 45 jours | F3: 4.2
A4: F03 | B4: Marée Atlantique | C4: Poissons | D4: 2 | E4: 30 jours | F4: 3.9
A5: F04 | B5: Primeurs Val de Loire | C5: Fruits & Légumes | D5: 1 | E5: Comptant | F5: 4.4
A6: F05 | B6: Boulangerie Industrielle Artois | C6: Pains & Buns | D6: 2 | E6: 30 jours | F6: 4.1
A7: F06 | B7: Fromagerie des Monts | C7: Produits laitiers | D7: 3 | E7: 45 jours | F7: 4.5
A8: F07 | B8: Distri-Boissons France | C8: Boissons | D8: 4 | E8: 60 jours | F8: 3.4
A9: F08 | B9: Sucré Salé Desserts | C9: Desserts | D9: 5 | E9: 45 jours | F9: 3.1
A10: F09 | B10: Pomme de Terre du Nord | C10: Féculents | D10: 2 | E10: 30 jours | F10: 4.7
A11: F10 | B11: Épices & Sauces Méditerranée | C11: Épicerie | D11: 6 | E11: 30 jours | F11: 4
A12: F11 | B12: Emballages Verts Solutions | C12: Emballages | D12: 7 | E12: 60 jours | F12: 4.3
A13: F12 | B13: Bio Légumes Occitanie | C13: Fruits & Légumes | D13: 2 | E13: Comptant | F13: 4.8
... A16: F15 | B16: Grossiste Horizon Approvisionnement | C16: Multi-catégories | D16: 3 | E16: 30 jours fin de mois | F16: 3.7
